Workbook

Sheet Dashboard
B2: PromptHalo — SOC 2 Common Criteria Gap Assessment
B3: 160 controls across CC1–CC9 · Version 2.0 · August 5, 2026 · Internal · Every figure on this tab is calculated — change a Score on any Controls tab and this updates.
B5: READINESS AT A GLANCE
B6: Controls in scope | C6: =COUNTIF('CC1 Controls'!$B$5:$B$39,"<>")+COUNTIF('CC2 Controls'!$B$5:$B$24,"<>")+COUNTIF('CC3 Controls'!$B$5:$B$28,"<>")+COUNTIF('CC4 Controls'!$B$5:$B$19,"<>")+COUNTIF('CC5 Controls'!$B$5:$B$19,"<>")+COUNTIF('CC6 Controls'!$B$5:$B$44,"<>")+COUNTIF('CC7 Controls'!$B$5:$B$30,"<>")+COUNTIF('CC8 Controls'!$B$5:$B$12,"<>")+COUNTIF('CC9 Controls'!$B$5:$B$16,"<>") -> 160 | D6: Every row on the nine Controls tabs.
B7: Applicable (N/A excluded) | C7: =((COUNTIF('CC1 Controls'!$B$5:$B$39,"<>")+COUNTIF('CC2 Controls'!$B$5:$B$24,"<>")+COUNTIF('CC3 Controls'!$B$5:$B$28,"<>")+COUNTIF('CC4 Controls'!$B$5:$B$19,"<>")+COUNTIF('CC5 Controls'!$B$5:$B$19,"<>")+COUNTIF('CC6 Controls'!$B$5:$B$44,"<>")+COUNTIF('CC7 Controls'!$B$5:$B$30,"<>")+COUNTIF('CC8 Controls'!$B$5:$B$12,"<>")+COUNTIF('CC9 Controls'!$B$5:$B$16,"<>")) - (COUNTIFS('CC1 Controls'!$B$5:$B$39,"<>",'CC1 Controls'!$J$5:$J$39,"N/A")+COUNTIFS('CC2 Controls'!$B$5:$B$24,"<>",'CC2 Controls'!$J$5:$J$24,"N/A")+COUNTIFS('CC3 Controls'!$B$5:$B$28,"<>",'CC3 Controls'!$J$5:$J$28,"N/A")+COUNTIFS('CC4 Controls'!$B$5:$B$19,"<>",'CC4 Controls'!$J$5:$J$19,"N/A")+COUNTIFS('CC5 Controls'!$B$5:$B$19,"<>",'CC5 Controls'!$J$5:$J$19,"N/A")+COUNTIFS('CC6 Controls'!$B$5:$B$44,"<>",'CC6 Controls'!$J$5:$J$44,"N/A")+COUNTIFS('CC7 Controls'!$B$5:$B$30,"<>",'CC7 Controls'!$J$5:$J$30,"N/A")+COUNTIFS('CC8 Controls'!$B$5:$B$12,"<>",'CC8 Controls'!$J$5:$J$12,"N/A")+COUNTIFS('CC9 Controls'!$B$5:$B$16,"<>",'CC9 Controls'!$J$5:$J$16,"N/A"))) -> 159 | D7: N/A rows are excluded from both the score and the maximum.
B8: Assessed | C8: =COUNTIFS('CC1 Controls'!$B$5:$B$39,"<>",'CC1 Controls'!$J$5:$J$39,">=0")+COUNTIFS('CC2 Controls'!$B$5:$B$24,"<>",'CC2 Controls'!$J$5:$J$24,">=0")+COUNTIFS('CC3 Controls'!$B$5:$B$28,"<>",'CC3 Controls'!$J$5:$J$28,">=0")+COUNTIFS('CC4 Controls'!$B$5:$B$19,"<>",'CC4 Controls'!$J$5:$J$19,">=0")+COUNTIFS('CC5 Controls'!$B$5:$B$19,"<>",'CC5 Controls'!$J$5:$J$19,">=0")+COUNTIFS('CC6 Controls'!$B$5:$B$44,"<>",'CC6 Controls'!$J$5:$J$44,">=0")+COUNTIFS('CC7 Controls'!$B$5:$B$30,"<>",'CC7 Controls'!$J$5:$J$30,">=0")+COUNTIFS('CC8 Controls'!$B$5:$B$12,"<>",'CC8 Controls'!$J$5:$J$12,">=0")+COUNTIFS('CC9 Controls'!$B$5:$B$16,"<>",'CC9 Controls'!$J$5:$J$16,">=0") -> 159 | D8: A blank Score is not a zero — it is reported separately below.
B9: Not yet assessed | C9: =((COUNTIF('CC1 Controls'!$B$5:$B$39,"<>")+COUNTIF('CC2 Controls'!$B$5:$B$24,"<>")+COUNTIF('CC3 Controls'!$B$5:$B$28,"<>")+COUNTIF('CC4 Controls'!$B$5:$B$19,"<>")+COUNTIF('CC5 Controls'!$B$5:$B$19,"<>")+COUNTIF('CC6 Controls'!$B$5:$B$44,"<>")+COUNTIF('CC7 Controls'!$B$5:$B$30,"<>")+COUNTIF('CC8 Controls'!$B$5:$B$12,"<>")+COUNTIF('CC9 Controls'!$B$5:$B$16,"<>")) - (COUNTIFS('CC1 Controls'!$B$5:$B$39,"<>",'CC1 Controls'!$J$5:$J$39,">=0")+COUNTIFS('CC2 Controls'!$B$5:$B$24,"<>",'CC2 Controls'!$J$5:$J$24,">=0")+COUNTIFS('CC3 Controls'!$B$5:$B$28,"<>",'CC3 Controls'!$J$5:$J$28,">=0")+COUNTIFS('CC4 Controls'!$B$5:$B$19,"<>",'CC4 Controls'!$J$5:$J$19,">=0")+COUNTIFS('CC5 Controls'!$B$5:$B$19,"<>",'CC5 Controls'!$J$5:$J$19,">=0")+COUNTIFS('CC6 Controls'!$B$5:$B$44,"<>",'CC6 Controls'!$J$5:$J$44,">=0")+COUNTIFS('CC7 Controls'!$B$5:$B$30,"<>",'CC7 Controls'!$J$5:$J$30,">=0")+COUNTIFS('CC8 Controls'!$B$5:$B$12,"<>",'CC8 Controls'!$J$5:$J$12,">=0")+COUNTIFS('CC9 Controls'!$B$5:$B$16,"<>",'CC9 Controls'!$J$5:$J$16,">=0"))) -> 1 | D9: Score these before relying on the readiness figure.
B10: Readiness | C10: =IFERROR((SUMIFS('CC1 Controls'!$J$5:$J$39,'CC1 Controls'!$B$5:$B$39,"<>")+SUMIFS('CC2 Controls'!$J$5:$J$24,'CC2 Controls'!$B$5:$B$24,"<>")+SUMIFS('CC3 Controls'!$J$5:$J$28,'CC3 Controls'!$B$5:$B$28,"<>")+SUMIFS('CC4 Controls'!$J$5:$J$19,'CC4 Controls'!$B$5:$B$19,"<>")+SUMIFS('CC5 Controls'!$J$5:$J$19,'CC5 Controls'!$B$5:$B$19,"<>")+SUMIFS('CC6 Controls'!$J$5:$J$44,'CC6 Controls'!$B$5:$B$44,"<>")+SUMIFS('CC7 Controls'!$J$5:$J$30,'CC7 Controls'!$B$5:$B$30,"<>")+SUMIFS('CC8 Controls'!$J$5:$J$12,'CC8 Controls'!$B$5:$B$12,"<>")+SUMIFS('CC9 Controls'!$J$5:$J$16,'CC9 Controls'!$B$5:$B$16,"<>"))/(((COUNTIF('CC1 Controls'!$B$5:$B$39,"<>")+COUNTIF('CC2 Controls'!$B$5:$B$24,"<>")+COUNTIF('CC3 Controls'!$B$5:$B$28,"<>")+COUNTIF('CC4 Controls'!$B$5:$B$19,"<>")+COUNTIF('CC5 Controls'!$B$5:$B$19,"<>")+COUNTIF('CC6 Controls'!$B$5:$B$44,"<>")+COUNTIF('CC7 Controls'!$B$5:$B$30,"<>")+COUNTIF('CC8 Controls'!$B$5:$B$12,"<>")+COUNTIF('CC9 Controls'!$B$5:$B$16,"<>")) - (COUNTIFS('CC1 Controls'!$B$5:$B$39,"<>",'CC1 Controls'!$J$5:$J$39,"N/A")+COUNTIFS('CC2 Controls'!$B$5:$B$24,"<>",'CC2 Controls'!$J$5:$J$24,"N/A")+COUNTIFS('CC3 Controls'!$B$5:$B$28,"<>",'CC3 Controls'!$J$5:$J$28,"N/A")+COUNTIFS('CC4 Controls'!$B$5:$B$19,"<>",'CC4 Controls'!$J$5:$J$19,"N/A")+COUNTIFS('CC5 Controls'!$B$5:$B$19,"<>",'CC5 Controls'!$J$5:$J$19,"N/A")+COUNTIFS('CC6 Controls'!$B$5:$B$44,"<>",'CC6 Controls'!$J$5:$J$44,"N/A")+COUNTIFS('CC7 Controls'!$B$5:$B$30,"<>",'CC7 Controls'!$J$5:$J$30,"N/A")+COUNTIFS('CC8 Controls'!$B$5:$B$12,"<>",'CC8 Controls'!$J$5:$J$12,"N/A")+COUNTIFS('CC9 Controls'!$B$5:$B$16,"<>",'CC9 Controls'!$J$5:$J$16,"N/A")))*4),0) -> 0.21855346 | D10: =REPT("|",ROUND(C10*100,0)) -> |||||||||||||||||||||| | E10: =TEXT(C10,"0.0%")&" of the maximum achievable score" -> 21.9% of the maximum achievable score
B11: Average level | C11: =IFERROR((SUMIFS('CC1 Controls'!$J$5:$J$39,'CC1 Controls'!$B$5:$B$39,"<>")+SUMIFS('CC2 Controls'!$J$5:$J$24,'CC2 Controls'!$B$5:$B$24,"<>")+SUMIFS('CC3 Controls'!$J$5:$J$28,'CC3 Controls'!$B$5:$B$28,"<>")+SUMIFS('CC4 Controls'!$J$5:$J$19,'CC4 Controls'!$B$5:$B$19,"<>")+SUMIFS('CC5 Controls'!$J$5:$J$19,'CC5 Controls'!$B$5:$B$19,"<>")+SUMIFS('CC6 Controls'!$J$5:$J$44,'CC6 Controls'!$B$5:$B$44,"<>")+SUMIFS('CC7 Controls'!$J$5:$J$30,'CC7 Controls'!$B$5:$B$30,"<>")+SUMIFS('CC8 Controls'!$J$5:$J$12,'CC8 Controls'!$B$5:$B$12,"<>")+SUMIFS('CC9 Controls'!$J$5:$J$16,'CC9 Controls'!$B$5:$B$16,"<>"))/(COUNTIFS('CC1 Controls'!$B$5:$B$39,"<>",'CC1 Controls'!$J$5:$J$39,">=0")+COUNTIFS('CC2 Controls'!$B$5:$B$24,"<>",'CC2 Controls'!$J$5:$J$24,">=0")+COUNTIFS('CC3 Controls'!$B$5:$B$28,"<>",'CC3 Controls'!$J$5:$J$28,">=0")+COUNTIFS('CC4 Controls'!$B$5:$B$19,"<>",'CC4 Controls'!$J$5:$J$19,">=0")+COUNTIFS('CC5 Controls'!$B$5:$B$19,"<>",'CC5 Controls'!$J$5:$J$19,">=0")+COUNTIFS('CC6 Controls'!$B$5:$B$44,"<>",'CC6 Controls'!$J$5:$J$44,">=0")+COUNTIFS('CC7 Controls'!$B$5:$B$30,"<>",'CC7 Controls'!$J$5:$J$30,">=0")+COUNTIFS('CC8 Controls'!$B$5:$B$12,"<>",'CC8 Controls'!$J$5:$J$12,">=0")+COUNTIFS('CC9 Controls'!$B$5:$B$16,"<>",'CC9 Controls'!$J$5:$J$16,">=0")),0) -> 0.87421384 | D11: Mean of the assessed rows only.
B12: Short of Type I (below level 2) | C12: =COUNTIFS('CC1 Controls'!$B$5:$B$39,"<>",'CC1 Controls'!$J$5:$J$39,"<2")+COUNTIFS('CC2 Controls'!$B$5:$B$24,"<>",'CC2 Controls'!$J$5:$J$24,"<2")+COUNTIFS('CC3 Controls'!$B$5:$B$28,"<>",'CC3 Controls'!$J$5:$J$28,"<2")+COUNTIFS('CC4 Controls'!$B$5:$B$19,"<>",'CC4 Controls'!$J$5:$J$19,"<2")+COUNTIFS('CC5 Controls'!$B$5:$B$19,"<>",'CC5 Controls'!$J$5:$J$19,"<2")+COUNTIFS('CC6 Controls'!$B$5:$B$44,"<>",'CC6 Controls'!$J$5:$J$44,"<2")+COUNTIFS('CC7 Controls'!$B$5:$B$30,"<>",'CC7 Controls'!$J$5:$J$30,"<2")+COUNTIFS('CC8 Controls'!$B$5:$B$12,"<>",'CC8 Controls'!$J$5:$J$12,"<2")+COUNTIFS('CC9 Controls'!$B$5:$B$16,"<>",'CC9 Controls'!$J$5:$J$16,"<2") -> 158 | D12: Design deficiencies. Each one fails a Type I.
B13: Short of Type II (below level 3) | C13: =COUNTIFS('CC1 Controls'!$B$5:$B$39,"<>",'CC1 Controls'!$J$5:$J$39,"<3")+COUNTIFS('CC2 Controls'!$B$5:$B$24,"<>",'CC2 Controls'!$J$5:$J$24,"<3")+COUNTIFS('CC3 Controls'!$B$5:$B$28,"<>",'CC3 Controls'!$J$5:$J$28,"<3")+COUNTIFS('CC4 Controls'!$B$5:$B$19,"<>",'CC4 Controls'!$J$5:$J$19,"<3")+COUNTIFS('CC5 Controls'!$B$5:$B$19,"<>",'CC5 Controls'!$J$5:$J$19,"<3")+COUNTIFS('CC6 Controls'!$B$5:$B$44,"<>",'CC6 Controls'!$J$5:$J$44,"<3")+COUNTIFS('CC7 Controls'!$B$5:$B$30,"<>",'CC7 Controls'!$J$5:$J$30,"<3")+COUNTIFS('CC8 Controls'!$B$5:$B$12,"<>",'CC8 Controls'!$J$5:$J$12,"<3")+COUNTIFS('CC9 Controls'!$B$5:$B$16,"<>",'CC9 Controls'!$J$5:$J$16,"<3") -> 159 | D13: Operating without retained evidence. Each one fails a Type II sample.
B15: SCORE DISTRIBUTION
B16: Level | C16: Controls | D16: Share | E16: Distribution
B17: 0 — Gap | C17: =COUNTIFS('CC1 Controls'!$B$5:$B$39,"<>",'CC1 Controls'!$J$5:$J$39,0)+COUNTIFS('CC2 Controls'!$B$5:$B$24,"<>",'CC2 Controls'!$J$5:$J$24,0)+COUNTIFS('CC3 Controls'!$B$5:$B$28,"<>",'CC3 Controls'!$J$5:$J$28,0)+COUNTIFS('CC4 Controls'!$B$5:$B$19,"<>",'CC4 Controls'!$J$5:$J$19,0)+COUNTIFS('CC5 Controls'!$B$5:$B$19,"<>",'CC5 Controls'!$J$5:$J$19,0)+COUNTIFS('CC6 Controls'!$B$5:$B$44,"<>",'CC6 Controls'!$J$5:$J$44,0)+COUNTIFS('CC7 Controls'!$B$5:$B$30,"<>",'CC7 Controls'!$J$5:$J$30,0)+COUNTIFS('CC8 Controls'!$B$5:$B$12,"<>",'CC8 Controls'!$J$5:$J$12,0)+COUNTIFS('CC9 Controls'!$B$5:$B$16,"<>",'CC9 Controls'!$J$5:$J$16,0) -> 21 | D17: =IFERROR(C17/$C$6,0) -> 0.13125 | E17: =REPT("|",ROUND(C17/$C$6*60,0)) -> ||||||||
B18: 1 — Documented | C18: =COUNTIFS('CC1 Controls'!$B$5:$B$39,"<>",'CC1 Controls'!$J$5:$J$39,1)+COUNTIFS('CC2 Controls'!$B$5:$B$24,"<>",'CC2 Controls'!$J$5:$J$24,1)+COUNTIFS('CC3 Controls'!$B$5:$B$28,"<>",'CC3 Controls'!$J$5:$J$28,1)+COUNTIFS('CC4 Controls'!$B$5:$B$19,"<>",'CC4 Controls'!$J$5:$J$19,1)+COUNTIFS('CC5 Controls'!$B$5:$B$19,"<>",'CC5 Controls'!$J$5:$J$19,1)+COUNTIFS('CC6 Controls'!$B$5:$B$44,"<>",'CC6 Controls'!$J$5:$J$44,1)+COUNTIFS('CC7 Controls'!$B$5:$B$30,"<>",'CC7 Controls'!$J$5:$J$30,1)+COUNTIFS('CC8 Controls'!$B$5:$B$12,"<>",'CC8 Controls'!$J$5:$J$12,1)+COUNTIFS('CC9 Controls'!$B$5:$B$16,"<>",'CC9 Controls'!$J$5:$J$16,1) -> 137 | D18: =IFERROR(C18/$C$6,0) -> 0.85625 | E18: =REPT("|",ROUND(C18/$C$6*60,0)) -> |||||||||||||||||||||||||||||||||||||||||||||||||||
B19: 2 — Implemented | C19: =COUNTIFS('CC1 Controls'!$B$5:$B$39,"<>",'CC1 Controls'!$J$5:$J$39,2)+COUNTIFS('CC2 Controls'!$B$5:$B$24,"<>",'CC2 Controls'!$J$5:$J$24,2)+COUNTIFS('CC3 Controls'!$B$5:$B$28,"<>",'CC3 Controls'!$J$5:$J$28,2)+COUNTIFS('CC4 Controls'!$B$5:$B$19,"<>",'CC4 Controls'!$J$5:$J$19,2)+COUNTIFS('CC5 Controls'!$B$5:$B$19,"<>",'CC5 Controls'!$J$5:$J$19,2)+COUNTIFS('CC6 Controls'!$B$5:$B$44,"<>",'CC6 Controls'!$J$5:$J$44,2)+COUNTIFS('CC7 Controls'!$B$5:$B$30,"<>",'CC7 Controls'!$J$5:$J$30,2)+COUNTIFS('CC8 Controls'!$B$5:$B$12,"<>",'CC8 Controls'!$J$5:$J$12,2)+COUNTIFS('CC9 Controls'!$B$5:$B$16,"<>",'CC9 Controls'!$J$5:$J$16,2) -> 1 | D19: =IFERROR(C19/$C$6,0) -> 0.00625 | E19: =REPT("|",ROUND(C19/$C$6*60,0))
B20: 3 — Evidenced | C20: =COUNTIFS('CC1 Controls'!$B$5:$B$39,"<>",'CC1 Controls'!$J$5:$J$39,3)+COUNTIFS('CC2 Controls'!$B$5:$B$24,"<>",'CC2 Controls'!$J$5:$J$24,3)+COUNTIFS('CC3 Controls'!$B$5:$B$28,"<>",'CC3 Controls'!$J$5:$J$28,3)+COUNTIFS('CC4 Controls'!$B$5:$B$19,"<>",'CC4 Controls'!$J$5:$J$19,3)+COUNTIFS('CC5 Controls'!$B$5:$B$19,"<>",'CC5 Controls'!$J$5:$J$19,3)+COUNTIFS('CC6 Controls'!$B$5:$B$44,"<>",'CC6 Controls'!$J$5:$J$44,3)+COUNTIFS('CC7 Controls'!$B$5:$B$30,"<>",'CC7 Controls'!$J$5:$J$30,3)+COUNTIFS('CC8 Controls'!$B$5:$B$12,"<>",'CC8 Controls'!$J$5:$J$12,3)+COUNTIFS('CC9 Controls'!$B$5:$B$16,"<>",'CC9 Controls'!$J$5:$J$16,3) -> 0 | D20: =IFERROR(C20/$C$6,0) -> 0 | E20: =REPT("|",ROUND(C20/$C$6*60,0))
B21: 4 — Automated | C21: =COUNTIFS('CC1 Controls'!$B$5:$B$39,"<>",'CC1 Controls'!$J$5:$J$39,4)+COUNTIFS('CC2 Controls'!$B$5:$B$24,"<>",'CC2 Controls'!$J$5:$J$24,4)+COUNTIFS('CC3 Controls'!$B$5:$B$28,"<>",'CC3 Controls'!$J$5:$J$28,4)+COUNTIFS('CC4 Controls'!$B$5:$B$19,"<>",'CC4 Controls'!$J$5:$J$19,4)+COUNTIFS('CC5 Controls'!$B$5:$B$19,"<>",'CC5 Controls'!$J$5:$J$19,4)+COUNTIFS('CC6 Controls'!$B$5:$B$44,"<>",'CC6 Controls'!$J$5:$J$44,4)+COUNTIFS('CC7 Controls'!$B$5:$B$30,"<>",'CC7 Controls'!$J$5:$J$30,4)+COUNTIFS('CC8 Controls'!$B$5:$B$12,"<>",'CC8 Controls'!$J$5:$J$12,4)+COUNTIFS('CC9 Controls'!$B$5:$B$16,"<>",'CC9 Controls'!$J$5:$J$16,4) -> 0 | D21: =IFERROR(C21/$C$6,0) -> 0 | E21: =REPT("|",ROUND(C21/$C$6*60,0))
B22: N/A — Not applicable | C22: =COUNTIFS('CC1 Controls'!$B$5:$B$39,"<>",'CC1 Controls'!$J$5:$J$39,"N/A")+COUNTIFS('CC2 Controls'!$B$5:$B$24,"<>",'CC2 Controls'!$J$5:$J$24,"N/A")+COUNTIFS('CC3 Controls'!$B$5:$B$28,"<>",'CC3 Controls'!$J$5:$J$28,"N/A")+COUNTIFS('CC4 Controls'!$B$5:$B$19,"<>",'CC4 Controls'!$J$5:$J$19,"N/A")+COUNTIFS('CC5 Controls'!$B$5:$B$19,"<>",'CC5 Controls'!$J$5:$J$19,"N/A")+COUNTIFS('CC6 Controls'!$B$5:$B$44,"<>",'CC6 Controls'!$J$5:$J$44,"N/A")+COUNTIFS('CC7 Controls'!$B$5:$B$30,"<>",'CC7 Controls'!$J$5:$J$30,"N/A")+COUNTIFS('CC8 Controls'!$B$5:$B$12,"<>",'CC8 Controls'!$J$5:$J$12,"N/A")+COUNTIFS('CC9 Controls'!$B$5:$B$16,"<>",'CC9 Controls'!$J$5:$J$16,"N/A") -> 1 | D22: =IFERROR(C22/$C$6,0) -> 0.00625 | E22: =REPT("|",ROUND(C22/$C$6*60,0))
B24: BY CRITERION
B25: Criterion | C25: Controls | D25: Assessed | E25: Average level | F25: At level 0 | G25: Below level 3 | H25: Policy: Yes | I25: Partial | J25: No
B26: CC1 Control Environment | C26: =COUNTIF('CC1 Controls'!$B$5:$B$39,"<>") -> 28 | D26: =COUNTIFS('CC1 Controls'!$B$5:$B$39,"<>",'CC1 Controls'!$J$5:$J$39,">=0") -> 27 | E26: =IFERROR(SUMIFS('CC1 Controls'!$J$5:$J$39,'CC1 Controls'!$B$5:$B$39,"<>")/COUNTIFS('CC1 Controls'!$B$5:$B$39,"<>",'CC1 Controls'!$J$5:$J$39,">=0"),0) -> 0.55555556 | F26: =COUNTIFS('CC1 Controls'!$B$5:$B$39,"<>",'CC1 Controls'!$J$5:$J$39,0) -> 13 | G26: =COUNTIFS('CC1 Controls'!$B$5:$B$39,"<>",'CC1 Controls'!$J$5:$J$39,"<3") -> 27 | H26: =COUNTIFS('CC1 Controls'!$B$5:$B$39,"<>",'CC1 Controls'!$O$5:$O$39,"Yes") -> 9 | I26: =COUNTIFS('CC1 Controls'!$B$5:$B$39,"<>",'CC1 Controls'!$O$5:$O$39,"Partial") -> 10 | J26: =COUNTIFS('CC1 Controls'!$B$5:$B$39,"<>",'CC1 Controls'!$O$5:$O$39,"No") -> 9
B27: CC2 Communication and Information | C27: =COUNTIF('CC2 Controls'!$B$5:$B$24,"<>") -> 17 | D27: =COUNTIFS('CC2 Controls'!$B$5:$B$24,"<>",'CC2 Controls'!$J$5:$J$24,">=0") -> 17 | E27: =IFERROR(SUMIFS('CC2 Controls'!$J$5:$J$24,'CC2 Controls'!$B$5:$B$24,"<>")/COUNTIFS('CC2 Controls'!$B$5:$B$24,"<>",'CC2 Controls'!$J$5:$J$24,">=0"),0) -> 0.70588235 | F27: =COUNTIFS('CC2 Controls'!$B$5:$B$24,"<>",'CC2 Controls'!$J$5:$J$24,0) -> 5 | G27: =COUNTIFS('CC2 Controls'!$B$5:$B$24,"<>",'CC2 Controls'!$J$5:$J$24,"<3") -> 17 | H27: =COUNTIFS('CC2 Controls'!$B$5:$B$24,"<>",'CC2 Controls'!$O$5:$O$24,"Yes") -> 10 | I27: =COUNTIFS('CC2 Controls'!$B$5:$B$24,"<>",'CC2 Controls'!$O$5:$O$24,"Partial") -> 4 | J27: =COUNTIFS('CC2 Controls'!$B$5:$B$24,"<>",'CC2 Controls'!$O$5:$O$24,"No") -> 3
B28: CC3 Risk Assessment | C28: =COUNTIF('CC3 Controls'!$B$5:$B$28,"<>") -> 20 | D28: =COUNTIFS('CC3 Controls'!$B$5:$B$28,"<>",'CC3 Controls'!$J$5:$J$28,">=0") -> 20 | E28: =IFERROR(SUMIFS('CC3 Controls'!$J$5:$J$28,'CC3 Controls'!$B$5:$B$28,"<>")/COUNTIFS('CC3 Controls'!$B$5:$B$28,"<>",'CC3 Controls'!$J$5:$J$28,">=0"),0) -> 0.9 | F28: =COUNTIFS('CC3 Controls'!$B$5:$B$28,"<>",'CC3 Controls'!$J$5:$J$28,0) -> 2 | G28: =COUNTIFS('CC3 Controls'!$B$5:$B$28,"<>",'CC3 Controls'!$J$5:$J$28,"<3") -> 20 | H28: =COUNTIFS('CC3 Controls'!$B$5:$B$28,"<>",'CC3 Controls'!$O$5:$O$28,"Yes") -> 14 | I28: =COUNTIFS('CC3 Controls'!$B$5:$B$28,"<>",'CC3 Controls'!$O$5:$O$28,"Partial") -> 4 | J28: =COUNTIFS('CC3 Controls'!$B$5:$B$28,"<>",'CC3 Controls'!$O$5:$O$28,"No") -> 2
B29: CC4 Monitoring Activities | C29: =COUNTIF('CC4 Controls'!$B$5:$B$19,"<>") -> 13 | D29: =COUNTIFS('CC4 Controls'!$B$5:$B$19,"<>",'CC4 Controls'!$J$5:$J$19,">=0") -> 13 | E29: =IFERROR(SUMIFS('CC4 Controls'!$J$5:$J$19,'CC4 Controls'!$B$5:$B$19,"<>")/COUNTIFS('CC4 Controls'!$B$5:$B$19,"<>",'CC4 Controls'!$J$5:$J$19,">=0"),0) -> 1 | F29: =COUNTIFS('CC4 Controls'!$B$5:$B$19,"<>",'CC4 Controls'!$J$5:$J$19,0) -> 0 | G29: =COUNTIFS('CC4 Controls'!$B$5:$B$19,"<>",'CC4 Controls'!$J$5:$J$19,"<3") -> 13 | H29: =COUNTIFS('CC4 Controls'!$B$5:$B$19,"<>",'CC4 Controls'!$O$5:$O$19,"Yes") -> 9 | I29: =COUNTIFS('CC4 Controls'!$B$5:$B$19,"<>",'CC4 Controls'!$O$5:$O$19,"Partial") -> 4 | J29: =COUNTIFS('CC4 Controls'!$B$5:$B$19,"<>",'CC4 Controls'!$O$5:$O$19,"No") -> 0
B30: CC5 Control Activities | C30: =COUNTIF('CC5 Controls'!$B$5:$B$19,"<>") -> 12 | D30: =COUNTIFS('CC5 Controls'!$B$5:$B$19,"<>",'CC5 Controls'!$J$5:$J$19,">=0") -> 12 | E30: =IFERROR(SUMIFS('CC5 Controls'!$J$5:$J$19,'CC5 Controls'!$B$5:$B$19,"<>")/COUNTIFS('CC5 Controls'!$B$5:$B$19,"<>",'CC5 Controls'!$J$5:$J$19,">=0"),0) -> 1 | F30: =COUNTIFS('CC5 Controls'!$B$5:$B$19,"<>",'CC5 Controls'!$J$5:$J$19,0) -> 0 | G30: =COUNTIFS('CC5 Controls'!$B$5:$B$19,"<>",'CC5 Controls'!$J$5:$J$19,"<3") -> 12 | H30: =COUNTIFS('CC5 Controls'!$B$5:$B$19,"<>",'CC5 Controls'!$O$5:$O$19,"Yes") -> 10 | I30: =COUNTIFS('CC5 Controls'!$B$5:$B$19,"<>",'CC5 Controls'!$O$5:$O$19,"Partial") -> 2 | J30: =COUNTIFS('CC5 Controls'!$B$5:$B$19,"<>",'CC5 Controls'!$O$5:$O$19,"No") -> 0
B31: CC6 Logical and Physical Access | C31: =COUNTIF('CC6 Controls'!$B$5:$B$44,"<>") -> 32 | D31: =COUNTIFS('CC6 Controls'!$B$5:$B$44,"<>",'CC6 Controls'!$J$5:$J$44,">=0") -> 32 | E31: =IFERROR(SUMIFS('CC6 Controls'!$J$5:$J$44,'CC6 Controls'!$B$5:$B$44,"<>")/COUNTIFS('CC6 Controls'!$B$5:$B$44,"<>",'CC6 Controls'!$J$5:$J$44,">=0"),0) -> 0.96875 | F31: =COUNTIFS('CC6 Controls'!$B$5:$B$44,"<>",'CC6 Controls'!$J$5:$J$44,0) -> 1 | G31: =COUNTIFS('CC6 Controls'!$B$5:$B$44,"<>",'CC6 Controls'!$J$5:$J$44,"<3") -> 32 | H31: =COUNTIFS('CC6 Controls'!$B$5:$B$44,"<>",'CC6 Controls'!$O$5:$O$44,"Yes") -> 31 | I31: =COUNTIFS('CC6 Controls'!$B$5:$B$44,"<>",'CC6 Controls'!$O$5:$O$44,"Partial") -> 0 | J31: =COUNTIFS('CC6 Controls'!$B$5:$B$44,"<>",'CC6 Controls'!$O$5:$O$44,"No") -> 1
B32: CC7 System Operations | C32: =COUNTIF('CC7 Controls'!$B$5:$B$30,"<>") -> 21 | D32: =COUNTIFS('CC7 Controls'!$B$5:$B$30,"<>",'CC7 Controls'!$J$5:$J$30,">=0") -> 21 | E32: =IFERROR(SUMIFS('CC7 Controls'!$J$5:$J$30,'CC7 Controls'!$B$5:$B$30,"<>")/COUNTIFS('CC7 Controls'!$B$5:$B$30,"<>",'CC7 Controls'!$J$5:$J$30,">=0"),0) -> 1 | F32: =COUNTIFS('CC7 Controls'!$B$5:$B$30,"<>",'CC7 Controls'!$J$5:$J$30,0) -> 0 | G32: =COUNTIFS('CC7 Controls'!$B$5:$B$30,"<>",'CC7 Controls'!$J$5:$J$30,"<3") -> 21 | H32: =COUNTIFS('CC7 Controls'!$B$5:$B$30,"<>",'CC7 Controls'!$O$5:$O$30,"Yes") -> 19 | I32: =COUNTIFS('CC7 Controls'!$B$5:$B$30,"<>",'CC7 Controls'!$O$5:$O$30,"Partial") -> 2 | J32: =COUNTIFS('CC7 Controls'!$B$5:$B$30,"<>",'CC7 Controls'!$O$5:$O$30,"No") -> 0
B33: CC8 Change Management | C33: =COUNTIF('CC8 Controls'!$B$5:$B$12,"<>") -> 7 | D33: =COUNTIFS('CC8 Controls'!$B$5:$B$12,"<>",'CC8 Controls'!$J$5:$J$12,">=0") -> 7 | E33: =IFERROR(SUMIFS('CC8 Controls'!$J$5:$J$12,'CC8 Controls'!$B$5:$B$12,"<>")/COUNTIFS('CC8 Controls'!$B$5:$B$12,"<>",'CC8 Controls'!$J$5:$J$12,">=0"),0) -> 1 | F33: =COUNTIFS('CC8 Controls'!$B$5:$B$12,"<>",'CC8 Controls'!$J$5:$J$12,0) -> 0 | G33: =COUNTIFS('CC8 Controls'!$B$5:$B$12,"<>",'CC8 Controls'!$J$5:$J$12,"<3") -> 7 | H33: =COUNTIFS('CC8 Controls'!$B$5:$B$12,"<>",'CC8 Controls'!$O$5:$O$12,"Yes") -> 7 | I33: =COUNTIFS('CC8 Controls'!$B$5:$B$12,"<>",'CC8 Controls'!$O$5:$O$12,"Partial") -> 0 | J33: =COUNTIFS('CC8 Controls'!$B$5:$B$12,"<>",'CC8 Controls'!$O$5:$O$12,"No") -> 0
B34: CC9 Risk Mitigation | C34: =COUNTIF('CC9 Controls'!$B$5:$B$16,"<>") -> 10 | D34: =COUNTIFS('CC9 Controls'!$B$5:$B$16,"<>",'CC9 Controls'!$J$5:$J$16,">=0") -> 10 | E34: =IFERROR(SUMIFS('CC9 Controls'!$J$5:$J$16,'CC9 Controls'!$B$5:$B$16,"<>")/COUNTIFS('CC9 Controls'!$B$5:$B$16,"<>",'CC9 Controls'!$J$5:$J$16,">=0"),0) -> 1 | F34: =COUNTIFS('CC9 Controls'!$B$5:$B$16,"<>",'CC9 Controls'!$J$5:$J$16,0) -> 0 | G34: =COUNTIFS('CC9 Controls'!$B$5:$B$16,"<>",'CC9 Controls'!$J$5:$J$16,"<3") -> 10 | H34: =COUNTIFS('CC9 Controls'!$B$5:$B$16,"<>",'CC9 Controls'!$O$5:$O$16,"Yes") -> 9 | I34: =COUNTIFS('CC9 Controls'!$B$5:$B$16,"<>",'CC9 Controls'!$O$5:$O$16,"Partial") -> 1 | J34: =COUNTIFS('CC9 Controls'!$B$5:$B$16,"<>",'CC9 Controls'!$O$5:$O$16,"No") -> 0
B35: All nine criteria | C35: =COUNTIF('CC1 Controls'!$B$5:$B$39,"<>")+COUNTIF('CC2 Controls'!$B$5:$B$24,"<>")+COUNTIF('CC3 Controls'!$B$5:$B$28,"<>")+COUNTIF('CC4 Controls'!$B$5:$B$19,"<>")+COUNTIF('CC5 Controls'!$B$5:$B$19,"<>")+COUNTIF('CC6 Controls'!$B$5:$B$44,"<>")+COUNTIF('CC7 Controls'!$B$5:$B$30,"<>")+COUNTIF('CC8 Controls'!$B$5:$B$12,"<>")+COUNTIF('CC9 Controls'!$B$5:$B$16,"<>") -> 160 | D35: =COUNTIFS('CC1 Controls'!$B$5:$B$39,"<>",'CC1 Controls'!$J$5:$J$39,">=0")+COUNTIFS('CC2 Controls'!$B$5:$B$24,"<>",'CC2 Controls'!$J$5:$J$24,">=0")+COUNTIFS('CC3 Controls'!$B$5:$B$28,"<>",'CC3 Controls'!$J$5:$J$28,">=0")+COUNTIFS('CC4 Controls'!$B$5:$B$19,"<>",'CC4 Controls'!$J$5:$J$19,">=0")+COUNTIFS('CC5 Controls'!$B$5:$B$19,"<>",'CC5 Controls'!$J$5:$J$19,">=0")+COUNTIFS('CC6 Controls'!$B$5:$B$44,"<>",'CC6 Controls'!$J$5:$J$44,">=0")+COUNTIFS('CC7 Controls'!$B$5:$B$30,"<>",'CC7 Controls'!$J$5:$J$30,">=0")+COUNTIFS('CC8 Controls'!$B$5:$B$12,"<>",'CC8 Controls'!$J$5:$J$12,">=0")+COUNTIFS('CC9 Controls'!$B$5:$B$16,"<>",'CC9 Controls'!$J$5:$J$16,">=0") -> 159 | E35: =IFERROR((SUMIFS('CC1 Controls'!$J$5:$J$39,'CC1 Controls'!$B$5:$B$39,"<>")+SUMIFS('CC2 Controls'!$J$5:$J$24,'CC2 Controls'!$B$5:$B$24,"<>")+SUMIFS('CC3 Controls'!$J$5:$J$28,'CC3 Controls'!$B$5:$B$28,"<>")+SUMIFS('CC4 Controls'!$J$5:$J$19,'CC4 Controls'!$B$5:$B$19,"<>")+SUMIFS('CC5 Controls'!$J$5:$J$19,'CC5 Controls'!$B$5:$B$19,"<>")+SUMIFS('CC6 Controls'!$J$5:$J$44,'CC6 Controls'!$B$5:$B$44,"<>")+SUMIFS('CC7 Controls'!$J$5:$J$30,'CC7 Controls'!$B$5:$B$30,"<>")+SUMIFS('CC8 Controls'!$J$5:$J$12,'CC8 Controls'!$B$5:$B$12,"<>")+SUMIFS('CC9 Controls'!$J$5:$J$16,'CC9 Controls'!$B$5:$B$16,"<>"))/(COUNTIFS('CC1 Controls'!$B$5:$B$39,"<>",'CC1 Controls'!$J$5:$J$39,">=0")+COUNTIFS('CC2 Controls'!$B$5:$B$24,"<>",'CC2 Controls'!$J$5:$J$24,">=0")+COUNTIFS('CC3 Controls'!$B$5:$B$28,"<>",'CC3 Controls'!$J$5:$J$28,">=0")+COUNTIFS('CC4 Controls'!$B$5:$B$19,"<>",'CC4 Controls'!$J$5:$J$19,">=0")+COUNTIFS('CC5 Controls'!$B$5:$B$19,"<>",'CC5 Controls'!$J$5:$J$19,">=0")+COUNTIFS('CC6 Controls'!$B$5:$B$44,"<>",'CC6 Controls'!$J$5:$J$44,">=0")+COUNTIFS('CC7 Controls'!$B$5:$B$30,"<>",'CC7 Controls'!$J$5:$J$30,">=0")+COUNTIFS('CC8 Controls'!$B$5:$B$12,"<>",'CC8 Controls'!$J$5:$J$12,">=0")+COUNTIFS('CC9 Controls'!$B$5:$B$16,"<>",'CC9 Controls'!$J$5:$J$16,">=0")),0) -> 0.87421384 | F35: =COUNTIFS('CC1 Controls'!$B$5:$B$39,"<>",'CC1 Controls'!$J$5:$J$39,0)+COUNTIFS('CC2 Controls'!$B$5:$B$24,"<>",'CC2 Controls'!$J$5:$J$24,0)+COUNTIFS('CC3 Controls'!$B$5:$B$28,"<>",'CC3 Controls'!$J$5:$J$28,0)+COUNTIFS('CC4 Controls'!$B$5:$B$19,"<>",'CC4 Controls'!$J$5:$J$19,0)+COUNTIFS('CC5 Controls'!$B$5:$B$19,"<>",'CC5 Controls'!$J$5:$J$19,0)+COUNTIFS('CC6 Controls'!$B$5:$B$44,"<>",'CC6 Controls'!$J$5:$J$44,0)+COUNTIFS('CC7 Controls'!$B$5:$B$30,"<>",'CC7 Controls'!$J$5:$J$30,0)+COUNTIFS('CC8 Controls'!$B$5:$B$12,"<>",'CC8 Controls'!$J$5:$J$12,0)+COUNTIFS('CC9 Controls'!$B$5:$B$16,"<>",'CC9 Controls'!$J$5:$J$16,0) -> 21 | G35: =COUNTIFS('CC1 Controls'!$B$5:$B$39,"<>",'CC1 Controls'!$J$5:$J$39,"<3")+COUNTIFS('CC2 Controls'!$B$5:$B$24,"<>",'CC2 Controls'!$J$5:$J$24,"<3")+COUNTIFS('CC3 Controls'!$B$5:$B$28,"<>",'CC3 Controls'!$J$5:$J$28,"<3")+COUNTIFS('CC4 Controls'!$B$5:$B$19,"<>",'CC4 Controls'!$J$5:$J$19,"<3")+COUNTIFS('CC5 Controls'!$B$5:$B$19,"<>",'CC5 Controls'!$J$5:$J$19,"<3")+COUNTIFS('CC6 Controls'!$B$5:$B$44,"<>",'CC6 Controls'!$J$5:$J$44,"<3")+COUNTIFS('CC7 Controls'!$B$5:$B$30,"<>",'CC7 Controls'!$J$5:$J$30,"<3")+COUNTIFS('CC8 Controls'!$B$5:$B$12,"<>",'CC8 Controls'!$J$5:$J$12,"<3")+COUNTIFS('CC9 Controls'!$B$5:$B$16,"<>",'CC9 Controls'!$J$5:$J$16,"<3") -> 159 | H35: =COUNTIFS('CC1 Controls'!$B$5:$B$39,"<>",'CC1 Controls'!$O$5:$O$39,"Yes")+COUNTIFS('CC2 Controls'!$B$5:$B$24,"<>",'CC2 Controls'!$O$5:$O$24,"Yes")+COUNTIFS('CC3 Controls'!$B$5:$B$28,"<>",'CC3 Controls'!$O$5:$O$28,"Yes")+COUNTIFS('CC4 Controls'!$B$5:$B$19,"<>",'CC4 Controls'!$O$5:$O$19,"Yes")+COUNTIFS('CC5 Controls'!$B$5:$B$19,"<>",'CC5 Controls'!$O$5:$O$19,"Yes")+COUNTIFS('CC6 Controls'!$B$5:$B$44,"<>",'CC6 Controls'!$O$5:$O$44,"Yes")+COUNTIFS('CC7 Controls'!$B$5:$B$30,"<>",'CC7 Controls'!$O$5:$O$30,"Yes")+COUNTIFS('CC8 Controls'!$B$5:$B$12,"<>",'CC8 Controls'!$O$5:$O$12,"Yes")+COUNTIFS('CC9 Controls'!$B$5:$B$16,"<>",'CC9 Controls'!$O$5:$O$16,"Yes") -> 118 | I35: =COUNTIFS('CC1 Controls'!$B$5:$B$39,"<>",'CC1 Controls'!$O$5:$O$39,"Partial")+COUNTIFS('CC2 Controls'!$B$5:$B$24,"<>",'CC2 Controls'!$O$5:$O$24,"Partial")+COUNTIFS('CC3 Controls'!$B$5:$B$28,"<>",'CC3 Controls'!$O$5:$O$28,"Partial")+COUNTIFS('CC4 Controls'!$B$5:$B$19,"<>",'CC4 Controls'!$O$5:$O$19,"Partial")+COUNTIFS('CC5 Controls'!$B$5:$B$19,"<>",'CC5 Controls'!$O$5:$O$19,"Partial")+COUNTIFS('CC6 Controls'!$B$5:$B$44,"<>",'CC6 Controls'!$O$5:$O$44,"Partial")+COUNTIFS('CC7 Controls'!$B$5:$B$30,"<>",'CC7 Controls'!$O$5:$O$30,"Partial")+COUNTIFS('CC8 Controls'!$B$5:$B$12,"<>",'CC8 Controls'!$O$5:$O$12,"Partial")+COUNTIFS('CC9 Controls'!$B$5:$B$16,"<>",'CC9 Controls'!$O$5:$O$16,"Partial") -> 27 | J35: =COUNTIFS('CC1 Controls'!$B$5:$B$39,"<>",'CC1 Controls'!$O$5:$O$39,"No")+COUNTIFS('CC2 Controls'!$B$5:$B$24,"<>",'CC2 Controls'!$O$5:$O$24,"No")+COUNTIFS('CC3 Controls'!$B$5:$B$28,"<>",'CC3 Controls'!$O$5:$O$28,"No")+COUNTIFS('CC4 Controls'!$B$5:$B$19,"<>",'CC4 Controls'!$O$5:$O$19,"No")+COUNTIFS('CC5 Controls'!$B$5:$B$19,"<>",'CC5 Controls'!$O$5:$O$19,"No")+COUNTIFS('CC6 Controls'!$B$5:$B$44,"<>",'CC6 Controls'!$O$5:$O$44,"No")+COUNTIFS('CC7 Controls'!$B$5:$B$30,"<>",'CC7 Controls'!$O$5:$O$30,"No")+COUNTIFS('CC8 Controls'!$B$5:$B$12,"<>",'CC8 Controls'!$O$5:$O$12,"No")+COUNTIFS('CC9 Controls'!$B$5:$B$16,"<>",'CC9 Controls'!$O$5:$O$16,"No") -> 15
B38: OPEN GAPS — CONTROLS ASSESSED AT LEVEL 0 (21 of 160)
B39: Status is live: rescore the control on its tab and this column changes.
B40: Control | C40: Live status | D40: What is missing
B41: CC1.1-01 | C41: =IF('CC1 Controls'!J6=0,"Open",IF('CC1 Controls'!J6="","Not scored","Now level "&'CC1 Controls'!J6)) -> Open | D41: Code of Conduct (POL-COC-001) approved by the Steering Committee and published to all personnel.
B42: CC1.1-02 | C42: =IF('CC1 Controls'!J7=0,"Open",IF('CC1 Controls'!J7="","Not scored","Now level "&'CC1 Controls'!J7)) -> Open | D42: Every employee and contractor accepts the Code of Conduct at onboarding, on material revision, and annually.
B43: CC1.1-03 | C43: =IF('CC1 Controls'!J8=0,"Open",IF('CC1 Controls'!J8="","Not scored","Now level "&'CC1 Controls'!J8)) -> Open | D43: Conflict of interest declaration completed annually and whenever a new client engagement is accepted.
B44: CC1.1-04 | C44: =IF('CC1 Controls'!J9=0,"Open",IF('CC1 Controls'!J9="","Not scored","Now level "&'CC1 Controls'!J9)) -> Open | D44: Ethics reporting channel that bypasses the Security Officer, with anti-retaliation stated.
B45: CC1.1-05 | C45: =IF('CC1 Controls'!J10=0,"Open",IF('CC1 Controls'!J10="","Not scored","Now level "&'CC1 Controls'!J10)) -> Open | D45: Conduct deviations are documented with the finding, the decision and the rationale.
B46: CC1.2-06 | C46: =IF('CC1 Controls'!J19=0,"Open",IF('CC1 Controls'!J19="","Not scored","Now level "&'CC1 Controls'!J19)) -> Open | D46: Committee composition is reviewed as the Company grows and additional members are appointed when available.
B47: CC1.3-01 | C47: =IF('CC1 Controls'!J22=0,"Open",IF('CC1 Controls'!J22="","Not scored","Now level "&'CC1 Controls'!J22)) -> Open | D47: Current org chart showing reporting lines, including contractors and the fractional CISO.
B48: CC1.3-04 | C48: =IF('CC1 Controls'!J25=0,"Open",IF('CC1 Controls'!J25="","Not scored","Now level "&'CC1 Controls'!J25)) -> Open | D48: Delegated duties are documented with their scope and duration.
B49: CC1.3-05 | C49: =IF('CC1 Controls'!J26=0,"Open",IF('CC1 Controls'!J26="","Not scored","Now level "&'CC1 Controls'!J26)) -> Open | D49: Segregation of duties assessed; where not practicable, compensating controls are documented.
B50: CC1.4-01 | C50: =IF('CC1 Controls'!J28=0,"Open",IF('CC1 Controls'!J28="","Not scored","Now level "&'CC1 Controls'!J28)) -> Open | D50: Competency requirements, including required skills and certifications, defined per role.
B51: CC1.4-05 | C51: =IF('CC1 Controls'!J32=0,"Open",IF('CC1 Controls'!J32="","Not scored","Now level "&'CC1 Controls'!J32)) -> Open | D51: Remote working requirements — device standard, network, physical handling of screens and printouts — acknowledged.
B52: CC1.4-06 | C52: =IF('CC1 Controls'!J33=0,"Open",IF('CC1 Controls'!J33="","Not scored","Now level "&'CC1 Controls'!J33)) -> Open | D52: Contractors meet the same screening, training and acknowledgment requirements as employees.
B53: CC1.5-02 | C53: =IF('CC1 Controls'!J36=0,"Open",IF('CC1 Controls'!J36="","Not scored","Now level "&'CC1 Controls'!J36)) -> Open | D53: Performance review includes control and security responsibilities.
B54: CC2.2-01 | C54: =IF('CC2 Controls'!J12=0,"Open",IF('CC2 Controls'!J12="","Not scored","Now level "&'CC2 Controls'!J12)) -> Open | D54: Policies are published to the policy repository and personnel are notified on issue and on material change.
B55: CC2.2-05 | C55: =IF('CC2 Controls'!J16=0,"Open",IF('CC2 Controls'!J16="","Not scored","Now level "&'CC2 Controls'!J16)) -> Open | D55: A written quarterly report goes to the Steering Committee covering control status, open deficiencies with owners and dates, and the security metrics.
B56: CC2.2-06 | C56: =IF('CC2 Controls'!J17=0,"Open",IF('CC2 Controls'!J17="","Not scored","Now level "&'CC2 Controls'!J17)) -> Open | D56: Concerns about the conduct of the Security Officer, or which a person prefers not to raise with the Security Officer, may be reported directly to the CEO.
B57: CC2.3-01 | C57: =IF('CC2 Controls'!J19=0,"Open",IF('CC2 Controls'!J19="","Not scored","Now level "&'CC2 Controls'!J19)) -> Open | D57: Security, availability and confidentiality commitments made to customers are recorded in the customer agreement or DPA, and reviewed annually against the controls actually in operation.
B58: CC2.3-05 | C58: =IF('CC2 Controls'!J23=0,"Open",IF('CC2 Controls'!J23="","Not scored","Now level "&'CC2 Controls'!J23)) -> Open | D58: Security commitments to customers or prospective customers are reviewed by the Security Officer before they are made.
B59: CC3.1-03 | C59: =IF('CC3 Controls'!J8=0,"Open",IF('CC3 Controls'!J8="","Not scored","Now level "&'CC3 Controls'!J8)) -> Open | D59: Legal, regulatory and contractual security obligations are recorded in a single register and reviewed annually.
B60: CC3.1-05 | C60: =IF('CC3 Controls'!J10=0,"Open",IF('CC3 Controls'!J10="","Not scored","Now level "&'CC3 Controls'!J10)) -> Open | D60: Each objective is linked to the controls that deliver it, so a control failure traces to the objective it puts at risk.
B61: CC6.6-03 | C61: =IF('CC6 Controls'!J34=0,"Open",IF('CC6 Controls'!J34="","Not scored","Now level "&'CC6 Controls'!J34)) -> Open | D61: A current network diagram shows accounts, environments, public entry points and trust boundaries, and is maintained as the architecture changes.
B64: WHERE TO START
B65: One destination for deficiencies | D65: Five policies name five different homes for a deficiency — plan of action, deficiency log, risk register, finding population and incident corrective actions. Choose POL-ISP-001 §8 and amend the other four. Setup step 27.
B66: The two documents that do not exist | D66: POL-COI-001 and POL-PRIV-001 are referenced by CC1, CC2 and POL-ISP-001 Annex A and are not in the approved library. Until they exist or the references are corrected, Annex A cannot be reconciled.
B67: Refresh the tables of contents | D67: 21 of 27 documents carry a stale contents page — POL-VM-001 reads as Change Management. Every wrong cross-reference in this workbook traced back to that. A batch field refresh and reissue fixes it.
B68: Reconcile the incident role model | D68: POL-IRP-001 §6 assumes fifteen to twenty people and needs four incident roles. At current headcount it cannot be staffed. Name external parties or record the limitation. Setup step 40.
B69: Name the Security Officer alternate | D69: POL-BCP-001 §8 requires one with break-glass access. At two people it is the CEO. Writing it down costs nothing and closes the largest continuity exposure. Setup step 43.
B70: Then run the first assessment | D70: CC3 to CC9 are capped at level 1 because the policies are approved but nothing has operated yet. The first risk assessment, the first quarterly cycle and the first evidence set are what move 137 rows from Documented to Implemented.

Sheet Read Me
B2: PromptHalo — SOC 2 Common Criteria Control Plan (CC1–CC9)
B3: POL-ISP-001 supporting workbook · Version 2.1 · August 6, 2026 · Internal
B5: HOW TO USE THIS WORKBOOK
B6: Controls tabs | D6: Nine tabs in identical format covering the whole of the Common Criteria — 28 controls across CC1, 17 across CC2, 20 across CC3, 13 across CC4, 12 across CC5, 32 across CC6, 21 across CC7, 7 across CC8 and 10 across CC9, 160 in all — grouped so each criterion collapses to a single row. Use the outline buttons in the left margin. Fill in the shaded columns only: Owner, Score and Next due. On CC1 and CC2 columns O to Q assess the implementation plans; on CC3 to CC9 they assess the approved policy library, and the headers say which. The Dashboard tab summarises every figure below.
B7: Setup | D7: One-time Secureframe, Google Workspace, GitHub and AWS configuration, forty-four steps. Steps 1 to 13 switch on CC1; 14 to 20 cover CC2; 21 to 26 CC3; 27 to 30 CC4; 31 to 36 CC5 and CC6; 37 to 44 CC7, CC8 and CC9. From step 21 onward every step is written against a clause the approved policies already contain, so none of them asks you to rewrite policy you have.
B8: Governance Log | D8: The single log that satisfies CC1.2-02 (decisions recorded), CC1.3-04 (delegations), CC2.3-05 (commitments reviewed before they are made) and CC3.2-06 (risk acceptances). One line per decision, with the control reference so it traces back to a row on any controls tab.
B9: Calendar | D9: Seven scheduled events, six event-driven triggers, and one row for what runs continuously. All 160 controls appear at least once, so the Calendar is the coverage check: if these operate, the plan has operated for the year.
B11: THE SIMPLIFICATION
B12: Six artifacts | D12: 1. Policy repository (GitHub) 2. Acknowledgment register (Secureframe) 3. Governance Log (this workbook) 4. Onboarding checklist (Secureframe) 5. Control matrix (Secureframe) 6. Annual Assessment (signed Word document) 7. Risk register (Secureframe) 8. Annual risk assessment with fraud section (Word document) 9. Plan of action — the single deficiency population (Secureframe)
B13: Seven events | D13: Onboarding (per hire) · Monthly evaluation cycle · Quarterly evaluation cycle · Quarterly Committee report · Annual acknowledgment and training cycle · Annual risk assessment · Annual assessment and policy review. Plus four triggers that fire on an event rather than a date.
B14: Division of labour | D14: Secureframe owns anything involving a person: policy acceptance, training, screening, onboarding. GitHub owns anything that is a document: policy text, version history, approval trail. Nothing lives in email or in a local folder.
B16: THE ONE THING TO FIX
B17: CC1.2 independence | D17: With a CEO-only Steering Committee you cannot fully satisfy CC1.2. The ISP records this as a documented limitation with a compensating control, which is defensible. Recruiting one unpaid outside advisor to sign an annual oversight memo (CC1.2-05) converts a permanent scope limitation into a satisfied criterion for the cost of one meeting a year.
B21: GAP ASSESSMENT SCALE | D21: Score each control 0–4 in the Score column of its Controls tab. A Type I report needs every control at 2 or above; a Type II needs 3 or above, sustained across the observation period. CC3 to CC6 were scored from the approved policy library, which caps them at 1 until the controls are shown operating.
B23: N/A — Not applicable | D23: The control does not apply to the Company. Excluded from both the score and the maximum, so it does not distort readiness. Record the reason in the Governance Log — an auditor will ask why.
B24: 0 — Gap | D24: Nothing in place. The control is neither written down nor operating.
B25: 1 — Documented | D25: Written into an approved policy or procedure, but not yet operating in practice. Design only.
B26: 2 — Implemented | D26: Operating in practice, but evidence is not consistently produced or retained. Sufficient for a Type I; will fail a Type II sample.
B27: 3 — Evidenced | D27: Operating with dated evidence retained for every occurrence, sufficient for an auditor to sample across the observation period.
B28: 4 — Automated | D28: Evidence is produced and retained continuously by a system without manual effort, and drift is detected without anyone checking.
B30: Not scored | D30: Leave the Score cell blank until the control has been assessed. A blank is reported separately below and is not treated as a zero.
B32: SCORE SUMMARY
B33: Total controls | C33: =COUNTIF('CC1 Controls'!$B$5:$B$39,"<>")+COUNTIF('CC2 Controls'!$B$5:$B$24,"<>")+COUNTIF('CC3 Controls'!$B$5:$B$28,"<>")+COUNTIF('CC4 Controls'!$B$5:$B$19,"<>")+COUNTIF('CC5 Controls'!$B$5:$B$19,"<>")+COUNTIF('CC6 Controls'!$B$5:$B$44,"<>")+COUNTIF('CC7 Controls'!$B$5:$B$30,"<>")+COUNTIF('CC8 Controls'!$B$5:$B$12,"<>")+COUNTIF('CC9 Controls'!$B$5:$B$16,"<>") -> 160
B34: Not applicable | C34: =COUNTIFS('CC1 Controls'!$B$5:$B$39,"<>",'CC1 Controls'!$J$5:$J$39,"N/A")+COUNTIFS('CC2 Controls'!$B$5:$B$24,"<>",'CC2 Controls'!$J$5:$J$24,"N/A")+COUNTIFS('CC3 Controls'!$B$5:$B$28,"<>",'CC3 Controls'!$J$5:$J$28,"N/A")+COUNTIFS('CC4 Controls'!$B$5:$B$19,"<>",'CC4 Controls'!$J$5:$J$19,"N/A")+COUNTIFS('CC5 Controls'!$B$5:$B$19,"<>",'CC5 Controls'!$J$5:$J$19,"N/A")+COUNTIFS('CC6 Controls'!$B$5:$B$44,"<>",'CC6 Controls'!$J$5:$J$44,"N/A")+COUNTIFS('CC7 Controls'!$B$5:$B$30,"<>",'CC7 Controls'!$J$5:$J$30,"N/A")+COUNTIFS('CC8 Controls'!$B$5:$B$12,"<>",'CC8 Controls'!$J$5:$J$12,"N/A")+COUNTIFS('CC9 Controls'!$B$5:$B$16,"<>",'CC9 Controls'!$J$5:$J$16,"N/A") -> 1
B35: Applicable controls | C35: =((COUNTIF('CC1 Controls'!$B$5:$B$39,"<>")+COUNTIF('CC2 Controls'!$B$5:$B$24,"<>")+COUNTIF('CC3 Controls'!$B$5:$B$28,"<>")+COUNTIF('CC4 Controls'!$B$5:$B$19,"<>")+COUNTIF('CC5 Controls'!$B$5:$B$19,"<>")+COUNTIF('CC6 Controls'!$B$5:$B$44,"<>")+COUNTIF('CC7 Controls'!$B$5:$B$30,"<>")+COUNTIF('CC8 Controls'!$B$5:$B$12,"<>")+COUNTIF('CC9 Controls'!$B$5:$B$16,"<>")) - (COUNTIFS('CC1 Controls'!$B$5:$B$39,"<>",'CC1 Controls'!$J$5:$J$39,"N/A")+COUNTIFS('CC2 Controls'!$B$5:$B$24,"<>",'CC2 Controls'!$J$5:$J$24,"N/A")+COUNTIFS('CC3 Controls'!$B$5:$B$28,"<>",'CC3 Controls'!$J$5:$J$28,"N/A")+COUNTIFS('CC4 Controls'!$B$5:$B$19,"<>",'CC4 Controls'!$J$5:$J$19,"N/A")+COUNTIFS('CC5 Controls'!$B$5:$B$19,"<>",'CC5 Controls'!$J$5:$J$19,"N/A")+COUNTIFS('CC6 Controls'!$B$5:$B$44,"<>",'CC6 Controls'!$J$5:$J$44,"N/A")+COUNTIFS('CC7 Controls'!$B$5:$B$30,"<>",'CC7 Controls'!$J$5:$J$30,"N/A")+COUNTIFS('CC8 Controls'!$B$5:$B$12,"<>",'CC8 Controls'!$J$5:$J$12,"N/A")+COUNTIFS('CC9 Controls'!$B$5:$B$16,"<>",'CC9 Controls'!$J$5:$J$16,"N/A"))) -> 159
B36: Controls scored | C36: =COUNTIFS('CC1 Controls'!$B$5:$B$39,"<>",'CC1 Controls'!$J$5:$J$39,">=0")+COUNTIFS('CC2 Controls'!$B$5:$B$24,"<>",'CC2 Controls'!$J$5:$J$24,">=0")+COUNTIFS('CC3 Controls'!$B$5:$B$28,"<>",'CC3 Controls'!$J$5:$J$28,">=0")+COUNTIFS('CC4 Controls'!$B$5:$B$19,"<>",'CC4 Controls'!$J$5:$J$19,">=0")+COUNTIFS('CC5 Controls'!$B$5:$B$19,"<>",'CC5 Controls'!$J$5:$J$19,">=0")+COUNTIFS('CC6 Controls'!$B$5:$B$44,"<>",'CC6 Controls'!$J$5:$J$44,">=0")+COUNTIFS('CC7 Controls'!$B$5:$B$30,"<>",'CC7 Controls'!$J$5:$J$30,">=0")+COUNTIFS('CC8 Controls'!$B$5:$B$12,"<>",'CC8 Controls'!$J$5:$J$12,">=0")+COUNTIFS('CC9 Controls'!$B$5:$B$16,"<>",'CC9 Controls'!$J$5:$J$16,">=0") -> 159
B37: Not yet scored | C37: =((COUNTIF('CC1 Controls'!$B$5:$B$39,"<>")+COUNTIF('CC2 Controls'!$B$5:$B$24,"<>")+COUNTIF('CC3 Controls'!$B$5:$B$28,"<>")+COUNTIF('CC4 Controls'!$B$5:$B$19,"<>")+COUNTIF('CC5 Controls'!$B$5:$B$19,"<>")+COUNTIF('CC6 Controls'!$B$5:$B$44,"<>")+COUNTIF('CC7 Controls'!$B$5:$B$30,"<>")+COUNTIF('CC8 Controls'!$B$5:$B$12,"<>")+COUNTIF('CC9 Controls'!$B$5:$B$16,"<>")) - (COUNTIFS('CC1 Controls'!$B$5:$B$39,"<>",'CC1 Controls'!$J$5:$J$39,">=0")+COUNTIFS('CC2 Controls'!$B$5:$B$24,"<>",'CC2 Controls'!$J$5:$J$24,">=0")+COUNTIFS('CC3 Controls'!$B$5:$B$28,"<>",'CC3 Controls'!$J$5:$J$28,">=0")+COUNTIFS('CC4 Controls'!$B$5:$B$19,"<>",'CC4 Controls'!$J$5:$J$19,">=0")+COUNTIFS('CC5 Controls'!$B$5:$B$19,"<>",'CC5 Controls'!$J$5:$J$19,">=0")+COUNTIFS('CC6 Controls'!$B$5:$B$44,"<>",'CC6 Controls'!$J$5:$J$44,">=0")+COUNTIFS('CC7 Controls'!$B$5:$B$30,"<>",'CC7 Controls'!$J$5:$J$30,">=0")+COUNTIFS('CC8 Controls'!$B$5:$B$12,"<>",'CC8 Controls'!$J$5:$J$12,">=0")+COUNTIFS('CC9 Controls'!$B$5:$B$16,"<>",'CC9 Controls'!$J$5:$J$16,">=0"))) -> 1
B39: Total score | C39: =SUMIFS('CC1 Controls'!$J$5:$J$39,'CC1 Controls'!$B$5:$B$39,"<>")+SUMIFS('CC2 Controls'!$J$5:$J$24,'CC2 Controls'!$B$5:$B$24,"<>")+SUMIFS('CC3 Controls'!$J$5:$J$28,'CC3 Controls'!$B$5:$B$28,"<>")+SUMIFS('CC4 Controls'!$J$5:$J$19,'CC4 Controls'!$B$5:$B$19,"<>")+SUMIFS('CC5 Controls'!$J$5:$J$19,'CC5 Controls'!$B$5:$B$19,"<>")+SUMIFS('CC6 Controls'!$J$5:$J$44,'CC6 Controls'!$B$5:$B$44,"<>")+SUMIFS('CC7 Controls'!$J$5:$J$30,'CC7 Controls'!$B$5:$B$30,"<>")+SUMIFS('CC8 Controls'!$J$5:$J$12,'CC8 Controls'!$B$5:$B$12,"<>")+SUMIFS('CC9 Controls'!$J$5:$J$16,'CC9 Controls'!$B$5:$B$16,"<>") -> 139
B40: Maximum possible | C40: =((COUNTIF('CC1 Controls'!$B$5:$B$39,"<>")+COUNTIF('CC2 Controls'!$B$5:$B$24,"<>")+COUNTIF('CC3 Controls'!$B$5:$B$28,"<>")+COUNTIF('CC4 Controls'!$B$5:$B$19,"<>")+COUNTIF('CC5 Controls'!$B$5:$B$19,"<>")+COUNTIF('CC6 Controls'!$B$5:$B$44,"<>")+COUNTIF('CC7 Controls'!$B$5:$B$30,"<>")+COUNTIF('CC8 Controls'!$B$5:$B$12,"<>")+COUNTIF('CC9 Controls'!$B$5:$B$16,"<>")) - (COUNTIFS('CC1 Controls'!$B$5:$B$39,"<>",'CC1 Controls'!$J$5:$J$39,"N/A")+COUNTIFS('CC2 Controls'!$B$5:$B$24,"<>",'CC2 Controls'!$J$5:$J$24,"N/A")+COUNTIFS('CC3 Controls'!$B$5:$B$28,"<>",'CC3 Controls'!$J$5:$J$28,"N/A")+COUNTIFS('CC4 Controls'!$B$5:$B$19,"<>",'CC4 Controls'!$J$5:$J$19,"N/A")+COUNTIFS('CC5 Controls'!$B$5:$B$19,"<>",'CC5 Controls'!$J$5:$J$19,"N/A")+COUNTIFS('CC6 Controls'!$B$5:$B$44,"<>",'CC6 Controls'!$J$5:$J$44,"N/A")+COUNTIFS('CC7 Controls'!$B$5:$B$30,"<>",'CC7 Controls'!$J$5:$J$30,"N/A")+COUNTIFS('CC8 Controls'!$B$5:$B$12,"<>",'CC8 Controls'!$J$5:$J$12,"N/A")+COUNTIFS('CC9 Controls'!$B$5:$B$16,"<>",'CC9 Controls'!$J$5:$J$16,"N/A")))*4 -> 636
B41: Readiness | C41: =IFERROR((SUMIFS('CC1 Controls'!$J$5:$J$39,'CC1 Controls'!$B$5:$B$39,"<>")+SUMIFS('CC2 Controls'!$J$5:$J$24,'CC2 Controls'!$B$5:$B$24,"<>")+SUMIFS('CC3 Controls'!$J$5:$J$28,'CC3 Controls'!$B$5:$B$28,"<>")+SUMIFS('CC4 Controls'!$J$5:$J$19,'CC4 Controls'!$B$5:$B$19,"<>")+SUMIFS('CC5 Controls'!$J$5:$J$19,'CC5 Controls'!$B$5:$B$19,"<>")+SUMIFS('CC6 Controls'!$J$5:$J$44,'CC6 Controls'!$B$5:$B$44,"<>")+SUMIFS('CC7 Controls'!$J$5:$J$30,'CC7 Controls'!$B$5:$B$30,"<>")+SUMIFS('CC8 Controls'!$J$5:$J$12,'CC8 Controls'!$B$5:$B$12,"<>")+SUMIFS('CC9 Controls'!$J$5:$J$16,'CC9 Controls'!$B$5:$B$16,"<>"))/(((COUNTIF('CC1 Controls'!$B$5:$B$39,"<>")+COUNTIF('CC2 Controls'!$B$5:$B$24,"<>")+COUNTIF('CC3 Controls'!$B$5:$B$28,"<>")+COUNTIF('CC4 Controls'!$B$5:$B$19,"<>")+COUNTIF('CC5 Controls'!$B$5:$B$19,"<>")+COUNTIF('CC6 Controls'!$B$5:$B$44,"<>")+COUNTIF('CC7 Controls'!$B$5:$B$30,"<>")+COUNTIF('CC8 Controls'!$B$5:$B$12,"<>")+COUNTIF('CC9 Controls'!$B$5:$B$16,"<>")) - (COUNTIFS('CC1 Controls'!$B$5:$B$39,"<>",'CC1 Controls'!$J$5:$J$39,"N/A")+COUNTIFS('CC2 Controls'!$B$5:$B$24,"<>",'CC2 Controls'!$J$5:$J$24,"N/A")+COUNTIFS('CC3 Controls'!$B$5:$B$28,"<>",'CC3 Controls'!$J$5:$J$28,"N/A")+COUNTIFS('CC4 Controls'!$B$5:$B$19,"<>",'CC4 Controls'!$J$5:$J$19,"N/A")+COUNTIFS('CC5 Controls'!$B$5:$B$19,"<>",'CC5 Controls'!$J$5:$J$19,"N/A")+COUNTIFS('CC6 Controls'!$B$5:$B$44,"<>",'CC6 Controls'!$J$5:$J$44,"N/A")+COUNTIFS('CC7 Controls'!$B$5:$B$30,"<>",'CC7 Controls'!$J$5:$J$30,"N/A")+COUNTIFS('CC8 Controls'!$B$5:$B$12,"<>",'CC8 Controls'!$J$5:$J$12,"N/A")+COUNTIFS('CC9 Controls'!$B$5:$B$16,"<>",'CC9 Controls'!$J$5:$J$16,"N/A")))*4),0) -> 0.21855346 | D41: Total score as a share of the maximum. A blunt but useful single number.
B42: Average level | C42: =IFERROR((SUMIFS('CC1 Controls'!$J$5:$J$39,'CC1 Controls'!$B$5:$B$39,"<>")+SUMIFS('CC2 Controls'!$J$5:$J$24,'CC2 Controls'!$B$5:$B$24,"<>")+SUMIFS('CC3 Controls'!$J$5:$J$28,'CC3 Controls'!$B$5:$B$28,"<>")+SUMIFS('CC4 Controls'!$J$5:$J$19,'CC4 Controls'!$B$5:$B$19,"<>")+SUMIFS('CC5 Controls'!$J$5:$J$19,'CC5 Controls'!$B$5:$B$19,"<>")+SUMIFS('CC6 Controls'!$J$5:$J$44,'CC6 Controls'!$B$5:$B$44,"<>")+SUMIFS('CC7 Controls'!$J$5:$J$30,'CC7 Controls'!$B$5:$B$30,"<>")+SUMIFS('CC8 Controls'!$J$5:$J$12,'CC8 Controls'!$B$5:$B$12,"<>")+SUMIFS('CC9 Controls'!$J$5:$J$16,'CC9 Controls'!$B$5:$B$16,"<>"))/(COUNTIFS('CC1 Controls'!$B$5:$B$39,"<>",'CC1 Controls'!$J$5:$J$39,">=0")+COUNTIFS('CC2 Controls'!$B$5:$B$24,"<>",'CC2 Controls'!$J$5:$J$24,">=0")+COUNTIFS('CC3 Controls'!$B$5:$B$28,"<>",'CC3 Controls'!$J$5:$J$28,">=0")+COUNTIFS('CC4 Controls'!$B$5:$B$19,"<>",'CC4 Controls'!$J$5:$J$19,">=0")+COUNTIFS('CC5 Controls'!$B$5:$B$19,"<>",'CC5 Controls'!$J$5:$J$19,">=0")+COUNTIFS('CC6 Controls'!$B$5:$B$44,"<>",'CC6 Controls'!$J$5:$J$44,">=0")+COUNTIFS('CC7 Controls'!$B$5:$B$30,"<>",'CC7 Controls'!$J$5:$J$30,">=0")+COUNTIFS('CC8 Controls'!$B$5:$B$12,"<>",'CC8 Controls'!$J$5:$J$12,">=0")+COUNTIFS('CC9 Controls'!$B$5:$B$16,"<>",'CC9 Controls'!$J$5:$J$16,">=0")),0) -> 0.87421384
B44: Level 0 — Gap | C44: =COUNTIFS('CC1 Controls'!$B$5:$B$39,"<>",'CC1 Controls'!$J$5:$J$39,0)+COUNTIFS('CC2 Controls'!$B$5:$B$24,"<>",'CC2 Controls'!$J$5:$J$24,0)+COUNTIFS('CC3 Controls'!$B$5:$B$28,"<>",'CC3 Controls'!$J$5:$J$28,0)+COUNTIFS('CC4 Controls'!$B$5:$B$19,"<>",'CC4 Controls'!$J$5:$J$19,0)+COUNTIFS('CC5 Controls'!$B$5:$B$19,"<>",'CC5 Controls'!$J$5:$J$19,0)+COUNTIFS('CC6 Controls'!$B$5:$B$44,"<>",'CC6 Controls'!$J$5:$J$44,0)+COUNTIFS('CC7 Controls'!$B$5:$B$30,"<>",'CC7 Controls'!$J$5:$J$30,0)+COUNTIFS('CC8 Controls'!$B$5:$B$12,"<>",'CC8 Controls'!$J$5:$J$12,0)+COUNTIFS('CC9 Controls'!$B$5:$B$16,"<>",'CC9 Controls'!$J$5:$J$16,0) -> 21
B45: Level 1 — Documented | C45: =COUNTIFS('CC1 Controls'!$B$5:$B$39,"<>",'CC1 Controls'!$J$5:$J$39,1)+COUNTIFS('CC2 Controls'!$B$5:$B$24,"<>",'CC2 Controls'!$J$5:$J$24,1)+COUNTIFS('CC3 Controls'!$B$5:$B$28,"<>",'CC3 Controls'!$J$5:$J$28,1)+COUNTIFS('CC4 Controls'!$B$5:$B$19,"<>",'CC4 Controls'!$J$5:$J$19,1)+COUNTIFS('CC5 Controls'!$B$5:$B$19,"<>",'CC5 Controls'!$J$5:$J$19,1)+COUNTIFS('CC6 Controls'!$B$5:$B$44,"<>",'CC6 Controls'!$J$5:$J$44,1)+COUNTIFS('CC7 Controls'!$B$5:$B$30,"<>",'CC7 Controls'!$J$5:$J$30,1)+COUNTIFS('CC8 Controls'!$B$5:$B$12,"<>",'CC8 Controls'!$J$5:$J$12,1)+COUNTIFS('CC9 Controls'!$B$5:$B$16,"<>",'CC9 Controls'!$J$5:$J$16,1) -> 137
B46: Level 2 — Implemented | C46: =COUNTIFS('CC1 Controls'!$B$5:$B$39,"<>",'CC1 Controls'!$J$5:$J$39,2)+COUNTIFS('CC2 Controls'!$B$5:$B$24,"<>",'CC2 Controls'!$J$5:$J$24,2)+COUNTIFS('CC3 Controls'!$B$5:$B$28,"<>",'CC3 Controls'!$J$5:$J$28,2)+COUNTIFS('CC4 Controls'!$B$5:$B$19,"<>",'CC4 Controls'!$J$5:$J$19,2)+COUNTIFS('CC5 Controls'!$B$5:$B$19,"<>",'CC5 Controls'!$J$5:$J$19,2)+COUNTIFS('CC6 Controls'!$B$5:$B$44,"<>",'CC6 Controls'!$J$5:$J$44,2)+COUNTIFS('CC7 Controls'!$B$5:$B$30,"<>",'CC7 Controls'!$J$5:$J$30,2)+COUNTIFS('CC8 Controls'!$B$5:$B$12,"<>",'CC8 Controls'!$J$5:$J$12,2)+COUNTIFS('CC9 Controls'!$B$5:$B$16,"<>",'CC9 Controls'!$J$5:$J$16,2) -> 1
B47: Level 3 — Evidenced | C47: =COUNTIFS('CC1 Controls'!$B$5:$B$39,"<>",'CC1 Controls'!$J$5:$J$39,3)+COUNTIFS('CC2 Controls'!$B$5:$B$24,"<>",'CC2 Controls'!$J$5:$J$24,3)+COUNTIFS('CC3 Controls'!$B$5:$B$28,"<>",'CC3 Controls'!$J$5:$J$28,3)+COUNTIFS('CC4 Controls'!$B$5:$B$19,"<>",'CC4 Controls'!$J$5:$J$19,3)+COUNTIFS('CC5 Controls'!$B$5:$B$19,"<>",'CC5 Controls'!$J$5:$J$19,3)+COUNTIFS('CC6 Controls'!$B$5:$B$44,"<>",'CC6 Controls'!$J$5:$J$44,3)+COUNTIFS('CC7 Controls'!$B$5:$B$30,"<>",'CC7 Controls'!$J$5:$J$30,3)+COUNTIFS('CC8 Controls'!$B$5:$B$12,"<>",'CC8 Controls'!$J$5:$J$12,3)+COUNTIFS('CC9 Controls'!$B$5:$B$16,"<>",'CC9 Controls'!$J$5:$J$16,3) -> 0
B48: Level 4 — Automated | C48: =COUNTIFS('CC1 Controls'!$B$5:$B$39,"<>",'CC1 Controls'!$J$5:$J$39,4)+COUNTIFS('CC2 Controls'!$B$5:$B$24,"<>",'CC2 Controls'!$J$5:$J$24,4)+COUNTIFS('CC3 Controls'!$B$5:$B$28,"<>",'CC3 Controls'!$J$5:$J$28,4)+COUNTIFS('CC4 Controls'!$B$5:$B$19,"<>",'CC4 Controls'!$J$5:$J$19,4)+COUNTIFS('CC5 Controls'!$B$5:$B$19,"<>",'CC5 Controls'!$J$5:$J$19,4)+COUNTIFS('CC6 Controls'!$B$5:$B$44,"<>",'CC6 Controls'!$J$5:$J$44,4)+COUNTIFS('CC7 Controls'!$B$5:$B$30,"<>",'CC7 Controls'!$J$5:$J$30,4)+COUNTIFS('CC8 Controls'!$B$5:$B$12,"<>",'CC8 Controls'!$J$5:$J$12,4)+COUNTIFS('CC9 Controls'!$B$5:$B$16,"<>",'CC9 Controls'!$J$5:$J$16,4) -> 0
B49: N/A — Not applicable | C49: =COUNTIFS('CC1 Controls'!$B$5:$B$39,"<>",'CC1 Controls'!$J$5:$J$39,"N/A")+COUNTIFS('CC2 Controls'!$B$5:$B$24,"<>",'CC2 Controls'!$J$5:$J$24,"N/A")+COUNTIFS('CC3 Controls'!$B$5:$B$28,"<>",'CC3 Controls'!$J$5:$J$28,"N/A")+COUNTIFS('CC4 Controls'!$B$5:$B$19,"<>",'CC4 Controls'!$J$5:$J$19,"N/A")+COUNTIFS('CC5 Controls'!$B$5:$B$19,"<>",'CC5 Controls'!$J$5:$J$19,"N/A")+COUNTIFS('CC6 Controls'!$B$5:$B$44,"<>",'CC6 Controls'!$J$5:$J$44,"N/A")+COUNTIFS('CC7 Controls'!$B$5:$B$30,"<>",'CC7 Controls'!$J$5:$J$30,"N/A")+COUNTIFS('CC8 Controls'!$B$5:$B$12,"<>",'CC8 Controls'!$J$5:$J$12,"N/A")+COUNTIFS('CC9 Controls'!$B$5:$B$16,"<>",'CC9 Controls'!$J$5:$J$16,"N/A") -> 1
B51: Below level 2 (Type I risk) | C51: =COUNTIFS('CC1 Controls'!$B$5:$B$39,"<>",'CC1 Controls'!$J$5:$J$39,"<2")+COUNTIFS('CC2 Controls'!$B$5:$B$24,"<>",'CC2 Controls'!$J$5:$J$24,"<2")+COUNTIFS('CC3 Controls'!$B$5:$B$28,"<>",'CC3 Controls'!$J$5:$J$28,"<2")+COUNTIFS('CC4 Controls'!$B$5:$B$19,"<>",'CC4 Controls'!$J$5:$J$19,"<2")+COUNTIFS('CC5 Controls'!$B$5:$B$19,"<>",'CC5 Controls'!$J$5:$J$19,"<2")+COUNTIFS('CC6 Controls'!$B$5:$B$44,"<>",'CC6 Controls'!$J$5:$J$44,"<2")+COUNTIFS('CC7 Controls'!$B$5:$B$30,"<>",'CC7 Controls'!$J$5:$J$30,"<2")+COUNTIFS('CC8 Controls'!$B$5:$B$12,"<>",'CC8 Controls'!$J$5:$J$12,"<2")+COUNTIFS('CC9 Controls'!$B$5:$B$16,"<>",'CC9 Controls'!$J$5:$J$16,"<2") -> 158 | D51: Controls that are not yet operating. Each one is a design deficiency in a Type I.
B52: Below level 3 (Type II risk) | C52: =COUNTIFS('CC1 Controls'!$B$5:$B$39,"<>",'CC1 Controls'!$J$5:$J$39,"<3")+COUNTIFS('CC2 Controls'!$B$5:$B$24,"<>",'CC2 Controls'!$J$5:$J$24,"<3")+COUNTIFS('CC3 Controls'!$B$5:$B$28,"<>",'CC3 Controls'!$J$5:$J$28,"<3")+COUNTIFS('CC4 Controls'!$B$5:$B$19,"<>",'CC4 Controls'!$J$5:$J$19,"<3")+COUNTIFS('CC5 Controls'!$B$5:$B$19,"<>",'CC5 Controls'!$J$5:$J$19,"<3")+COUNTIFS('CC6 Controls'!$B$5:$B$44,"<>",'CC6 Controls'!$J$5:$J$44,"<3")+COUNTIFS('CC7 Controls'!$B$5:$B$30,"<>",'CC7 Controls'!$J$5:$J$30,"<3")+COUNTIFS('CC8 Controls'!$B$5:$B$12,"<>",'CC8 Controls'!$J$5:$J$12,"<3")+COUNTIFS('CC9 Controls'!$B$5:$B$16,"<>",'CC9 Controls'!$J$5:$J$16,"<3") -> 159 | D52: Controls operating without retained evidence. Each one will fail a Type II sample.
B55: SCORE BY CRITERION | D55: Bold rows are the criteria; the indented rows beneath are their sub-criteria. All figures are means of the scored controls only — unscored and N/A rows are excluded, so a partly scored plan is not dragged down.
B56: CC1 | C56: =IFERROR((SUMIFS('CC1 Controls'!$J$5:$J$39,'CC1 Controls'!$B$5:$B$39,"<>"))/(COUNTIFS('CC1 Controls'!$B$5:$B$39,"<>",'CC1 Controls'!$J$5:$J$39,">=0")),0) -> 0.55555556 | D56: =IF((COUNTIFS('CC1 Controls'!$B$5:$B$39,"<>",'CC1 Controls'!$J$5:$J$39,">=0"))=0,"Control Environment · not yet scored","Control Environment · "&(COUNTIFS('CC1 Controls'!$B$5:$B$39,"<>",'CC1 Controls'!$J$5:$J$39,0))&" at level 0, "&(COUNTIFS('CC1 Controls'!$B$5:$B$39,"<>",'CC1 Controls'!$J$5:$J$39,"<3"))&" below level 3") -> Control Environment · 13 at level 0, 27 below level 3
B57: CC1.1 | C57: =IFERROR(AVERAGE('CC1 Controls'!J6:J11),0) -> 0.16666667 | D57: =IF(COUNT('CC1 Controls'!J6:J11)=0,"Integrity and ethical values · not yet scored","Integrity and ethical values · "&COUNTIF('CC1 Controls'!J6:J11,0)&" at level 0, "&COUNTIFS('CC1 Controls'!J6:J11,"<3")&" below level 3") -> Integrity and ethical values · 5 at level 0, 6 below level 3
B58: CC1.2 | C58: =IFERROR(AVERAGE('CC1 Controls'!J14:J19),0) -> 1 | D58: =IF(COUNT('CC1 Controls'!J14:J19)=0,"Oversight of the control environment · not yet scored","Oversight of the control environment · "&COUNTIF('CC1 Controls'!J14:J19,0)&" at level 0, "&COUNTIFS('CC1 Controls'!J14:J19,"<3")&" below level 3") -> Oversight of the control environment · 1 at level 0, 5 below level 3
B59: CC1.3 | C59: =IFERROR(AVERAGE('CC1 Controls'!J22:J26),0) -> 0.4 | D59: =IF(COUNT('CC1 Controls'!J22:J26)=0,"Structure, authority and responsibility · not yet scored","Structure, authority and responsibility · "&COUNTIF('CC1 Controls'!J22:J26,0)&" at level 0, "&COUNTIFS('CC1 Controls'!J22:J26,"<3")&" below level 3") -> Structure, authority and responsibility · 3 at level 0, 5 below level 3
B60: CC1.4 | C60: =IFERROR(AVERAGE('CC1 Controls'!J28:J33),0) -> 0.5 | D60: =IF(COUNT('CC1 Controls'!J28:J33)=0,"Competence — attract, develop, retain · not yet scored","Competence — attract, develop, retain · "&COUNTIF('CC1 Controls'!J28:J33,0)&" at level 0, "&COUNTIFS('CC1 Controls'!J28:J33,"<3")&" below level 3") -> Competence — attract, develop, retain · 3 at level 0, 6 below level 3
B61: CC1.5 | C61: =IFERROR(AVERAGE('CC1 Controls'!J35:J39),0) -> 0.8 | D61: =IF(COUNT('CC1 Controls'!J35:J39)=0,"Accountability for internal control · not yet scored","Accountability for internal control · "&COUNTIF('CC1 Controls'!J35:J39,0)&" at level 0, "&COUNTIFS('CC1 Controls'!J35:J39,"<3")&" below level 3") -> Accountability for internal control · 1 at level 0, 5 below level 3
B62: CC2 | C62: =IFERROR((SUMIFS('CC2 Controls'!$J$5:$J$24,'CC2 Controls'!$B$5:$B$24,"<>"))/(COUNTIFS('CC2 Controls'!$B$5:$B$24,"<>",'CC2 Controls'!$J$5:$J$24,">=0")),0) -> 0.70588235 | D62: =IF((COUNTIFS('CC2 Controls'!$B$5:$B$24,"<>",'CC2 Controls'!$J$5:$J$24,">=0"))=0,"Communication and Information · not yet scored","Communication and Information · "&(COUNTIFS('CC2 Controls'!$B$5:$B$24,"<>",'CC2 Controls'!$J$5:$J$24,0))&" at level 0, "&(COUNTIFS('CC2 Controls'!$B$5:$B$24,"<>",'CC2 Controls'!$J$5:$J$24,"<3"))&" below level 3") -> Communication and Information · 5 at level 0, 17 below level 3
B63: CC2.1 | C63: =IFERROR(AVERAGE('CC2 Controls'!J6:J10),0) -> 1 | D63: =IF(COUNT('CC2 Controls'!J6:J10)=0,"Relevant, quality information · not yet scored","Relevant, quality information · "&COUNTIF('CC2 Controls'!J6:J10,0)&" at level 0, "&COUNTIFS('CC2 Controls'!J6:J10,"<3")&" below level 3") -> Relevant, quality information · 0 at level 0, 5 below level 3
B64: CC2.2 | C64: =IFERROR(AVERAGE('CC2 Controls'!J12:J17),0) -> 0.5 | D64: =IF(COUNT('CC2 Controls'!J12:J17)=0,"Internal communication · not yet scored","Internal communication · "&COUNTIF('CC2 Controls'!J12:J17,0)&" at level 0, "&COUNTIFS('CC2 Controls'!J12:J17,"<3")&" below level 3") -> Internal communication · 3 at level 0, 6 below level 3
B65: CC2.3 | C65: =IFERROR(AVERAGE('CC2 Controls'!J19:J24),0) -> 0.66666667 | D65: =IF(COUNT('CC2 Controls'!J19:J24)=0,"External communication · not yet scored","External communication · "&COUNTIF('CC2 Controls'!J19:J24,0)&" at level 0, "&COUNTIFS('CC2 Controls'!J19:J24,"<3")&" below level 3") -> External communication · 2 at level 0, 6 below level 3
B66: CC3 | C66: =IFERROR((SUMIFS('CC3 Controls'!$J$5:$J$28,'CC3 Controls'!$B$5:$B$28,"<>"))/(COUNTIFS('CC3 Controls'!$B$5:$B$28,"<>",'CC3 Controls'!$J$5:$J$28,">=0")),0) -> 0.9 | D66: =IF((COUNTIFS('CC3 Controls'!$B$5:$B$28,"<>",'CC3 Controls'!$J$5:$J$28,">=0"))=0,"Risk Assessment · not yet scored","Risk Assessment · "&(COUNTIFS('CC3 Controls'!$B$5:$B$28,"<>",'CC3 Controls'!$J$5:$J$28,0))&" at level 0, "&(COUNTIFS('CC3 Controls'!$B$5:$B$28,"<>",'CC3 Controls'!$J$5:$J$28,"<3"))&" below level 3") -> Risk Assessment · 2 at level 0, 20 below level 3
B67: CC3.1 | C67: =IFERROR(AVERAGE('CC3 Controls'!J6:J10),0) -> 0.6 | D67: =IF(COUNT('CC3 Controls'!J6:J10)=0,"Objectives specified with sufficient clarity · not yet scored","Objectives specified with sufficient clarity · "&COUNTIF('CC3 Controls'!J6:J10,0)&" at level 0, "&COUNTIFS('CC3 Controls'!J6:J10,"<3")&" below level 3") -> Objectives specified with sufficient clarity · 2 at level 0, 5 below level 3
B68: CC3.2 | C68: =IFERROR(AVERAGE('CC3 Controls'!J12:J18),0) -> 1 | D68: =IF(COUNT('CC3 Controls'!J12:J18)=0,"Identifies and analyzes risk · not yet scored","Identifies and analyzes risk · "&COUNTIF('CC3 Controls'!J12:J18,0)&" at level 0, "&COUNTIFS('CC3 Controls'!J12:J18,"<3")&" below level 3") -> Identifies and analyzes risk · 0 at level 0, 7 below level 3
B69: CC3.3 | C69: =IFERROR(AVERAGE('CC3 Controls'!J20:J23),0) -> 1 | D69: =IF(COUNT('CC3 Controls'!J20:J23)=0,"Considers the potential for fraud · not yet scored","Considers the potential for fraud · "&COUNTIF('CC3 Controls'!J20:J23,0)&" at level 0, "&COUNTIFS('CC3 Controls'!J20:J23,"<3")&" below level 3") -> Considers the potential for fraud · 0 at level 0, 4 below level 3
B70: CC3.4 | C70: =IFERROR(AVERAGE('CC3 Controls'!J25:J28),0) -> 1 | D70: =IF(COUNT('CC3 Controls'!J25:J28)=0,"Identifies and assesses significant change · not yet scored","Identifies and assesses significant change · "&COUNTIF('CC3 Controls'!J25:J28,0)&" at level 0, "&COUNTIFS('CC3 Controls'!J25:J28,"<3")&" below level 3") -> Identifies and assesses significant change · 0 at level 0, 4 below level 3
B71: CC4 | C71: =IFERROR((SUMIFS('CC4 Controls'!$J$5:$J$19,'CC4 Controls'!$B$5:$B$19,"<>"))/(COUNTIFS('CC4 Controls'!$B$5:$B$19,"<>",'CC4 Controls'!$J$5:$J$19,">=0")),0) -> 1 | D71: =IF((COUNTIFS('CC4 Controls'!$B$5:$B$19,"<>",'CC4 Controls'!$J$5:$J$19,">=0"))=0,"Monitoring Activities · not yet scored","Monitoring Activities · "&(COUNTIFS('CC4 Controls'!$B$5:$B$19,"<>",'CC4 Controls'!$J$5:$J$19,0))&" at level 0, "&(COUNTIFS('CC4 Controls'!$B$5:$B$19,"<>",'CC4 Controls'!$J$5:$J$19,"<3"))&" below level 3") -> Monitoring Activities · 0 at level 0, 13 below level 3
B72: CC4.1 | C72: =IFERROR(AVERAGE('CC4 Controls'!J6:J12),0) -> 1 | D72: =IF(COUNT('CC4 Controls'!J6:J12)=0,"Ongoing and separate evaluations · not yet scored","Ongoing and separate evaluations · "&COUNTIF('CC4 Controls'!J6:J12,0)&" at level 0, "&COUNTIFS('CC4 Controls'!J6:J12,"<3")&" below level 3") -> Ongoing and separate evaluations · 0 at level 0, 7 below level 3
B73: CC4.2 | C73: =IFERROR(AVERAGE('CC4 Controls'!J14:J19),0) -> 1 | D73: =IF(COUNT('CC4 Controls'!J14:J19)=0,"Evaluates and communicates deficiencies · not yet scored","Evaluates and communicates deficiencies · "&COUNTIF('CC4 Controls'!J14:J19,0)&" at level 0, "&COUNTIFS('CC4 Controls'!J14:J19,"<3")&" below level 3") -> Evaluates and communicates deficiencies · 0 at level 0, 6 below level 3
B74: CC5 | C74: =IFERROR((SUMIFS('CC5 Controls'!$J$5:$J$19,'CC5 Controls'!$B$5:$B$19,"<>"))/(COUNTIFS('CC5 Controls'!$B$5:$B$19,"<>",'CC5 Controls'!$J$5:$J$19,">=0")),0) -> 1 | D74: =IF((COUNTIFS('CC5 Controls'!$B$5:$B$19,"<>",'CC5 Controls'!$J$5:$J$19,">=0"))=0,"Control Activities · not yet scored","Control Activities · "&(COUNTIFS('CC5 Controls'!$B$5:$B$19,"<>",'CC5 Controls'!$J$5:$J$19,0))&" at level 0, "&(COUNTIFS('CC5 Controls'!$B$5:$B$19,"<>",'CC5 Controls'!$J$5:$J$19,"<3"))&" below level 3") -> Control Activities · 0 at level 0, 12 below level 3
B75: CC5.1 | C75: =IFERROR(AVERAGE('CC5 Controls'!J6:J9),0) -> 1 | D75: =IF(COUNT('CC5 Controls'!J6:J9)=0,"Selects and develops control activities · not yet scored","Selects and develops control activities · "&COUNTIF('CC5 Controls'!J6:J9,0)&" at level 0, "&COUNTIFS('CC5 Controls'!J6:J9,"<3")&" below level 3") -> Selects and develops control activities · 0 at level 0, 4 below level 3
B76: CC5.2 | C76: =IFERROR(AVERAGE('CC5 Controls'!J11:J14),0) -> 1 | D76: =IF(COUNT('CC5 Controls'!J11:J14)=0,"General controls over technology · not yet scored","General controls over technology · "&COUNTIF('CC5 Controls'!J11:J14,0)&" at level 0, "&COUNTIFS('CC5 Controls'!J11:J14,"<3")&" below level 3") -> General controls over technology · 0 at level 0, 4 below level 3
B77: CC5.3 | C77: =IFERROR(AVERAGE('CC5 Controls'!J16:J19),0) -> 1 | D77: =IF(COUNT('CC5 Controls'!J16:J19)=0,"Deploys through policies and procedures · not yet scored","Deploys through policies and procedures · "&COUNTIF('CC5 Controls'!J16:J19,0)&" at level 0, "&COUNTIFS('CC5 Controls'!J16:J19,"<3")&" below level 3") -> Deploys through policies and procedures · 0 at level 0, 4 below level 3
B78: CC6 | C78: =IFERROR((SUMIFS('CC6 Controls'!$J$5:$J$44,'CC6 Controls'!$B$5:$B$44,"<>"))/(COUNTIFS('CC6 Controls'!$B$5:$B$44,"<>",'CC6 Controls'!$J$5:$J$44,">=0")),0) -> 0.96875 | D78: =IF((COUNTIFS('CC6 Controls'!$B$5:$B$44,"<>",'CC6 Controls'!$J$5:$J$44,">=0"))=0,"Logical and Physical Access Controls · not yet scored","Logical and Physical Access Controls · "&(COUNTIFS('CC6 Controls'!$B$5:$B$44,"<>",'CC6 Controls'!$J$5:$J$44,0))&" at level 0, "&(COUNTIFS('CC6 Controls'!$B$5:$B$44,"<>",'CC6 Controls'!$J$5:$J$44,"<3"))&" below level 3") -> Logical and Physical Access Controls · 1 at level 0, 32 below level 3
B79: CC6.1 | C79: =IFERROR(AVERAGE('CC6 Controls'!J6:J10),0) -> 1 | D79: =IF(COUNT('CC6 Controls'!J6:J10)=0,"Logical access security measures · not yet scored","Logical access security measures · "&COUNTIF('CC6 Controls'!J6:J10,0)&" at level 0, "&COUNTIFS('CC6 Controls'!J6:J10,"<3")&" below level 3") -> Logical access security measures · 0 at level 0, 5 below level 3
B80: CC6.2 | C80: =IFERROR(AVERAGE('CC6 Controls'!J12:J15),0) -> 1 | D80: =IF(COUNT('CC6 Controls'!J12:J15)=0,"Registration and authorization of users · not yet scored","Registration and authorization of users · "&COUNTIF('CC6 Controls'!J12:J15,0)&" at level 0, "&COUNTIFS('CC6 Controls'!J12:J15,"<3")&" below level 3") -> Registration and authorization of users · 0 at level 0, 4 below level 3
B81: CC6.3 | C81: =IFERROR(AVERAGE('CC6 Controls'!J17:J21),0) -> 1 | D81: =IF(COUNT('CC6 Controls'!J17:J21)=0,"Role-based access, least privilege, segregation · not yet scored","Role-based access, least privilege, segregation · "&COUNTIF('CC6 Controls'!J17:J21,0)&" at level 0, "&COUNTIFS('CC6 Controls'!J17:J21,"<3")&" below level 3") -> Role-based access, least privilege, segregation · 0 at level 0, 5 below level 3
B82: CC6.4 | C82: =IFERROR(AVERAGE('CC6 Controls'!J23:J26),0) -> 1 | D82: =IF(COUNT('CC6 Controls'!J23:J26)=0,"Physical access · not yet scored","Physical access · "&COUNTIF('CC6 Controls'!J23:J26,0)&" at level 0, "&COUNTIFS('CC6 Controls'!J23:J26,"<3")&" below level 3") -> Physical access · 0 at level 0, 4 below level 3
B83: CC6.5 | C83: =IFERROR(AVERAGE('CC6 Controls'!J28:J30),0) -> 1 | D83: =IF(COUNT('CC6 Controls'!J28:J30)=0,"Disposal of assets and information · not yet scored","Disposal of assets and information · "&COUNTIF('CC6 Controls'!J28:J30,0)&" at level 0, "&COUNTIFS('CC6 Controls'!J28:J30,"<3")&" below level 3") -> Disposal of assets and information · 0 at level 0, 3 below level 3
B84: CC6.6 | C84: =IFERROR(AVERAGE('CC6 Controls'!J32:J35),0) -> 0.75 | D84: =IF(COUNT('CC6 Controls'!J32:J35)=0,"Protection against external threats · not yet scored","Protection against external threats · "&COUNTIF('CC6 Controls'!J32:J35,0)&" at level 0, "&COUNTIFS('CC6 Controls'!J32:J35,"<3")&" below level 3") -> Protection against external threats · 1 at level 0, 4 below level 3
B85: CC6.7 | C85: =IFERROR(AVERAGE('CC6 Controls'!J37:J40),0) -> 1 | D85: =IF(COUNT('CC6 Controls'!J37:J40)=0,"Transmission, movement and removal of information · not yet scored","Transmission, movement and removal of information · "&COUNTIF('CC6 Controls'!J37:J40,0)&" at level 0, "&COUNTIFS('CC6 Controls'!J37:J40,"<3")&" below level 3") -> Transmission, movement and removal of information · 0 at level 0, 4 below level 3
B86: CC6.8 | C86: =IFERROR(AVERAGE('CC6 Controls'!J42:J44),0) -> 1 | D86: =IF(COUNT('CC6 Controls'!J42:J44)=0,"Prevention and detection of unauthorized software · not yet scored","Prevention and detection of unauthorized software · "&COUNTIF('CC6 Controls'!J42:J44,0)&" at level 0, "&COUNTIFS('CC6 Controls'!J42:J44,"<3")&" below level 3") -> Prevention and detection of unauthorized software · 0 at level 0, 3 below level 3
B87: CC7 | C87: =IFERROR((SUMIFS('CC7 Controls'!$J$5:$J$30,'CC7 Controls'!$B$5:$B$30,"<>"))/(COUNTIFS('CC7 Controls'!$B$5:$B$30,"<>",'CC7 Controls'!$J$5:$J$30,">=0")),0) -> 1 | D87: =IF((COUNTIFS('CC7 Controls'!$B$5:$B$30,"<>",'CC7 Controls'!$J$5:$J$30,">=0"))=0,"System Operations · not yet scored","System Operations · "&(COUNTIFS('CC7 Controls'!$B$5:$B$30,"<>",'CC7 Controls'!$J$5:$J$30,0))&" at level 0, "&(COUNTIFS('CC7 Controls'!$B$5:$B$30,"<>",'CC7 Controls'!$J$5:$J$30,"<3"))&" below level 3") -> System Operations · 0 at level 0, 21 below level 3
B88: CC7.1 | C88: =IFERROR(AVERAGE('CC7 Controls'!J6:J9),0) -> 1 | D88: =IF(COUNT('CC7 Controls'!J6:J9)=0,"Detection of configuration changes and vulnerabilities · not yet scored","Detection of configuration changes and vulnerabilities · "&COUNTIF('CC7 Controls'!J6:J9,0)&" at level 0, "&COUNTIFS('CC7 Controls'!J6:J9,"<3")&" below level 3") -> Detection of configuration changes and vulnerabilities · 0 at level 0, 4 below level 3
B89: CC7.2 | C89: =IFERROR(AVERAGE('CC7 Controls'!J11:J14),0) -> 1 | D89: =IF(COUNT('CC7 Controls'!J11:J14)=0,"Monitoring for anomalies · not yet scored","Monitoring for anomalies · "&COUNTIF('CC7 Controls'!J11:J14,0)&" at level 0, "&COUNTIFS('CC7 Controls'!J11:J14,"<3")&" below level 3") -> Monitoring for anomalies · 0 at level 0, 4 below level 3
B90: CC7.3 | C90: =IFERROR(AVERAGE('CC7 Controls'!J16:J19),0) -> 1 | D90: =IF(COUNT('CC7 Controls'!J16:J19)=0,"Evaluation of security events · not yet scored","Evaluation of security events · "&COUNTIF('CC7 Controls'!J16:J19,0)&" at level 0, "&COUNTIFS('CC7 Controls'!J16:J19,"<3")&" below level 3") -> Evaluation of security events · 0 at level 0, 4 below level 3
B91: CC7.4 | C91: =IFERROR(AVERAGE('CC7 Controls'!J21:J25),0) -> 1 | D91: =IF(COUNT('CC7 Controls'!J21:J25)=0,"Incident response · not yet scored","Incident response · "&COUNTIF('CC7 Controls'!J21:J25,0)&" at level 0, "&COUNTIFS('CC7 Controls'!J21:J25,"<3")&" below level 3") -> Incident response · 0 at level 0, 5 below level 3
B92: CC7.5 | C92: =IFERROR(AVERAGE('CC7 Controls'!J27:J30),0) -> 1 | D92: =IF(COUNT('CC7 Controls'!J27:J30)=0,"Recovery from incidents · not yet scored","Recovery from incidents · "&COUNTIF('CC7 Controls'!J27:J30,0)&" at level 0, "&COUNTIFS('CC7 Controls'!J27:J30,"<3")&" below level 3") -> Recovery from incidents · 0 at level 0, 4 below level 3
B93: CC8 | C93: =IFERROR((SUMIFS('CC8 Controls'!$J$5:$J$12,'CC8 Controls'!$B$5:$B$12,"<>"))/(COUNTIFS('CC8 Controls'!$B$5:$B$12,"<>",'CC8 Controls'!$J$5:$J$12,">=0")),0) -> 1 | D93: =IF((COUNTIFS('CC8 Controls'!$B$5:$B$12,"<>",'CC8 Controls'!$J$5:$J$12,">=0"))=0,"Change Management · not yet scored","Change Management · "&(COUNTIFS('CC8 Controls'!$B$5:$B$12,"<>",'CC8 Controls'!$J$5:$J$12,0))&" at level 0, "&(COUNTIFS('CC8 Controls'!$B$5:$B$12,"<>",'CC8 Controls'!$J$5:$J$12,"<3"))&" below level 3") -> Change Management · 0 at level 0, 7 below level 3
B94: CC8.1 | C94: =IFERROR(AVERAGE('CC8 Controls'!J6:J12),0) -> 1 | D94: =IF(COUNT('CC8 Controls'!J6:J12)=0,"Authorises, designs, develops, tests, approves and implements changes · not yet scored","Authorises, designs, develops, tests, approves and implements changes · "&COUNTIF('CC8 Controls'!J6:J12,0)&" at level 0, "&COUNTIFS('CC8 Controls'!J6:J12,"<3")&" below level 3") -> Authorises, designs, develops, tests, approves and implements changes · 0 at level 0, 7 below level 3
B95: CC9 | C95: =IFERROR((SUMIFS('CC9 Controls'!$J$5:$J$16,'CC9 Controls'!$B$5:$B$16,"<>"))/(COUNTIFS('CC9 Controls'!$B$5:$B$16,"<>",'CC9 Controls'!$J$5:$J$16,">=0")),0) -> 1 | D95: =IF((COUNTIFS('CC9 Controls'!$B$5:$B$16,"<>",'CC9 Controls'!$J$5:$J$16,">=0"))=0,"Risk Mitigation · not yet scored","Risk Mitigation · "&(COUNTIFS('CC9 Controls'!$B$5:$B$16,"<>",'CC9 Controls'!$J$5:$J$16,0))&" at level 0, "&(COUNTIFS('CC9 Controls'!$B$5:$B$16,"<>",'CC9 Controls'!$J$5:$J$16,"<3"))&" below level 3") -> Risk Mitigation · 0 at level 0, 10 below level 3
B96: CC9.1 | C96: =IFERROR(AVERAGE('CC9 Controls'!J6:J10),0) -> 1 | D96: =IF(COUNT('CC9 Controls'!J6:J10)=0,"Business disruption risk mitigation · not yet scored","Business disruption risk mitigation · "&COUNTIF('CC9 Controls'!J6:J10,0)&" at level 0, "&COUNTIFS('CC9 Controls'!J6:J10,"<3")&" below level 3") -> Business disruption risk mitigation · 0 at level 0, 5 below level 3
B97: CC9.2 | C97: =IFERROR(AVERAGE('CC9 Controls'!J12:J16),0) -> 1 | D97: =IF(COUNT('CC9 Controls'!J12:J16)=0,"Vendor and business partner risk · not yet scored","Vendor and business partner risk · "&COUNTIF('CC9 Controls'!J12:J16,0)&" at level 0, "&COUNTIFS('CC9 Controls'!J12:J16,"<3")&" below level 3") -> Vendor and business partner risk · 0 at level 0, 5 below level 3
B98: All | C98: =IFERROR((SUMIFS('CC1 Controls'!$J$5:$J$39,'CC1 Controls'!$B$5:$B$39,"<>")+SUMIFS('CC2 Controls'!$J$5:$J$24,'CC2 Controls'!$B$5:$B$24,"<>")+SUMIFS('CC3 Controls'!$J$5:$J$28,'CC3 Controls'!$B$5:$B$28,"<>")+SUMIFS('CC4 Controls'!$J$5:$J$19,'CC4 Controls'!$B$5:$B$19,"<>")+SUMIFS('CC5 Controls'!$J$5:$J$19,'CC5 Controls'!$B$5:$B$19,"<>")+SUMIFS('CC6 Controls'!$J$5:$J$44,'CC6 Controls'!$B$5:$B$44,"<>")+SUMIFS('CC7 Controls'!$J$5:$J$30,'CC7 Controls'!$B$5:$B$30,"<>")+SUMIFS('CC8 Controls'!$J$5:$J$12,'CC8 Controls'!$B$5:$B$12,"<>")+SUMIFS('CC9 Controls'!$J$5:$J$16,'CC9 Controls'!$B$5:$B$16,"<>"))/(COUNTIFS('CC1 Controls'!$B$5:$B$39,"<>",'CC1 Controls'!$J$5:$J$39,">=0")+COUNTIFS('CC2 Controls'!$B$5:$B$24,"<>",'CC2 Controls'!$J$5:$J$24,">=0")+COUNTIFS('CC3 Controls'!$B$5:$B$28,"<>",'CC3 Controls'!$J$5:$J$28,">=0")+COUNTIFS('CC4 Controls'!$B$5:$B$19,"<>",'CC4 Controls'!$J$5:$J$19,">=0")+COUNTIFS('CC5 Controls'!$B$5:$B$19,"<>",'CC5 Controls'!$J$5:$J$19,">=0")+COUNTIFS('CC6 Controls'!$B$5:$B$44,"<>",'CC6 Controls'!$J$5:$J$44,">=0")+COUNTIFS('CC7 Controls'!$B$5:$B$30,"<>",'CC7 Controls'!$J$5:$J$30,">=0")+COUNTIFS('CC8 Controls'!$B$5:$B$12,"<>",'CC8 Controls'!$J$5:$J$12,">=0")+COUNTIFS('CC9 Controls'!$B$5:$B$16,"<>",'CC9 Controls'!$J$5:$J$16,">=0")),0) -> 0.87421384 | D98: =IF((COUNTIFS('CC1 Controls'!$B$5:$B$39,"<>",'CC1 Controls'!$J$5:$J$39,">=0")+COUNTIFS('CC2 Controls'!$B$5:$B$24,"<>",'CC2 Controls'!$J$5:$J$24,">=0")+COUNTIFS('CC3 Controls'!$B$5:$B$28,"<>",'CC3 Controls'!$J$5:$J$28,">=0")+COUNTIFS('CC4 Controls'!$B$5:$B$19,"<>",'CC4 Controls'!$J$5:$J$19,">=0")+COUNTIFS('CC5 Controls'!$B$5:$B$19,"<>",'CC5 Controls'!$J$5:$J$19,">=0")+COUNTIFS('CC6 Controls'!$B$5:$B$44,"<>",'CC6 Controls'!$J$5:$J$44,">=0")+COUNTIFS('CC7 Controls'!$B$5:$B$30,"<>",'CC7 Controls'!$J$5:$J$30,">=0")+COUNTIFS('CC8 Controls'!$B$5:$B$12,"<>",'CC8 Controls'!$J$5:$J$12,">=0")+COUNTIFS('CC9 Controls'!$B$5:$B$16,"<>",'CC9 Controls'!$J$5:$J$16,">=0"))=0,"Every control in the plan · not yet scored","Every control in the plan · "&(COUNTIFS('CC1 Controls'!$B$5:$B$39,"<>",'CC1 Controls'!$J$5:$J$39,0)+COUNTIFS('CC2 Controls'!$B$5:$B$24,"<>",'CC2 Controls'!$J$5:$J$24,0)+COUNTIFS('CC3 Controls'!$B$5:$B$28,"<>",'CC3 Controls'!$J$5:$J$28,0)+COUNTIFS('CC4 Controls'!$B$5:$B$19,"<>",'CC4 Controls'!$J$5:$J$19,0)+COUNTIFS('CC5 Controls'!$B$5:$B$19,"<>",'CC5 Controls'!$J$5:$J$19,0)+COUNTIFS('CC6 Controls'!$B$5:$B$44,"<>",'CC6 Controls'!$J$5:$J$44,0)+COUNTIFS('CC7 Controls'!$B$5:$B$30,"<>",'CC7 Controls'!$J$5:$J$30,0)+COUNTIFS('CC8 Controls'!$B$5:$B$12,"<>",'CC8 Controls'!$J$5:$J$12,0)+COUNTIFS('CC9 Controls'!$B$5:$B$16,"<>",'CC9 Controls'!$J$5:$J$16,0))&" at level 0, "&(COUNTIFS('CC1 Controls'!$B$5:$B$39,"<>",'CC1 Controls'!$J$5:$J$39,"<3")+COUNTIFS('CC2 Controls'!$B$5:$B$24,"<>",'CC2 Controls'!$J$5:$J$24,"<3")+COUNTIFS('CC3 Controls'!$B$5:$B$28,"<>",'CC3 Controls'!$J$5:$J$28,"<3")+COUNTIFS('CC4 Controls'!$B$5:$B$19,"<>",'CC4 Controls'!$J$5:$J$19,"<3")+COUNTIFS('CC5 Controls'!$B$5:$B$19,"<>",'CC5 Controls'!$J$5:$J$19,"<3")+COUNTIFS('CC6 Controls'!$B$5:$B$44,"<>",'CC6 Controls'!$J$5:$J$44,"<3")+COUNTIFS('CC7 Controls'!$B$5:$B$30,"<>",'CC7 Controls'!$J$5:$J$30,"<3")+COUNTIFS('CC8 Controls'!$B$5:$B$12,"<>",'CC8 Controls'!$J$5:$J$12,"<3")+COUNTIFS('CC9 Controls'!$B$5:$B$16,"<>",'CC9 Controls'!$J$5:$J$16,"<3"))&" below level 3") -> Every control in the plan · 21 at level 0, 159 below level 3
B103: WHEN N/A IS ACTUALLY AVAILABLE
B104: Short answer | D104: Almost never. Working through all 160 controls against a CEO-only, fully remote, newly formed company, exactly one is safely N/A and one more is conditional. Nothing in CC3 to CC9 qualifies. Small headcount changes how a control operates, not whether the criterion applies.
B105: Pre-set to N/A | D105: CC1.2-05, the independent advisor. It is the only row in this workbook that no Trust Services Criterion requires — it was added as an enhancement. The rationale is filled in for you. Replace it with a score of 0–4 if you appoint an advisor.
B106: Conditional | D106: CC1.5-02, control responsibilities in the performance review. If the CEO is the sole employee there is no review cycle to attach them to. If anyone else is employed, it applies to them and N/A is not available. Left blank for you to decide.
B107: Not N/A, however tempting | D107: CC1.2 independence, CC1.3-05 segregation of duties, CC1.3-04 delegations, the whole of CC3.3, and the independence requirements at CC4.1-01 and CC4.1-02. These feel inapplicable at two people, but the criterion still applies — and in every case the owning policy already supplies the substitute, which is CEO review and signature. CC6.4 physical access belongs on the same list — a company with no office carves those controls out to AWS, which is a treatment rather than an exclusion. A documented limitation is defensible; marking them N/A is not.
B108: Nil returns | D108: Several controls will produce nothing in year one: no conduct reports, no delegations, no disciplinary cases, no fraud suspicions, no overdue items, no alerts to dispose of in a quiet month. Record the nil affirmatively and score the control normally. An auditor cannot tell an empty file from an unperformed control.
B109: Every N/A needs a reason | D109: The rationale cell turns red if it is left empty, and the same reason belongs in the Governance Log. N/A is the most challenged cell in any gap assessment.
B112: Shaded cells are yours to fill in on the Controls tabs. Everything on this tab is calculated.

Sheet CC1 Controls
A1: CC1 — Control Environment
A2: 28 control activities across CC1.1–CC1.5. Read the scoping note before scoring — it says how each control operates at this headcount. Fill in the shaded columns only.
A4: Ref | B4: Criterion | C4: Control activity | D4: Owner | E4: Frequency | F4: System of record | G4: How to automate it | H4: Evidence artifact | I4: Scoping note at this size | J4: Score | K4: Level | L4: Rationale if N/A | M4: Next due | N4: Owning policy or standard | O4: In the plans? | P4: What the implementation plans say | Q4: What to add to close it
A5: CC1.1 | C5: Integrity and ethical values | J5: =IFERROR(ROUND(AVERAGE(J6:J10),1),"") -> 0 | K5: =IF(COUNT(J6:J10)=0,IF(COUNTIF(J6:J10,"N/A")>0,"all n/a","not scored"),COUNTIF(J6:J10,0)&" gaps, "&COUNTIFS(J6:J10,"<3")&" below 3") -> 5 gaps, 5 below 3 | O5: 1 of 6
A6: CC1.1-01 | B6: CC1.1 | C6: Code of Conduct (POL-COC-001) approved by the Steering Committee and published to all personnel. | D6: CEO | E6: Annual | F6: GitHub + Secureframe | G6: Policy lives in the GitHub policy repo. Approval = a merged pull request approved by the CEO; the merge commit is the dated approval record. Publish the approved PDF to Secureframe > Policies. | H6: Approved policy + merge commit | I6: Applies. Approval is the CEO merging the pull request. A one-person approval is still an approval as long as it is dated and attributable. | J6: 0 | K6: =IF(J6="","",IF(J6="N/A","Not applicable",CHOOSE(J6+1,"Gap","Documented","Implemented","Evidenced","Automated"))) -> Gap | N6: POL-COC-001 (authorised by POL-ISP-001 §13 Annex A) | O6: Partial | P6: ISP plan Phase 1 publishes “all subordinate policies”, but there is no Code of Conduct implementation plan in the set and the Code is never named. | Q6: Create PLN-COC, or add two tasks to ISP plan Phase 1: publish POL-COC-001 by name, and record the Committee approval date and version.
A7: CC1.1-02 | B7: CC1.1 | C7: Every employee and contractor accepts the Code of Conduct at onboarding, on material revision, and annually. | D7: Security Officer | E7: On hire + annual | F7: Secureframe | G7: Secureframe > Policies: assign to the 'employee' and 'contractor' groups. Acceptance tests reset automatically at the annual mark and reminders are sent from the platform. Reset acceptances manually after a material revision. | H7: Acknowledgment register export | I7: Applies to everyone, the CEO included. A two-name acceptance list is still an acceptance list. | J7: 0 | K7: =IF(J7="","",IF(J7="N/A","Not applicable",CHOOSE(J7+1,"Gap","Documented","Implemented","Evidenced","Automated"))) -> Gap | N7: POL-COC-001 §17 + POL-HRS-001 | O7: Partial | P7: ISP plan Phase 2 collects signed policy acknowledgments. Annual re-acceptance and reset on material revision are not stated. | Q7: Add to ISP plan Phase 2: set the annual re-acceptance recurrence in Secureframe, and reset acceptances whenever a policy is materially revised.
A8: CC1.1-03 | B8: CC1.1 | C8: Conflict of interest declaration completed annually and whenever a new client engagement is accepted. | D8: CEO | E8: Annual + per engagement | F8: Secureframe | G8: Add a custom policy document 'Annual COI Declaration' in Secureframe so it inherits the same accept-and-reset workflow. Add a COI line to the engagement intake checklist for the event-driven case. | H8: Signed declarations, incl. 'no conflicts' | I8: Applies, and carries more weight here than at a larger company, because the fractional CISO serves several clients at once. | J8: 0 | K8: =IF(J8="","",IF(J8="N/A","Not applicable",CHOOSE(J8+1,"Gap","Documented","Implemented","Evidenced","Automated"))) -> Gap | N8: POL-COC-001 §7 (no separate POL-COI-001 exists in the library) | O8: No | P8: “Conflict of interest” appears nowhere in the 20 plans. No owning plan exists. | Q8: Create PLN-COI, or add to HRS plan Phase 2: upload the annual conflict confirmation as a policy document in Secureframe so it inherits the accept-and-reset workflow, and stand up the register.
A9: CC1.1-04 | B9: CC1.1 | C9: Ethics reporting channel that bypasses the Security Officer, with anti-retaliation stated. | D9: CEO | E9: Continuous | F9: Google Workspace | G9: Create ethics@prompthalo.com routing only to the CEO. Name it in the Code of Conduct. No tooling needed beyond the alias. Need to be put on the publicly availble web site. | H9: Documented channel + report log or nil return | I9: Applies. The channel must not terminate at the Security Officer. Where the CEO is the only alternative recipient, say exactly that in the Code of Conduct. | J9: 0 | K9: =IF(J9="","",IF(J9="N/A","Not applicable",CHOOSE(J9+1,"Gap","Documented","Implemented","Evidenced","Automated"))) -> Gap | N9: POL-COC-001 §16 + POL-ISP-001 §7 | O9: No | P9: No ethics channel, whistleblowing route or anti-retaliation task in any plan. | Q9: Add to HRS plan Phase 1: create an ethics alias routing only to the CEO, name it in POL-COC-001, and state the anti-retaliation commitment. Record a nil return annually.
A10: CC1.1-05 | B10: CC1.1 | C10: Conduct deviations are documented with the finding, the decision and the rationale. | D10: CEO | E10: As they occur | F10: GitHub Issues | G10: Use a 'conduct' issue label in a private governance repo. Never handle these in email — an auditor cannot sample an inbox. | H10: Case record per event | I10: Applies. Expect a nil return in year one. Record the nil return — an empty file and a clean year look identical to an auditor. | J10: 0 | K10: =IF(J10="","",IF(J10="N/A","Not applicable",CHOOSE(J10+1,"Gap","Documented","Implemented","Evidenced","Automated"))) -> Gap | N10: POL-COC-001 §18 + POL-HRS-001 | O10: Partial | P10: HRS plan Phase 2 defines a sanctions process reference. Nothing requires the finding, decision and rationale to be recorded per event. | Q10: Extend the HRS sanctions task: require a dated record per event capturing the finding, the decision and the rationale, held as a labelled issue in the governance repo, never in email.
A11: CC1.1-06 | B11: CC1.1 | C11: Background screening is completed and recorded for every new starter before access is granted, showing the tier applied, the date completed, the outcome and who authorised access afterwards. | D11: CEO | E11: Per Hire | F11: Secureframe | G11: Enable the background check step in Secureframe > Personnel > Onboarding and connect a screening provider. Completion shows in the personnel view and the record lands in the evidence library. Make it a gate: no AWS or repository access until it passes. Store the outcome only — pass or adjudicated — never the underlying report. | H11: Screening record per hire: tier, date, outcome, authoriser | I11: Applies to contractors as well as employees, with no exception for a founder or a fractional officer. Verify claimed certifications as well as criminal history — misrepresented credentials are the failure mode specific to a security firm, and CISSP and OSCP both verify publicly at no cost. Individualised assessment on any record, never automatic disqualification. | J11: 1 | K11: =IF(J11="","",IF(J11="N/A","Not applicable",CHOOSE(J11+1,"Gap","Documented","Implemented","Evidenced","Automated"))) -> Documented | N11: POL-HRS-001 + STD-SCR-001 (to create) | O11: Yes | P11: HRS plan Phase 1 selects the provider and defines checks per role tier; Phase 3 backfills; screening records per tier are listed as evidence. | Q11: Nothing outstanding. Capture the tier definitions the HRS task produces in STD-SCR-001 so they can change without reissuing a policy.
A12: CC1.2 | C12: Oversight of the control environment | J12: =IFERROR(ROUND(AVERAGE(J14:J19),1),"") -> 1 | K12: =IF(COUNT(J14:J19)=0,IF(COUNTIF(J14:J19,"N/A")>0,"all n/a","not scored"),COUNTIF(J14:J19,0)&" gaps, "&COUNTIFS(J14:J19,"<3")&" below 3") -> 1 gaps, 5 below 3 | O12: 1 of 6
A14: CC1.2-01 | B14: CC1.2 | C14: Governance body defined: the Steering Committee comprises the CEO, satisfied by a dated written record. | D14: Security Officer | E14: Annual | F14: GitHub | G14: Already defined in the POL-ISP-001 Terminology section. Keep the definition in exactly one place and reference it; never restate it per policy. | H14: ISP Terminology entry | I14: Applies. Already satisfied by the Terminology note in POL-ISP-001 defining the Committee as the CEO. | J14: 2 | K14: =IF(J14="","",IF(J14="N/A","Not applicable",CHOOSE(J14+1,"Gap","Documented","Implemented","Evidenced","Automated"))) -> Implemented | N14: POL-ISP-001 §4 (Terminology) | O14: Yes | P14: ISP plan Phase 1 confirms Security Officer appointment and Steering Committee membership in writing. | Q14: Nothing outstanding.
A15: CC1.2-02 | B15: CC1.2 | C15: Every approval, risk acceptance and exception is recorded with the date and the person deciding. | D15: CEO | E15: Continuous | F15: This workbook | G15: Use the Governance Log tab. One line per decision, filled in the same day. This is the single most-requested CC1 artifact and the easiest to lose. | H15: Governance Log | I15: Applies. A dated written note replaces a meeting at this size; the ISP already says so, which is what makes it defensible. | J15: 1 | K15: =IF(J15="","",IF(J15="N/A","Not applicable",CHOOSE(J15+1,"Gap","Documented","Implemented","Evidenced","Automated"))) -> Documented | N15: POL-ISP-001 → Governance Log | O15: Partial | P15: Committee minutes appear in the ISP and Risk plans. No general log of approvals, risk acceptances and exceptions with date and decider. | Q15: Add to ISP plan Phase 1: stand up the Governance Decisions Log covering every approval, risk acceptance, exception and delegation — not only meeting minutes. Use the tab in this workbook.
A16: CC1.2-03 | B16: CC1.2 | C16: The absence of oversight independent of security operations is recorded as a risk with an annual review date. | D16: Security Officer | E16: Annual | F16: Secureframe | G16: Secureframe > Risk Register: one entry, treatment = 'accepted with compensating control', review date set to the annual assessment. | H16: Risk register entry + review note | I16: Applies, and is the control that turns the CC1.2 independence gap into a managed limitation rather than a deficiency. Do not skip it. | J16: 1 | K16: =IF(J16="","",IF(J16="N/A","Not applicable",CHOOSE(J16+1,"Gap","Documented","Implemented","Evidenced","Automated"))) -> Documented | N16: POL-RSK-001 → risk register | O16: Partial | P16: Risk plan builds the register and routes acceptances to the Committee. The independence limitation is not seeded as an entry. | Q16: Add to the Risk plan Phase 1 seeding task: create the independence-limitation entry explicitly, treatment ‘accepted with compensating control’, review date set to the annual assessment.
A17: CC1.2-04 | B17: CC1.2 | C17: CEO reviews and signs the Security Officer's control effectiveness assessment. | D17: CEO | E17: Annual | F17: Word + GitHub | G17: Use the Annual Control Environment Assessment template. One signature covers CC1.2, CC1.3, CC1.4 and CC1.5 — do not split it into four documents. | H17: Signed Annual Assessment | I17: Applies. This is the compensating control for CC1.2 and the reason the size limitation is acceptable. | J17: 1 | K17: =IF(J17="","",IF(J17="N/A","Not applicable",CHOOSE(J17+1,"Gap","Documented","Implemented","Evidenced","Automated"))) -> Documented | N17: POL-ISP-001 §8 → FRM-CE-001 | O17: Partial | P17: ISP plan Phase 3 runs the first control self-assessment and presents it to the Committee. No CEO signature on the Security Officer’s assessment. | Q17: Add to ISP plan Phase 3: the CEO reviews and signs the completed assessment at FRM-CE-001 Section 11. This signature is the CC1.2 compensating control.
A18: CC1.2-05 | B18: CC1.2 | C18: RECOMMENDED — an advisor outside the management reporting line reviews the annual assessment and signs a short oversight memo. | D18: CEO | E18: Annual | F18: Word + GitHub | G18: One unpaid outside advisor, one meeting a year, one signature appended to the Annual Assessment. This is what closes the CC1.2 gap properly. | H18: Advisor oversight memo | I18: Enhancement, not a Trust Services Criteria requirement — the only row in this workbook that is not criterion-mandated. Pre-set to N/A; change it to a score if you appoint an advisor. | J18: N/A | K18: =IF(J18="","",IF(J18="N/A","Not applicable",CHOOSE(J18+1,"Gap","Documented","Implemented","Evidenced","Automated"))) -> Not applicable | L18: Enhancement beyond the Trust Services Criteria; no criterion requires an independent advisor. Recorded as a deliberate scoping decision. Change to a score of 0–4 if an advisor is appointed. | N18: POL-ISP-001 → FRM-CE-001 Annex A | O18: No | P18: No independent advisor task in any plan. Expected — this control is the optional enhancement, not a criterion requirement. | Q18: If adopted: add to ISP plan Phase 3 — appoint the advisor and obtain the oversight memo at FRM-CE-001 Annex A. If declined: record the decision in the Governance Log and score this row N/A.
A19: CC1.2-06 | B19: CC1.2 | C19: Committee composition is reviewed as the Company grows and additional members are appointed when available. | D19: CEO | E19: Annual | F19: Secureframe | G19: Tie the trigger to headcount in the HRIS feeding Secureframe, not to memory. Review at each annual policy review. | H19: Review note in Annual Assessment | I19: Applies. At this size the annual review is a single line confirming nothing has changed. It still has to be written down. | J19: 0 | K19: =IF(J19="","",IF(J19="N/A","Not applicable",CHOOSE(J19+1,"Gap","Documented","Implemented","Evidenced","Automated"))) -> Gap | N19: POL-ISP-001 | O19: No | P19: No growth trigger or committee composition review task in any plan. | Q19: Add to ISP plan Operational Cadence: annual review of Committee composition against a defined headcount trigger, with the outcome recorded even when nothing changes.
A21: CC1.3 | C21: Structure, authority and responsibility | J21: =IFERROR(ROUND(AVERAGE(J22:J26),1),"") -> 0.4 | K21: =IF(COUNT(J22:J26)=0,IF(COUNTIF(J22:J26,"N/A")>0,"all n/a","not scored"),COUNTIF(J22:J26,0)&" gaps, "&COUNTIFS(J22:J26,"<3")&" below 3") -> 3 gaps, 5 below 3 | O21: 2 of 5
A22: CC1.3-01 | B22: CC1.3 | C22: Current org chart showing reporting lines, including contractors and the fractional CISO. | D22: CEO | E22: Annual + on hire | F22: GitHub | G22: A one-page chart in the governance repo, even if it is four boxes. Regenerate from the HRIS roster so it cannot drift from Secureframe's personnel list. | H22: Org chart | I22: Applies. Four boxes is a valid org chart. Include the fractional CISO and every contractor — omitting contractors is a common finding. | J22: 0 | K22: =IF(J22="","",IF(J22="N/A","Not applicable",CHOOSE(J22+1,"Gap","Documented","Implemented","Evidenced","Automated"))) -> Gap | N22: POL-ISP-001 → org chart in governance repo | O22: No | P22: An org chart appears in no plan, in tasks or in evidence. | Q22: Add to HRS plan Phase 1: produce a one-page org chart including contractors and the fractional CISO, add it to the evidence list, and review it annually and on each hire.
A23: CC1.3-02 | B23: CC1.3 | C23: Each role description states its security responsibilities. | D23: CEO | E23: Annual | F23: GitHub | G23: One markdown file per role in the governance repo. Same file serves CC1.3-02 and CC1.4-01 — write it once. | H23: Role descriptions | I23: Applies. One paragraph per role, and roles rather than named people, so it survives the next hire. | J23: 1 | K23: =IF(J23="","",IF(J23="N/A","Not applicable",CHOOSE(J23+1,"Gap","Documented","Implemented","Evidenced","Automated"))) -> Documented | N23: POL-HRS-001 → role descriptions | O23: Yes | P23: HRS plan Phase 1 adds security responsibilities to role descriptions; listed as an evidence artifact. | Q23: Nothing outstanding.
A24: CC1.3-03 | B24: CC1.3 | C24: The Accountable Party is named: the CEO, or the Security Officer in their absence. | D24: Security Officer | E24: Annual | F24: GitHub | G24: Already defined in POL-ISP-001. Reference it; do not duplicate the definition into subordinate policies. | H24: ISP clause | I24: Applies. Already named in POL-ISP-001; this row is confirming it is still current. | J24: 1 | K24: =IF(J24="","",IF(J24="N/A","Not applicable",CHOOSE(J24+1,"Gap","Documented","Implemented","Evidenced","Automated"))) -> Documented | N24: POL-ISP-001 | O24: Yes | P24: ISP plan Phase 1 confirms the Security Officer appointment in writing. | Q24: Nothing outstanding.
A25: CC1.3-04 | B25: CC1.3 | C25: Delegated duties are documented with their scope and duration. | D25: CEO | E25: As they occur | F25: This workbook | G25: Same Governance Log as CC1.2-02, with type = 'Delegation'. No second log. | H25: Governance Log | I25: Applies. Expect few or none. Record 'no delegations in force' at the annual review rather than leaving the log empty. | J25: 0 | K25: =IF(J25="","",IF(J25="N/A","Not applicable",CHOOSE(J25+1,"Gap","Documented","Implemented","Evidenced","Automated"))) -> Gap | N25: POL-ISP-001 → Governance Log | O25: No | P25: Every plan permits the Security Officer to delegate to a designee, but none requires the delegation, its scope or its duration to be recorded. | Q25: Add to ISP plan Phase 2: record every delegation in the Governance Log with scope and duration, and confirm ‘no delegations in force’ at the annual review when there are none.
A26: CC1.3-05 | B26: CC1.3 | C26: Segregation of duties assessed; where not practicable, compensating controls are documented. | D26: Security Officer | E26: Annual | F26: Word + GitHub | G26: A section of the Annual Assessment, not a standalone document. At this headcount the honest answer is that segregation is limited — say so and name the compensating controls. | H26: SoD section of Annual Assessment | I26: Applies. The assessment is required even when the conclusion is that segregation is not practicable. Do not mark N/A because you cannot segregate — that is the finding to document, not a reason to exclude the control. | J26: 0 | K26: =IF(J26="","",IF(J26="N/A","Not applicable",CHOOSE(J26+1,"Gap","Documented","Implemented","Evidenced","Automated"))) -> Gap | N26: POL-ISP-001 §7 → FRM-CE-001 §7 | O26: No | P26: Segregation of duties is not assessed in any plan. The Access Control plan separates privileged from standard accounts, which is a different control. | Q26: Add to ISP plan Phase 3: complete the segregation of duties assessment at FRM-CE-001 Section 7. ‘Not practicable at this size, compensated by X’ is a valid conclusion; an absent assessment is not.
A27: CC1.4 | C27: Competence — attract, develop, retain | J27: =IFERROR(ROUND(AVERAGE(J28:J33),1),"") -> 0.5 | K27: =IF(COUNT(J28:J33)=0,IF(COUNTIF(J28:J33,"N/A")>0,"all n/a","not scored"),COUNTIF(J28:J33,0)&" gaps, "&COUNTIFS(J28:J33,"<3")&" below 3") -> 3 gaps, 6 below 3 | O27: 3 of 6
A28: CC1.4-01 | B28: CC1.4 | C28: Competency requirements, including required skills and certifications, defined per role. | D28: CEO | E28: Annual | F28: GitHub | G28: Same role description files as CC1.3-02. One artifact, two criteria. | H28: Role descriptions | I28: Applies. Same file as CC1.3-02, written once and serving both. | J28: 0 | K28: =IF(J28="","",IF(J28="N/A","Not applicable",CHOOSE(J28+1,"Gap","Documented","Implemented","Evidenced","Automated"))) -> Gap | N28: POL-HRS-001 → role descriptions | O28: Partial | P28: Role descriptions carry security responsibilities. Required skills and certifications per role are not named. | Q28: Extend the HRS plan Phase 1 role-description task to name required skills and certifications per role, and verify claimed certifications during screening.
A29: CC1.4-02 | B29: CC1.4 | C29: Background screening completed before access to production systems or customer data is granted. | D29: Security Officer | E29: Per hire | F29: Secureframe | G29: Enable the background check step in Secureframe > Personnel > Onboarding. Make the check a gate: do not provision AWS or repo access until it passes. | H29: Screening completion record | I29: Applies to contractors as well as employees. There is no exception for a fractional officer or a founder. | J29: 1 | K29: =IF(J29="","",IF(J29="N/A","Not applicable",CHOOSE(J29+1,"Gap","Documented","Implemented","Evidenced","Automated"))) -> Documented | N29: POL-AC-001 + STD-SCR-001 (to create) | O29: Yes | P29: HRS plan success metric requires 100% of new hires screened before Confidential or Restricted access. | Q29: Nothing outstanding. Make screening a hard gate in Secureframe onboarding so access cannot be provisioned until it passes.
A30: CC1.4-03 | B30: CC1.4 | C30: Onboarding checklist completed for every joiner: policies, training, screening, access, equipment. | D30: Security Officer | E30: Per hire | F30: Secureframe | G30: Secureframe Employee Onboarding sends the invite and tracks all four tasks in one view. Connect the HRIS so joiners import automatically and you never onboard from memory. | H30: Completed onboarding record | I30: Applies. One joiner a year still needs the checklist, and the checklist is what an auditor samples. | J30: 1 | K30: =IF(J30="","",IF(J30="N/A","Not applicable",CHOOSE(J30+1,"Gap","Documented","Implemented","Evidenced","Automated"))) -> Documented | N30: POL-HRS-001 | O30: Yes | P30: HRS plan Phase 2 builds the onboarding checklist covering screening, agreements, training and least-privilege access; completed checklists listed as evidence. | Q30: Nothing outstanding.
A31: CC1.4-04 | B31: CC1.4 | C31: Security awareness training completed at onboarding and at least annually. | D31: Security Officer | E31: On hire + annual | F31: Secureframe | G31: Secureframe's built-in training with auto-enrolment and annual reset. Add role-specific content for anyone touching customer AWS environments. | H31: Training completion report | I31: Applies. The CEO takes the training too. A completion rate of 100% across two people is a clean result. | J31: 1 | K31: =IF(J31="","",IF(J31="N/A","Not applicable",CHOOSE(J31+1,"Gap","Documented","Implemented","Evidenced","Automated"))) -> Documented | N31: POL-SAT-001 | O31: Yes | P31: SAT plan Phase 1 assigns onboarding training and sets the annual recurrence; completion reports listed as evidence. | Q31: Nothing outstanding.
A32: CC1.4-05 | B32: CC1.4 | C32: Remote working requirements — device standard, network, physical handling of screens and printouts — acknowledged. | D32: Security Officer | E32: On hire + annual | F32: Secureframe | G32: Do not create a separate acceptance. Put the home-working requirements inside an existing policy and let the same acknowledgment cover it. | H32: Acknowledgment register export | I32: Applies with more force here, not less. Everyone is remote, there is no office perimeter, and the home environment is the control boundary. | J32: 0 | K32: =IF(J32="","",IF(J32="N/A","Not applicable",CHOOSE(J32+1,"Gap","Documented","Implemented","Evidenced","Automated"))) -> Gap | N32: POL-COC-001 §12 + STD-EPT-001 | O32: Partial | P32: Acceptable Use plan documents the remote-work and BYOD permission process and the annual acknowledgment set. Its device enforcement task assumes Company-managed devices, which is not the model we chose. | Q32: Rewrite Acceptable Use plan Phase 1 task 3: replace enforcement on Company-managed devices with deployment of the read-only posture check on personal devices. As written it contradicts POL-COC-001 Section 5.
A33: CC1.4-06 | B33: CC1.4 | C33: Contractors meet the same screening, training and acknowledgment requirements as employees. | D33: Security Officer | E33: Per engagement | F33: Secureframe | G33: Assign contractors to the 'contractor' group in Secureframe and give that group the same policy and training set. Do not build a second workflow. | H33: Same records as employees | I33: Applies, and is the primary path at this size, since most of the team is engaged rather than employed. | J33: 0 | K33: =IF(J33="","",IF(J33="N/A","Not applicable",CHOOSE(J33+1,"Gap","Documented","Implemented","Evidenced","Automated"))) -> Gap | N33: POL-HRS-001 + POL-VM-001 | O33: No | P33: No plan states that contractors meet the same screening, training and acknowledgment standard as employees. | Q33: Add to HRS plan Phase 2: assign contractors to the same Secureframe group as employees so they inherit the same policy, training and screening set, and flow the requirement down in contractor agreements.
A34: CC1.5 | C34: Accountability for internal control | J34: =IFERROR(ROUND(AVERAGE(J35:J39),1),"") -> 0.8 | K34: =IF(COUNT(J35:J39)=0,IF(COUNTIF(J35:J39,"N/A")>0,"all n/a","not scored"),COUNTIF(J35:J39,0)&" gaps, "&COUNTIFS(J35:J39,"<3")&" below 3") -> 1 gaps, 5 below 3 | O34: 2 of 5
A35: CC1.5-01 | B35: CC1.5 | C35: Security responsibilities are communicated and accepted as a condition of employment or engagement. | D35: Security Officer | E35: On hire + annual | F35: Secureframe | G35: Covered by the same acceptance as CC1.1-02. One acknowledgment satisfies both criteria — do not run two. | H35: Acknowledgment register export | I35: Applies. Covered by the same acceptance as CC1.1-02 — do not run a second one. | J35: 1 | K35: =IF(J35="","",IF(J35="N/A","Not applicable",CHOOSE(J35+1,"Gap","Documented","Implemented","Evidenced","Automated"))) -> Documented | N35: POL-COC-001 §17 + POL-HRS-001 | O35: Yes | P35: HRS plan Phase 1 updates offer and engagement templates to include confidentiality, IP and policy-acceptance terms. | Q35: Nothing outstanding.
A36: CC1.5-02 | B36: CC1.5 | C36: Performance review includes control and security responsibilities. | D36: CEO | E36: Annual | F36: Word + GitHub | G36: A one-page annual review form in the governance repo. Do not buy a performance platform for this at current headcount. | H36: Completed review form | I36: The only other N/A candidate. If the CEO is the sole employee there is no review cycle to attach control responsibilities to. If anyone else is employed, it applies to them and N/A is not available. Decide, then record the reason. | J36: 0 | K36: =IF(J36="","",IF(J36="N/A","Not applicable",CHOOSE(J36+1,"Gap","Documented","Implemented","Evidenced","Automated"))) -> Gap | N36: POL-HRS-001 | O36: No | P36: Performance review appears in no plan. | Q36: Add to HRS plan Phase 2: a one-page annual review form that includes security and control responsibilities, and add completed forms to the evidence list. Do not buy a performance platform for this.
A37: CC1.5-03 | B37: CC1.5 | C37: Every control has a named owner and a defined operating frequency. | D37: Security Officer | E37: Quarterly | F37: Secureframe | G37: Secureframe > Controls: owner is a required field. Review unassigned controls at the quarterly report rather than before the audit. | H37: Control matrix export | I37: Applies. Twenty-seven controls still need named owners, and 'the CEO' is a valid owner for most of them. | J37: 1 | K37: =IF(J37="","",IF(J37="N/A","Not applicable",CHOOSE(J37+1,"Gap","Documented","Implemented","Evidenced","Automated"))) -> Documented | N37: POL-ISP-001 §8 → control matrix | O37: Partial | P37: ISP plan Phase 1 builds a compliance calendar with owners and due dates. A control matrix naming an owner and frequency per control is not required. | Q37: Add to ISP plan Phase 1: build the control matrix with an owner and operating frequency per control alongside the calendar. Secureframe makes owner a required field.
A38: CC1.5-04 | B38: CC1.5 | C38: Controls that do not operate on schedule become deficiencies, are tracked in the plan of action and escalated when overdue. | D38: Security Officer | E38: Quarterly | F38: Secureframe | G38: Failing Secureframe tests create tasks automatically. Route them to a Jira or Linear project via the task integration so overdue items surface without anyone checking. | H38: Plan of action + quarterly report | I38: Applies. Expect zero overdue items in the first quarter. Record the zero in the quarterly report. | J38: 1 | K38: =IF(J38="","",IF(J38="N/A","Not applicable",CHOOSE(J38+1,"Gap","Documented","Implemented","Evidenced","Automated"))) -> Documented | N38: POL-ISP-001 §8 + POL-RSK-001 §9 | O38: Yes | P38: ISP plan Phase 3 records gaps in a plan of action with owners and dates; escalation of overdue tasks is stated in the implementation approach. | Q38: Nothing outstanding.
A39: CC1.5-05 | B39: CC1.5 | C39: Security Officer documents the finding and recommends; CEO determines, documents and consistently applies the outcome. | D39: CEO | E39: As they occur | F39: GitHub Issues | G39: Same 'conduct' issue label as CC1.1-05. One process, one record type. | H39: Case record per event | I39: Applies. The process has to exist before it is needed. Expect a nil return and record it. | J39: 1 | K39: =IF(J39="","",IF(J39="N/A","Not applicable",CHOOSE(J39+1,"Gap","Documented","Implemented","Evidenced","Automated"))) -> Documented | N39: POL-COC-001 §18 + POL-HRS-001 | O39: Partial | P39: HRS plan Phase 2 defines the sanctions process reference with management. The split between who documents the finding and who decides the outcome is not stated. | Q39: Extend the HRS sanctions task to state the split: the Security Officer documents the finding and recommends; the CEO determines, documents and applies the outcome consistently.
A41: Scale | C41: 0 Gap · 1 Documented · 2 Implemented · 3 Evidenced · 4 Automated · N/A Not applicable. Full definitions on the Read Me tab. Leave blank until assessed — a blank is not a zero, and N/A is excluded from the score entirely.
A42: N/A rule | C42: An N/A with no rationale turns the rationale cell red. Every N/A must say why, and the same reason should appear in the Governance Log. Small headcount is a reason to document a limitation, not a reason to exclude a control — only CC1.2-05 and possibly CC1.5-02 qualify here.
A43: How to | C43: Use the outline buttons in the left margin (1 / 2, or the +/− next to each criterion) to collapse and expand. Level 1 shows the five criterion rows only; level 2 shows every control.
A45: Sources | C45: Column N names the document that should own each control. Column O records whether the requirement appears in the 20 implementation plans supplied in Plan.zip — 9 Yes, 10 Partial, 9 No. Column P quotes what those plans actually say, and column Q states what to add. Plan.zip contains implementation plans only: no Code of Conduct plan and no Conflict of Interest plan exist in the set, which is why CC1.1 scores worst.

Sheet CC2 Controls
A1: CC2 — Communication and Information
A2: 17 control activities across CC2.1–CC2.3. Same scale and same columns as the CC1 tab. Fill in the shaded columns only: Owner, Score and Next due.
A4: Ref | B4: Criterion | C4: Control activity | D4: Owner | E4: Frequency | F4: System of record | G4: How to automate it | H4: Evidence artifact | I4: Scoping note at this size | J4: Score | K4: Level | L4: Rationale if N/A | M4: Next due | N4: Owning policy or standard | O4: In the plans? | P4: What the implementation plans say | Q4: What to add to close it
A5: CC2.1 | C5: Relevant, quality information | J5: =IFERROR(ROUND(AVERAGE(J6:J10),1),"") -> 1 | K5: =IF(COUNT(J6:J10)=0,IF(COUNTIF(J6:J10,"N/A")>0,"all n/a","not scored"),COUNTIF(J6:J10,0)&" gaps, "&COUNTIFS(J6:J10,"<3")&" below 3") -> 0 gaps, 5 below 3 | O5: 5 of 5
A6: CC2.1-01 | B6: CC2.1 | C6: A System Security Plan describes the system boundary, environments of operation and implemented controls, and is reviewed at least annually. | D6: Security Officer | E6: Annual | F6: GitHub | G6: Keep it in the governance repo as markdown so changes are versioned. Regenerate the asset sections from Secureframe rather than retyping them. | H6: System Security Plan with version history | I6: Applies. At this size it is perhaps six pages. Its real job is to fix the audit boundary before the auditor fixes it for you. | J6: 1 | K6: =IF(J6="","",IF(J6="N/A","Not applicable",CHOOSE(J6+1,"Gap","Documented","Implemented","Evidenced","Automated"))) -> Documented | N6: POL-ISP-001 §8 | O6: Yes | P6: ISP plan Phase 2 task 3 drafts the system security plan; listed as an evidence artifact. | Q6: Nothing outstanding. Add an annual review to the ISP plan Operational Cadence.
A7: CC2.1-02 | B7: CC2.1 | C7: An asset inventory covers systems, SaaS, cloud resources and repositories, each with a named owner and its data classification. | D7: Security Officer | E7: Quarterly | F7: Secureframe | G7: Secureframe Asset Inventory populates from the AWS, GitHub and identity integrations. Review unassigned owners at the quarterly report rather than before the audit. | H7: Asset inventory export | I7: Applies. The inventory is what makes every other control provable, because it defines what “all systems” actually means. | J7: 1 | K7: =IF(J7="","",IF(J7="N/A","Not applicable",CHOOSE(J7+1,"Gap","Documented","Implemented","Evidenced","Automated"))) -> Documented | L7: Uddyan | N7: POL-AM-001 §5 + POL-AC-001 §15 | O7: Yes | P7: Asset Management plan Phase 1 task 1 stands up the inventory with an owner per asset; Access Control plan Phase 1 task 1 builds the system inventory. | Q7: Nothing outstanding.
A8: CC2.1-03 | B8: CC2.1 | C8: Information is classified and handled according to its sensitivity, and classifications are recorded against the assets that hold it. | D8: Security Officer | E8: Annual | F8: Secureframe | G8: Record the classification as an asset attribute so it travels with the inventory. Do not maintain a second spreadsheet. | H8: Classification scheme and repository inventory | I8: Applies. Client testing evidence is the highest classification you hold; make sure the scheme names it explicitly. | J8: 1 | K8: =IF(J8="","",IF(J8="N/A","Not applicable",CHOOSE(J8+1,"Gap","Documented","Implemented","Evidenced","Automated"))) -> Documented | N8: POL-DCL-001 §5, §6 | O8: Yes | P8: Data Classification plan Phase 1 publishes the scheme, classifies repositories and records classifications in the asset inventory. | Q8: Nothing outstanding.
A9: CC2.1-04 | B9: CC2.1 | C9: Logging and monitoring produce records complete and reliable enough to base control and incident decisions on. | D9: Security Officer | E9: Continuous | F9: AWS + Secureframe | G9: Enable cloud audit trails on every production account and identity provider logging; alert on any attempt to disable them. | H9: Log configuration evidence and retention settings | I9: Applies. For a testing firm this is also how you prove what you did and did not touch in a client environment. | J9: 1 | K9: =IF(J9="","",IF(J9="N/A","Not applicable",CHOOSE(J9+1,"Gap","Documented","Implemented","Evidenced","Automated"))) -> Documented | N9: POL-LOG-001 §6, §8 | O9: Yes | P9: Logging plan Phase 1 enables cloud audit trails and identity logging and verifies they cannot be disabled outside change management. | Q9: Nothing outstanding.
A10: CC2.1-05 | B10: CC2.1 | C10: Security objectives are set annually with defined metrics, baselined and measured against actual performance. | D10: CEO | E10: Annual | F10: This workbook | G10: Reuse the metrics you already have: control operating effectiveness, deficiencies open past date, training completion, vulnerability remediation time. | H10: Objectives and metrics with baseline values | I10: Applies. Four metrics is enough. Metrics nobody reviews are worse than none. | J10: 1 | K10: =IF(J10="","",IF(J10="N/A","Not applicable",CHOOSE(J10+1,"Gap","Documented","Implemented","Evidenced","Automated"))) -> Documented | N10: POL-ISP-001 §5 | O10: Yes | P10: ISP plan Phase 2 task 2 defines annual security objectives and metrics and baselines current values. | Q10: Nothing outstanding.
A11: CC2.2 | C11: Internal communication | J11: =IFERROR(ROUND(AVERAGE(J12:J17),1),"") -> 0.5 | K11: =IF(COUNT(J12:J17)=0,IF(COUNTIF(J12:J17,"N/A")>0,"all n/a","not scored"),COUNTIF(J12:J17,0)&" gaps, "&COUNTIFS(J12:J17,"<3")&" below 3") -> 3 gaps, 6 below 3 | O11: 4 of 6
A12: CC2.2-01 | B12: CC2.2 | C12: Policies are published to the policy repository and personnel are notified on issue and on material change. | D12: Security Officer | E12: On change | F12: GitHub + Secureframe | G12: Publish from the repo; push the approved PDF to Secureframe Policies, which notifies and chases automatically. | H12: Publication record and notification log | I12: Applies. A policy nobody was told about has not been communicated, however well it is written. | J12: 0 | K12: =IF(J12="","",IF(J12="N/A","Not applicable",CHOOSE(J12+1,"Gap","Documented","Implemented","Evidenced","Automated"))) -> Gap | N12: POL-ISP-001 §6 | O12: Yes | P12: ISP plan Phase 1 task 1 publishes the policy set to the repository and notifies all personnel. | Q12: Nothing outstanding.
A13: CC2.2-02 | B13: CC2.2 | C13: Security responsibilities are communicated in writing and acknowledged as a condition of employment or engagement. | D13: Security Officer | E13: On hire + annual | F13: Secureframe | G13: Same acknowledgement that satisfies CC1.1-02 and CC1.5-01. Do not run a third one. | H13: Acknowledgment register export | I13: Applies. One acceptance covers three criteria; keep it that way. | J13: 1 | K13: =IF(J13="","",IF(J13="N/A","Not applicable",CHOOSE(J13+1,"Gap","Documented","Implemented","Evidenced","Automated"))) -> Documented | N13: POL-COC-001 §17 + POL-HRS-001 | O13: Yes | P13: HRS plan Phase 1 task 2 puts policy-acceptance terms into offer and engagement templates. | Q13: Nothing outstanding.
A14: CC2.2-03 | B14: CC2.2 | C14: Security awareness training is delivered at onboarding and annually, supported by periodic awareness communications. | D14: Security Officer | E14: On hire + annual | F14: Secureframe | G14: Built-in training with auto-enrolment and annual reset; use the advisory channel for the periodic communications. | H14: Training completion report and awareness archive | I14: Applies. The awareness communications part is what turns a once-a-year tick into ongoing communication. | J14: 1 | K14: =IF(J14="","",IF(J14="N/A","Not applicable",CHOOSE(J14+1,"Gap","Documented","Implemented","Evidenced","Automated"))) -> Documented | N14: POL-SAT-001 §5, §11 | O14: Yes | P14: SAT plan Phase 1 and Phase 2 assign training, set the annual recurrence and establish the periodic awareness communication channel. | Q14: Nothing outstanding.
A15: CC2.2-04 | B15: CC2.2 | C15: Personnel report suspected security weaknesses and incidents through a published channel, and good-faith reporting is protected. | D15: Security Officer | E15: Continuous | F15: Google Workspace | G15: One monitored alias, briefed at onboarding and repeated in training. No form, no triage tree. | H15: Channel record and incident register entries | I15: Applies. Expect very few reports. Brief people that reporting early and being wrong is the outcome you want. | J15: 1 | K15: =IF(J15="","",IF(J15="N/A","Not applicable",CHOOSE(J15+1,"Gap","Documented","Implemented","Evidenced","Automated"))) -> Documented | N15: POL-IRP-001 §7 + POL-COC-001 §16 | O15: Yes | P15: Incident Response plan Phase 1 task 1 publishes the reporting channel and briefs personnel that immediate good-faith reporting is expected and protected. | Q15: Nothing outstanding.
A16: CC2.2-05 | B16: CC2.2 | C16: A written quarterly report goes to the Steering Committee covering control status, open deficiencies with owners and dates, and the security metrics. | D16: Security Officer | E16: Quarterly | F16: This workbook | G16: One page, generated from the control matrix and the plan of action. Put it on the compliance calendar so it cannot be forgotten. | H16: Quarterly report, four per year | I16: Applies. This is the single most sampled artifact in a Type II. Four reports in the file beats one long one. | J16: 0 | K16: =IF(J16="","",IF(J16="N/A","Not applicable",CHOOSE(J16+1,"Gap","Documented","Implemented","Evidenced","Automated"))) -> Gap | N16: POL-ISP-001 §8 | O16: Partial | P16: ISP plan Phase 3 task 2 presents program status, metrics and the plan of action to the Committee once. No quarterly cadence is established. | Q16: Add to ISP plan Operational Cadence: written report to the Steering Committee — quarterly, within 15 days of quarter end, covering control status, deficiencies and metrics.
A17: CC2.2-06 | B17: CC2.2 | C17: Concerns about the conduct of the Security Officer, or which a person prefers not to raise with the Security Officer, may be reported directly to the CEO. | D17: CEO | E17: Continuous | F17: Google Workspace | G17: A second alias routing only to the CEO. Name it in the Code of Conduct alongside the security channel so both appear in the same paragraph. | H17: Documented channel plus report log or nil return | I17: Applies, and matters more here than at a larger company: the Security Officer is a contractor, which is exactly the case the bypass exists for. | J17: 0 | K17: =IF(J17="","",IF(J17="N/A","Not applicable",CHOOSE(J17+1,"Gap","Documented","Implemented","Evidenced","Automated"))) -> Gap | N17: POL-ISP-001 §7 + POL-COC-001 §16 | O17: No | P17: No ethics or bypass channel appears in any of the 20 plans. Same gap as CC1.1-04. | Q17: Add to HRS plan Phase 1: create an ethics alias routing only to the CEO, name it in the Code of Conduct, and state the anti-retaliation commitment.
A18: CC2.3 | C18: External communication | J18: =IFERROR(ROUND(AVERAGE(J19:J24),1),"") -> 0.7 | K18: =IF(COUNT(J19:J24)=0,IF(COUNTIF(J19:J24,"N/A")>0,"all n/a","not scored"),COUNTIF(J19:J24,0)&" gaps, "&COUNTIFS(J19:J24,"<3")&" below 3") -> 2 gaps, 6 below 3 | O18: 1 of 6
A19: CC2.3-01 | B19: CC2.3 | C19: Security, availability and confidentiality commitments made to customers are recorded in the customer agreement or DPA, and reviewed annually against the controls actually in operation. | D19: CEO | E19: Annual | F19: Contracts + this workbook | G19: Keep a one-page commitments register listing each promise and the control that delivers it. Review it when the annual assessment is run. | H19: Commitments register with annual review note | I19: Applies, and it is the control that catches over-promising in a sales conversation before an auditor or a customer does. | J19: 0 | K19: =IF(J19="","",IF(J19="N/A","Not applicable",CHOOSE(J19+1,"Gap","Documented","Implemented","Evidenced","Automated"))) -> Gap | N19: POL-ISP-001 §9 + POL-VM-001 §12 | O19: No | P19: No plan records customer-facing security commitments or reviews them against controls in operation. | Q19: Add to ISP plan Phase 2: build the customer commitments register, and add an annual review of commitments against operating controls to the Operational Cadence.
A20: CC2.3-02 | B20: CC2.3 | C20: A monitored security contact address is published externally so third parties can report vulnerabilities, and reports are triaged under the Incident Response Policy. | D20: Security Officer | E20: Continuous | F20: Website + Google Workspace | G20: Publish on the website and add a security.txt file. Both are ten minutes of work and both are what a researcher looks for first. | H20: Published address, security.txt, triage records | I20: Applies with force for a security firm. Being hard to report a vulnerability to is a poor look in this particular market. | J20: 1 | K20: =IF(J20="","",IF(J20="N/A","Not applicable",CHOOSE(J20+1,"Gap","Documented","Implemented","Evidenced","Automated"))) -> Documented | N20: POL-ISP-001 §9 + POL-IRP-001 §7 | O20: Partial | P20: Incident Response plan Phase 1 task 1 publishes security@ and briefs personnel. External publication for third-party reporters is not stated. | Q20: Extend Incident Response plan Phase 1 task 1: publish the address externally on the website and in a security.txt file, and include externally reported vulnerabilities in the triage path.
A21: CC2.3-03 | B21: CC2.3 | C21: A current list of sub-processors and third parties that process customer data is maintained, and customers are notified of material changes. | D21: Security Officer | E21: On change | F21: Secureframe | G21: Derive it from the vendor inventory rather than maintaining a second list; publish the subset that processes customer data. | H21: Sub-processor list with change history | I21: Applies. Your Privacy Policy already promises this list on request, so the promise exists whether or not the list does. | J21: 1 | K21: =IF(J21="","",IF(J21="N/A","Not applicable",CHOOSE(J21+1,"Gap","Documented","Implemented","Evidenced","Automated"))) -> Documented | N21: POL-VM-001 §12 + POL-PRIV-001 (not in the library) | O21: Partial | P21: Vendor Management plan Phase 1 builds the vendor inventory with data shared per vendor. No customer-facing sub-processor list and no customer notification on change. | Q21: Add to Vendor Management plan Phase 2: derive and publish the sub-processor list from the vendor inventory, and define the customer notification step for material changes.
A22: CC2.3-04 | B22: CC2.3 | C22: Obligations to notify customers after a security incident, including triggers and timeframes, are defined and templated. | D22: CEO | E22: On incident | F22: Incident register | G22: Keep the notification matrix and letter templates with the playbooks so they are found under pressure, not searched for. | H22: Notification matrix and templates | I22: Applies. The 24-hour processor notification in the Privacy Policy needs to match whatever the matrix says. | J22: 1 | K22: =IF(J22="","",IF(J22="N/A","Not applicable",CHOOSE(J22+1,"Gap","Documented","Implemented","Evidenced","Automated"))) -> Documented | N22: POL-IRP-001 §11 + POL-PRIV-001 §16 (not in the library) | O22: Yes | P22: Incident Response plan Phase 2 task 2 maps customer and regulatory notification obligations and deadlines with counsel and templates the letters. | Q22: Nothing outstanding. Confirm the matrix matches the periods stated in POL-PRIV-001 Section 16.
A23: CC2.3-05 | B23: CC2.3 | C23: Security commitments to customers or prospective customers are reviewed by the Security Officer before they are made. | D23: Security Officer | E23: Per commitment | F23: Engagement intake | G23: One line in the engagement intake checklist. No workflow needed at this size. | H23: Reviewed questionnaire and proposal records | I23: Applies. In a two-person company the person answering the security questionnaire is often the person selling, which is precisely the risk. | J23: 0 | K23: =IF(J23="","",IF(J23="N/A","Not applicable",CHOOSE(J23+1,"Gap","Documented","Implemented","Evidenced","Automated"))) -> Gap | N23: POL-ISP-001 §9 | O23: No | P23: No plan requires review of security commitments before they are given to a customer or prospect. | Q23: Add to ISP plan Phase 2: add a Security Officer review step to the engagement intake checklist for every security questionnaire, proposal or contractual commitment.
A24: CC2.3-06 | B24: CC2.3 | C24: Vendors receive the Company's security requirements, and complementary user entity controls are communicated to customers. | D24: Security Officer | E24: On onboarding + annual | F24: Secureframe | G24: Vendor requirements go in the contract at intake. Put the customer-side controls in the report description and repeat them in onboarding material. | H24: Vendor contract clauses and stated user entity controls | I24: Applies. The user entity control half is routinely forgotten and is asked about directly in a SOC 2 report. | J24: 1 | K24: =IF(J24="","",IF(J24="N/A","Not applicable",CHOOSE(J24+1,"Gap","Documented","Implemented","Evidenced","Automated"))) -> Documented | N24: POL-VM-001 §6, §12 | O24: Partial | P24: Vendor Management plan Phase 2 task 3 requires Security Officer approval before data is shared and remediates contract gaps. Complementary user entity controls are not mentioned anywhere. | Q24: Add to Vendor Management plan Phase 2: define the complementary user entity controls customers must operate, and state where they are communicated.
A26: Scale | C26: 0 Gap · 1 Documented · 2 Implemented · 3 Evidenced · 4 Automated · N/A Not applicable. Full definitions on the Read Me tab. Leave blank until assessed — a blank is not a zero, and N/A is excluded from the score entirely.
A27: N/A rule | C27: An N/A with no rationale turns the rationale cell red. Every N/A must say why, and the same reason should appear in the Governance Log. Small headcount is a reason to document a limitation, not a reason to exclude a control — only CC1.2-05 and possibly CC1.5-02 qualify here.
A28: How to | C28: Use the outline buttons in the left margin (1 / 2, or the +/− next to each criterion) to collapse and expand. Level 1 shows the five criterion rows only; level 2 shows every control.
A30: Sources | C30: Columns N to Q assess the same 20 implementation plans in Plan.zip that were used for CC1. CC2 assessed 10 Yes, 4 Partial, 3 No. CC2.1 is fully covered because the plans are strong on information and inventory; CC2.3 is the weakest area in the whole set, because nothing in the plans addresses what the Company tells its customers.

Sheet CC3 Controls
A1: CC3 — Risk Assessment
A2: 20 control activities across CC3.1–CC3.4. Same scale and same columns as the CC1 and CC2 tabs, except that columns O to Q assess this tab against the approved policy library rather than the implementation plans, and are labelled accordingly. Scores were set from that policy review and are capped at 1 — a control written into an approved policy scores 1; moving to 2 means showing it operating.
A4: Ref | B4: Criterion | C4: Control activity | D4: Owner | E4: Frequency | F4: System of record | G4: How to automate it | H4: Evidence artifact | I4: Scoping note at this size | J4: Score | K4: Level | L4: Rationale if N/A | M4: Next due | N4: Owning policy or standard | O4: In the policies? | P4: What the policy set says | Q4: What to add to close it
A5: CC3.1 | C5: Objectives specified with sufficient clarity | J5: =IFERROR(ROUND(AVERAGE(J6:J10),1),"") -> 0.6 | K5: =IF(COUNT(J6:J10)=0,IF(COUNTIF(J6:J10,"N/A")>0,"all n/a","not scored"),COUNTIF(J6:J10,0)&" gaps, "&COUNTIFS(J6:J10,"<3")&" below 3") -> 2 gaps, 5 below 3 | O5: 2 of 5
A6: CC3.1-01 | B6: CC3.1 | C6: Security objectives are set annually, expressed in measurable terms, and approved by the Steering Committee. | D6: CEO | E6: Annual | F6: This workbook | G6: Reuse the four metrics POL-RSK-001 §17 already names — control operating effectiveness, incident trends, vulnerability remediation timeliness, training completion. Record the approved set in the Annual Assessment so objectives and assessment stay in one document. | H6: Approved objectives with baseline values | I6: Applies. Objectives have to be specific enough that a risk can be identified against each one. “Be secure” is not an objective; “no Confidential data leaves a managed repository” is. | J6: 1 | K6: =IF(J6="","",IF(J6="N/A","Not applicable",CHOOSE(J6+1,"Gap","Documented","Implemented","Evidenced","Automated"))) -> Documented | N6: POL-ISP-001 §5 + POL-RSK-001 §5, §17 | O6: Yes | P6: POL-RSK-001 §5 requires objectives set annually by the Steering Committee and expressed with sufficient clarity that risks to their achievement can be identified. §17 requires metrics reviewed against those objectives. POL-ISP-001 §5 states the same requirement and names the four metrics. | Q6: Nothing outstanding in policy. The gap is operational: this year’s objectives have not been set or baselined. Do it at the annual assessment and the control moves from 1 to 2.
A7: CC3.1-02 | B7: CC3.1 | C7: The system boundary, service commitments and system requirements are defined and used as the stated scope of the risk assessment. | D7: Security Officer | E7: Annual | F7: GitHub | G7: No new document. The risk assessment opens by referencing the System Security Plan boundary rather than restating it, so the two cannot drift apart. | H7: System Security Plan boundary section, cited by the risk assessment | I7: Applies. Same document as CC2.1-01. The risk assessment inherits its scope from the SSP, which means the annual SSP review and the annual risk assessment belong in the same sitting. | J7: 1 | K7: =IF(J7="","",IF(J7="N/A","Not applicable",CHOOSE(J7+1,"Gap","Documented","Implemented","Evidenced","Automated"))) -> Documented | N7: POL-ISP-001 §8 + POL-RSK-001 §2 | O7: Partial | P7: POL-ISP-001 requires a System Security Plan describing system boundaries, environments of operation and implemented controls. POL-RSK-001 §2 scopes risk to personnel, devices, AWS, AI and agentic systems, vendors, engagements and legal obligations. Neither states that the risk assessment scope is taken from the SSP boundary. | Q7: Add one clause to POL-RSK-001 §2: the scope of each assessment is the boundary defined in the System Security Plan as at the assessment date. Without it the two documents will describe different systems by year two.
A8: CC3.1-03 | B8: CC3.1 | C8: Legal, regulatory and contractual security obligations are recorded in a single register and reviewed annually. | D8: CEO | E8: Annual | F8: This workbook + contracts | G8: Extend the customer commitments register from CC2.3-01 with a source column rather than starting a second list. One page covers DPAs, client contract security schedules and breach notification duties. | H8: Obligations register with annual review note | I8: Applies. The list is short at this size, which is the point — it is what makes a risk relevant to this company rather than generic. An obligation you cannot name is one you cannot show you assessed. | J8: 0 | K8: =IF(J8="","",IF(J8="N/A","Not applicable",CHOOSE(J8+1,"Gap","Documented","Implemented","Evidenced","Automated"))) -> Gap | N8: POL-ISP-001 §9 + POL-COC-001 §15 (no register owner named) | O8: No | P8: No policy requires an obligations register. POL-RSK-001 §6 treats legal and regulatory change and client contractual commitments as inputs to risk identification; POL-COC-001 §10 requires personnel to comply with client obligations; POL-AI-001 records client AI obligations in the engagement file. Nothing consolidates them or requires an annual review. | Q8: Add a clause to POL-ISP-001 requiring a single obligations register with an annual review, owned by the CEO. Build it as a tab beside the commitments register — the two share a source and should not be maintained twice.
A9: CC3.1-04 | B9: CC3.1 | C9: A risk appetite statement defines which risks are accepted without treatment, which must be treated, and who may accept them. | D9: CEO | E9: Annual | F9: GitHub | G9: Already written. Configure the register so the treatment due-date bands at §9 are computed from the residual score rather than typed in by hand. | H9: POL-RSK-001 §9 treatment table and appetite statement | I9: Applies. Without a stated threshold every acceptance is an ad hoc judgement and an auditor cannot test whether they were applied consistently — which is the whole test. | J9: 1 | K9: =IF(J9="","",IF(J9="N/A","Not applicable",CHOOSE(J9+1,"Gap","Documented","Implemented","Evidenced","Automated"))) -> Documented | N9: POL-RSK-001 §9, §16 | O9: Yes | P9: POL-RSK-001 §9 sets a five-band treatment table with residual score ranges, required response, treatment due date and who may accept, and states the appetite: no risk shall remain untreated at a residual score of 12 or above. §16 requires written Committee acceptance with a review date no more than twelve months ahead. | Q9: Nothing outstanding in policy — this is the strongest row in CC3. One defect to fix at the next revision: §4 and §8 both cite “Section 8” for the risk appetite, which is at Section 9.
A10: CC3.1-05 | B10: CC3.1 | C10: Each objective is linked to the controls that deliver it, so a control failure traces to the objective it puts at risk. | D10: Security Officer | E10: Annual | F10: Secureframe | G10: Add an objective field to the control matrix built for CC1.5-03. One column of work, done once, and it is what makes the quarterly report readable by someone who is not the Security Officer. | H10: Control matrix showing the objective served by each control | I10: Applies. This is the link that turns the control matrix from a checklist into a risk instrument, and it is the cheapest row in CC3 to satisfy if the matrix is built with the field from the start. | J10: 0 | K10: =IF(J10="","",IF(J10="N/A","Not applicable",CHOOSE(J10+1,"Gap","Documented","Implemented","Evidenced","Automated"))) -> Gap | N10: POL-ISP-001 §8 → control matrix (link not yet required) | O10: No | P10: POL-RSK-001 §5 and §9 require the mapping from risk to control to be recorded in the register. No policy requires a mapping from objective to control, which is the direction CC3.1 tests. §17 comes closest by requiring metrics to be reviewed against objectives. | Q10: Extend the POL-RSK-001 §9 mapping clause: record the objective each control serves as well as the risk it treats. One field on the control matrix closes it.
A11: CC3.2 | C11: Identifies and analyzes risk | J11: =IFERROR(ROUND(AVERAGE(J12:J18),1),"") -> 1 | K11: =IF(COUNT(J12:J18)=0,IF(COUNTIF(J12:J18,"N/A")>0,"all n/a","not scored"),COUNTIF(J12:J18,0)&" gaps, "&COUNTIFS(J12:J18,"<3")&" below 3") -> 0 gaps, 7 below 3 | O11: 7 of 7
A12: CC3.2-01 | B12: CC3.2 | C12: A documented methodology defines the likelihood and impact scales, how they combine into a score, and the threshold at which a risk must be treated. | D12: Security Officer | E12: Annual review | F12: GitHub | G12: Already written. The work is to make the register compute the score and the treatment due date rather than accept typed values. | H12: POL-RSK-001 §7 to §9 scales, matrix and thresholds | I12: Applies. Two people can hold the whole risk picture in their heads, which is precisely why the scales must be written down — otherwise last year’s “high” and this year’s are not the same thing and the trend means nothing. | J12: 1 | K12: =IF(J12="","",IF(J12="N/A","Not applicable",CHOOSE(J12+1,"Gap","Documented","Implemented","Evidenced","Automated"))) -> Documented | N12: POL-RSK-001 §7, §8, §9 | O12: Yes | P12: POL-RSK-001 §7 defines 1–5 likelihood and impact scales with the score as their product, requires inherent and residual both recorded, and requires a written rationale per score. §8 adds a reachability and exploitability matrix setting a minimum likelihood, with CISA KEV entries floored at 4. §9 sets the treatment bands. | Q12: Nothing outstanding in policy, and §8 goes well beyond what CC3.2 requires. STD-RSK-001 is unnecessary — the scales are already in the policy and moving them now would only create a second source.
A13: CC3.2-02 | B13: CC3.2 | C13: A formal risk assessment is performed at least annually and repeated whenever a change trigger fires. | D13: Security Officer | E13: Annual + on trigger | F13: This workbook | G13: Put the annual run on the compliance calendar and the §12 trigger list in the engagement and vendor intake checklists, so the event-driven runs happen where the change originates rather than being remembered later. | H13: Dated risk assessment report per run | I13: Applies. One assessment a year is the floor. At this stage of the company the trigger-driven runs will outnumber the annual one, and those are the ones that demonstrate the process is live. | J13: 1 | K13: =IF(J13="","",IF(J13="N/A","Not applicable",CHOOSE(J13+1,"Gap","Documented","Implemented","Evidenced","Automated"))) -> Documented | N13: POL-RSK-001 §5, §12 | O13: Yes | P13: POL-RSK-001 §5 requires a full risk assessment at least annually with targeted reassessment on any significant change under §12. §18 makes proceeding with a significant change without that reassessment a serious violation. | Q13: Nothing outstanding in policy. No assessment has been run yet — the first run is what moves this from 1 to 2.
A14: CC3.2-03 | B14: CC3.2 | C14: A risk register records each risk with an owner, an inherent score, the treatment decision, a residual score and a review date. | D14: Security Officer | E14: Quarterly review | F14: Secureframe | G14: Secureframe Risk Register holds every §10 field natively. Review it at the quarterly report rather than before the audit, and never keep a second copy in a spreadsheet. | H14: Risk register export | I14: Applies. Inherent and residual both matter: residual alone hides how much the treatment is doing, and an auditor asks what would happen if the treatment stopped. | J14: 1 | K14: =IF(J14="","",IF(J14="N/A","Not applicable",CHOOSE(J14+1,"Gap","Documented","Implemented","Evidenced","Automated"))) -> Documented | N14: POL-RSK-001 §10 | O14: Yes | P14: POL-RSK-001 §10 specifies twelve required fields — identifier, threat, vulnerability and consequence, affected assets and data types, inherent score, existing controls, residual score, treatment, owner, agreed date, status and review date — requires accepted risks recorded alongside treated ones, and forbids deletion of entries. | Q14: Nothing outstanding in policy. Configure the register to the §10 field list before the first assessment, and seed the CC1.2 independence-limitation entry that CC1.2-03 requires.
A15: CC3.2-04 | B15: CC3.2 | C15: Risk identification covers the entity itself, its vendors and sub-processors, and the AI models and agentic components in the service. | D15: Security Officer | E15: Annual + on trigger | F15: Secureframe | G15: Run the identification pass in the three sweeps the policy already separates — §6 entity, §13 vendor, §14 AI — and record the ATLAS version referenced, as §14 requires. | H15: Risk assessment showing all three sweeps and the taxonomy version | I15: Applies with force. Agentic components fail in ways a conventional register does not anticipate — prompt injection, tool misuse, unbounded action, model supply chain. A register without them is incomplete for this company specifically, whatever it says about the rest. | J15: 1 | K15: =IF(J15="","",IF(J15="N/A","Not applicable",CHOOSE(J15+1,"Gap","Documented","Implemented","Evidenced","Automated"))) -> Documented | N15: POL-RSK-001 §6, §13, §14 | O15: Yes | P15: POL-RSK-001 §6 lists eight identification sources and requires size-related risks recorded explicitly. §13 covers vendors and subservice organisations including concentration risk. §14 requires AI risk enumerated against MITRE ATLAS supported by the OWASP LLM Top 10 and the NIST Generative AI Profile, names nine ATLAS tactic categories, requires every untrusted-content path to a tool-enabled model enumerated, and requires categories assessed as not applicable to be recorded rather than omitted. | Q15: Nothing outstanding, and §14 is materially stronger than most CC3.2 coverage at any company size. Carry the ATLAS version into the assessment template so it is captured by default.
A16: CC3.2-05 | B16: CC3.2 | C16: Every risk above the treatment threshold has a treatment plan with a named owner and a target date, and progress is reported quarterly. | D16: Security Officer | E16: Quarterly | F16: Secureframe | G16: Same plan of action already used for CC1.5-04. One list, not a second risk-only tracker, routed to the same task project so overdue treatments surface on their own. | H16: Treatment plans and quarterly progress record | I16: Applies. The failure mode at this size is not identifying risks — it is that treatments have no date and drift for a year. The date is the control. | J16: 1 | K16: =IF(J16="","",IF(J16="N/A","Not applicable",CHOOSE(J16+1,"Gap","Documented","Implemented","Evidenced","Automated"))) -> Documented | N16: POL-RSK-001 §9, §17 | O16: Yes | P16: POL-RSK-001 §9 requires every treatment to carry a named owner, an agreed date and a defined completion test, with treatments open beyond their agreed date escalated to the CEO. §17 requires quarterly reporting to the Steering Committee on the risk profile, movements, overdue treatments and newly accepted risks. | Q16: Nothing outstanding in policy. The completion test per treatment is the clause most often skipped in practice — make it a required field so it cannot be.
A17: CC3.2-06 | B17: CC3.2 | C17: Risk acceptances are approved by the CEO and recorded with the rationale, the decider, the date and an expiry. | D17: CEO | E17: As they occur | F17: This workbook | G17: Use the Governance Log tab with type = ‘Risk acceptance’, and put the register entry identifier in the Reference column so the log and the register point at each other. | H17: Governance Log entry linked to the register | I17: Applies. An acceptance without an expiry becomes permanent by default, which is how a temporary decision turns into an unexplained exclusion two audits later. | J17: 1 | K17: =IF(J17="","",IF(J17="N/A","Not applicable",CHOOSE(J17+1,"Gap","Documented","Implemented","Evidenced","Automated"))) -> Documented | N17: POL-RSK-001 §16 | O17: Yes | P17: POL-RSK-001 §16 requires written Steering Committee acceptance for residual scores of 12 or above, recording the rationale and the compensating controls, with a review date no more than twelve months ahead. Policy exceptions are recorded as accepted risks so exceptions and risks sit in one place, and acceptance is forbidden where it would breach a legal or client obligation. | Q17: Nothing outstanding in policy. Below score 12 the Security Officer accepts under §9 — log those too, or the Governance Log will show only the escalated minority.
A18: CC3.2-07 | B18: CC3.2 | C18: Vendors and sub-processors are risk-assessed before onboarding and reassessed annually where they process customer data. | D18: Security Officer | E18: On onboarding + annual | F18: Secureframe | G18: Vendor risk rating as an attribute of the vendor inventory, with reassessment set on the critical subset only. Do not run a full questionnaire against a vendor that holds no customer data. | H18: Vendor risk ratings and reassessment records | I18: Applies. The inventory records what is shared with a vendor; the assessment records what happens if that vendor fails. They are different artifacts and the second one is the control. | J18: 1 | K18: =IF(J18="","",IF(J18="N/A","Not applicable",CHOOSE(J18+1,"Gap","Documented","Implemented","Evidenced","Automated"))) -> Documented | N18: POL-RSK-001 §13 + POL-VM-001 §5, §7 | O18: Yes | P18: POL-RSK-001 §13 requires assessment under POL-VM-001 before Confidential or Restricted information is shared, criticality and data-sensitivity rating, annual review of the AWS assurance report with complementary user entity controls confirmed, concentration risk recorded and reassessed annually, and reassessment on renewal, material service change or vendor incident. POL-VM-001 adds provider deprecation and model retirement notices as reassessment triggers. | Q18: Nothing outstanding in policy. The annual AWS assurance review at §13 is a dated task with no calendar entry yet — attach it to the annual risk assessment event.
A19: CC3.3 | C19: Considers the potential for fraud | J19: =IFERROR(ROUND(AVERAGE(J20:J23),1),"") -> 1 | K19: =IF(COUNT(J20:J23)=0,IF(COUNTIF(J20:J23,"N/A")>0,"all n/a","not scored"),COUNTIF(J20:J23,0)&" gaps, "&COUNTIFS(J20:J23,"<3")&" below 3") -> 0 gaps, 4 below 3 | O19: 3 of 4
A20: CC3.3-01 | B20: CC3.3 | C20: The annual risk assessment includes a fraud section covering fraudulent reporting, misappropriation of assets, corruption, and management override of controls. | D20: CEO | E20: Annual | F20: Word + GitHub | G20: A section of the same risk assessment, not a separate exercise. The four company-specific fraud risks at §11 are already written — lift them into the template as standing headings. | H20: Fraud section of the risk assessment | I20: Applies, and cannot be marked N/A on the grounds that the company is small. Small headcount is the condition under which fraud risk is highest, because segregation is limited and one person can complete a transaction end to end. | J20: 1 | K20: =IF(J20="","",IF(J20="N/A","Not applicable",CHOOSE(J20+1,"Gap","Documented","Implemented","Evidenced","Automated"))) -> Documented | N20: POL-RSK-001 §11 + POL-COC-001 §5, §13 | O20: Yes | P20: POL-RSK-001 §11 requires fraud considered explicitly, including misappropriation of assets, falsification of records and management override, and names four company-specific risks: alteration or suppression of assessment findings to satisfy a client or preserve revenue, falsification of timesheets, invoices or expenses, misrepresentation of qualifications or work performed, and misuse of privileged access to client systems. POL-COC-001 forbids altering, omitting or overstating findings. | Q20: Nothing outstanding in policy. Corruption and bribery is the one heading not named explicitly — add a line at §11 if any client is government or government-adjacent.
A21: CC3.3-02 | B21: CC3.3 | C21: Insider misuse of privileged access — including standing access held inside customer environments — is assessed explicitly as a fraud risk. | D21: Security Officer | E21: Annual | F21: Secureframe | G21: Tie it to the logging already required for CC2.1-04: the assessment names the risk and the logs are the detective control. Name the log source in the register entry so the pairing is visible. | H21: Register entry naming the detective control | I21: Applies with force, and this is the row most likely to be missed. Standing access to client environments is the single largest fraud exposure this company has, and it appears on no conventional small-company fraud checklist. | J21: 1 | K21: =IF(J21="","",IF(J21="N/A","Not applicable",CHOOSE(J21+1,"Gap","Documented","Implemented","Evidenced","Automated"))) -> Documented | N21: POL-RSK-001 §11 + POL-AC-001 §9, §14 + POL-LOG-001 §12 | O21: Yes | P21: POL-RSK-001 §11 names misuse of privileged access to client systems for personal or competitive advantage as a company-specific fraud risk, and lists logging of privileged access among the compensating controls for management override. §14 separately forbids agentic systems holding standing privileged access to production or client environments. | Q21: Nothing outstanding in policy. Confirm the logging required by POL-LOG-001 actually reaches access exercised inside a client tenant — that is usually the client’s log source rather than the Company’s, and it is where this control fails in practice.
A22: CC3.3-03 | B22: CC3.3 | C22: The potential for management override of controls is assessed, and the compensating controls are documented given a single-member Steering Committee. | D22: CEO | E22: Annual | F22: Word + GitHub | G22: Use the same Annual Assessment that already carries the CC1.2 independence limitation and the CC1.3-05 segregation conclusion. One document, one signature, three related limitations stated together. | H22: Management override section of the Annual Assessment | I22: Applies, and is the hardest row in CC3 at this size, because the person who could override the controls is the person signing the assessment. Say that plainly and name what compensates. A stated limitation is defensible; silence is not. | J22: 1 | K22: =IF(J22="","",IF(J22="N/A","Not applicable",CHOOSE(J22+1,"Gap","Documented","Implemented","Evidenced","Automated"))) -> Documented | N22: POL-RSK-001 §11 + POL-ISP-001 §8 → FRM-CE-001 | O22: Yes | P22: POL-RSK-001 §11 treats management override as a standing risk because the Company’s size prevents full segregation, and names three compensating controls: CEO review of the Security Officer’s control assessments, second review of assessment deliverables, and logging of privileged access. §17 requires self-assessments not performed solely by the control operator, and where size prevents that, review and signature by the CEO. | Q22: Nothing outstanding in policy, but state the residual weakness in the assessment: two of the three compensating controls are performed by the CEO, who is the person the override risk concerns. Immutable logging and the external auditor are what actually compensate — say so.
A23: CC3.3-04 | B23: CC3.3 | C23: Suspected fraud is handled under the conduct process, and a nil return is recorded annually where there has been none. | D23: CEO | E23: As they occur + annual | F23: GitHub Issues | G23: Same ‘conduct’ issue label as CC1.1-05 and CC1.5-05. One process, one record type, three criteria satisfied. Never handle these in email. | H23: Case record per event, or annual nil return | I23: Applies. Expect a nil return in year one and record it affirmatively. An empty file and an unperformed process are indistinguishable to an auditor. | J23: 1 | K23: =IF(J23="","",IF(J23="N/A","Not applicable",CHOOSE(J23+1,"Gap","Documented","Implemented","Evidenced","Automated"))) -> Documented | N23: POL-RSK-001 §11, §18 + POL-COC-001 §16, §18 | O23: Partial | P23: POL-RSK-001 §11 points to POL-COC-001 for ethical expectations, disclosure duties and non-retaliation, and §18 requires disciplinary decisions documented by the Security Officer and applied consistently. §6 allows personnel to raise a risk without attribution and prohibits retaliation. No policy requires a nil return where no case arose. | Q23: Add the nil return to POL-RSK-001 §17 alongside the quarterly report: where no fraud or conduct case arose in the period, record that fact. One line, and it is the difference between an unperformed control and a clean year.
A24: CC3.4 | C24: Identifies and assesses significant change | J24: =IFERROR(ROUND(AVERAGE(J25:J28),1),"") -> 1 | K24: =IF(COUNT(J25:J28)=0,IF(COUNTIF(J25:J28,"N/A")>0,"all n/a","not scored"),COUNTIF(J25:J28,0)&" gaps, "&COUNTIFS(J25:J28,"<3")&" below 3") -> 0 gaps, 4 below 3 | O24: 2 of 4
A25: CC3.4-01 | B25: CC3.4 | C25: A defined list states what obliges a risk reassessment: new product or model, new customer segment, new vendor or sub-processor, new jurisdiction, infrastructure change, material headcount change, regulatory change. | D25: Security Officer | E25: Annual review of the list | F25: GitHub | G25: The list exists at §12. Repeat it as one line in the engagement intake checklist and the vendor intake form, so the trigger is met where the change actually originates. | H25: POL-RSK-001 §12 trigger list, restated at intake | I25: Applies. At this stage of the company almost everything is a change, so the value of the list is not completeness — it is that reassessment stops being a judgement call made under time pressure. | J25: 1 | K25: =IF(J25="","",IF(J25="N/A","Not applicable",CHOOSE(J25+1,"Gap","Documented","Implemented","Evidenced","Automated"))) -> Documented | N25: POL-RSK-001 §12 | O25: Yes | P25: POL-RSK-001 §12 lists seven significant-change triggers: a client engagement involving PHI, special category data or production access to a client environment; a new AWS Region, account or service class, or material network or identity change; a new AI service, model provider or hosting arrangement, or a grant of tool access to an agentic system; a new vendor or subprocessor handling Confidential or Restricted data; a material headcount or responsibility change, or departure of privileged personnel; a change in law or a new client security commitment; and a significant or repeat incident or control failure. | Q25: Nothing outstanding in policy — the list is more specific than the one this row was drafted against. The gap is that it appears nowhere in intake, which is where a trigger is actually encountered.
A26: CC3.4-02 | B26: CC3.4 | C26: When a trigger fires the risk assessment is refreshed and the change is approved before it goes live. | D26: Security Officer | E26: On trigger | F26: GitHub Issues | G26: One issue in the governance repo per trigger, closed by the updated register entry. Most changes will take ten minutes; the record is what proves the process runs. | H26: Trigger record closed by the updated register entry | I26: Applies. Most triggers will conclude “assessed, no new risk”. Record that outcome — it is the evidence the trigger process operates, and it is the only thing distinguishing a live process from a dormant one. | J26: 1 | K26: =IF(J26="","",IF(J26="N/A","Not applicable",CHOOSE(J26+1,"Gap","Documented","Implemented","Evidenced","Automated"))) -> Documented | N26: POL-RSK-001 §12, §18 + POL-CM-001 §5, §12 | O26: Yes | P26: POL-RSK-001 §12 requires reassessment before the change takes effect, or immediately afterwards where the change is unplanned. §18 makes proceeding without that reassessment, and concealment of a known risk, serious violations. | Q26: Nothing outstanding in policy. Record the “assessed, no new risk” outcome as well as the ones that change the register, or the evidence will show only the exceptional cases.
A27: CC3.4-03 | B27: CC3.4 | C27: Changes to the system boundary are reflected in the System Security Plan and the asset inventory. | D27: Security Officer | E27: On change | F27: GitHub + Secureframe | G27: Make the SSP update part of closing the trigger issue, and regenerate the asset sections from Secureframe rather than editing them by hand. | H27: SSP version history and asset inventory export | I27: Applies. A boundary that has drifted from the SSP is the first thing an auditor finds, because every other control is scoped from that document. | J27: 1 | K27: =IF(J27="","",IF(J27="N/A","Not applicable",CHOOSE(J27+1,"Gap","Documented","Implemented","Evidenced","Automated"))) -> Documented | N27: POL-ISP-001 §8 + POL-AM-001 §5 + POL-RSK-001 §6 | O27: Partial | P27: POL-ISP-001 requires a System Security Plan describing boundaries and environments. POL-AM-001 requires a current inventory with owner, classification and source system, and POL-RSK-001 §6 requires an inventory sufficient to support identification, covering AWS accounts and Regions, the SaaS estate, AI services and enrolled endpoints. No policy requires either artifact to be updated when a §12 trigger moves the boundary. | Q27: Add to POL-RSK-001 §12: closing a trigger includes updating the System Security Plan and the asset inventory where the boundary moved. Both artifacts exist; nothing currently obliges them to keep up.
A28: CC3.4-04 | B28: CC3.4 | C28: External change — the threat landscape, applicable regulation and AI-specific developments — is monitored and reviewed at least annually. | D28: Security Officer | E28: Annual + continuous | F28: This workbook | G28: Two or three named sources, read as they publish, reviewed formally at the annual assessment and noted in the quarterly report. Do not buy a threat intelligence feed at this size. | H28: Environmental review note in the Annual Assessment | I28: Applies. The lightweight version is legitimate: name the sources actually read and record what changed as a result. An unsourced claim to “monitor the landscape” is not evidence of anything. | J28: 1 | K28: =IF(J28="","",IF(J28="N/A","Not applicable",CHOOSE(J28+1,"Gap","Documented","Implemented","Evidenced","Automated"))) -> Documented | N28: POL-RSK-001 §6, §17 + POL-VM-001 §7 + POL-AI-001 §19 | O28: Partial | P28: POL-RSK-001 §6 treats legal and regulatory change as an identification source and §17 requires review on material change to the risk profile. POL-VM-001 requires provider deprecation notices, model retirement schedules and material terms changes to be monitored. POL-AI-001 states the EU AI Act is monitored for applicability. No policy names who monitors the threat landscape, from which sources, or on what cadence. | Q28: Add a clause to POL-RSK-001 §17: the Security Officer names the sources monitored — CISA KEV is already relied on at §8 — and records at the annual assessment what changed and what it altered in the register. Monitoring that names no source cannot be evidenced.
A30: Scale | C30: 0 Gap · 1 Documented · 2 Implemented · 3 Evidenced · 4 Automated · N/A Not applicable. Full definitions on the Read Me tab. Scores on this tab were set from the approved policy library and are therefore capped at 1: a control written into an approved policy scores 1, and moving to 2 requires showing it operating. Eighteen rows score 1 and two score 0. Adjust any row where you hold operating evidence a policy review could not see.
A31: N/A rule | C31: An N/A with no rationale turns the rationale cell red. Nothing in CC3 is safely N/A. CC3.3 in particular is the criterion most often excluded on the grounds of size, and that is backwards — limited segregation is what makes fraud risk higher at two people, not lower. POL-RSK-001 §11 already takes the correct position by treating management override as a standing risk with named compensating controls.
A32: How to | C32: Use the outline buttons in the left margin (1 / 2, or the +/− next to each criterion) to collapse and expand. Level 1 shows the four criterion rows only; level 2 shows every control.
A34: Sources | C34: Column N names the document and section that owns each control, verified against the approved policy library supplied in Polcies.zip — 22 policies and 5 standards, all v1.0, approved 23 July 2026 and signed by the CEO and the Security Officer. Columns O to Q assess this tab against that policy library rather than against the 20 implementation plans used on the CC1 and CC2 tabs, because the plans were not supplied; the column headers are labelled accordingly so the two bases are never confused. The result is 14 Yes, 4 Partial and 2 No. POL-RSK-001 is unusually strong for a company this size — Section 8 on exploitability and reachability, and Section 14 on AI and agentic risk, both go beyond what CC3.2 requires. The two No rows are the obligations register (CC3.1-03) and the objective-to-control link (CC3.1-05), neither of which any policy currently owns. Supply Plan.zip and the same 20 rows can be assessed against the plans on the CC1 and CC2 basis.

Sheet CC4 Controls
A1: CC4 — Monitoring Activities
A2: 13 control activities across CC4.1–CC4.2. Same scale and same columns as the CC1 and CC2 tabs, except that columns O to Q assess this tab against the approved policy library rather than the implementation plans, and are labelled accordingly. Scores were set from that policy review and are capped at 1 — a control written into an approved policy scores 1; moving to 2 means showing it operating.
A4: Ref | B4: Criterion | C4: Control activity | D4: Owner | E4: Frequency | F4: System of record | G4: How to automate it | H4: Evidence artifact | I4: Scoping note at this size | J4: Score | K4: Level | L4: Rationale if N/A | M4: Next due | N4: Owning policy or standard | O4: In the policies? | P4: What the policy set says | Q4: What to add to close it
A5: CC4.1 | C5: Ongoing and separate evaluations | J5: =IFERROR(ROUND(AVERAGE(J6:J12),1),"") -> 1 | K5: =IF(COUNT(J6:J12)=0,IF(COUNTIF(J6:J12,"N/A")>0,"all n/a","not scored"),COUNTIF(J6:J12,0)&" gaps, "&COUNTIFS(J6:J12,"<3")&" below 3") -> 0 gaps, 7 below 3 | O5: 7 of 7
A6: CC4.1-01 | B6: CC4.1 | C6: A control self-assessment covering every in-scope control is performed at least annually, is not performed solely by the person who operates the control, and is reviewed and signed by the CEO. | D6: Security Officer | E6: Annual | F6: Word + GitHub | G6: Same Annual Control Environment Assessment that carries CC1.2-04, CC1.3-05 and CC3.3-03. One document, one signature, one evidence artifact serving four criteria — do not split it. | H6: Signed annual control self-assessment | I6: Applies. This is the separate evaluation an auditor looks for first. At two people the independence requirement cannot be met literally, which is exactly why POL-ISP-001 §8 substitutes CEO signature — use that wording rather than inventing your own. | J6: 1 | K6: =IF(J6="","",IF(J6="N/A","Not applicable",CHOOSE(J6+1,"Gap","Documented","Implemented","Evidenced","Automated"))) -> Documented | N6: POL-ISP-001 §8 + POL-RSK-001 §17 | O6: Yes | P6: POL-ISP-001 §8 requires the security program assessed at least annually through internal control self-assessment and, where contractually required, independent examination; states that self-assessments shall not be performed solely by the control operator; and where size prevents an independent assessor, requires the completed assessment reviewed and signed by the CEO. POL-RSK-001 §17 repeats the requirement and adds that results update residual risk scores. | Q6: Nothing outstanding in policy. The first assessment has not been run — that is what moves this from 1 to 2.
A7: CC4.1-02 | B7: CC4.1 | C7: Quarterly access reviews are performed across the systems in the audit boundary, producing a complete population and a recorded decision per entitlement, reconciled against reviews due. | D7: Security Officer | E7: Quarterly | F7: Secureframe | G7: Drive the population from the identity provider and cloud accounts rather than a manual list, and export the reconciliation with the review. The reconciliation is the part auditors sample and the part most often missing. | H7: Quarterly access review records with reviewer, entitlement, decision and reconciliation | I7: Applies. POL-AC-001 §12 states the trap plainly — a review is only a control if it produces a complete population and a decision per entitlement. A screenshot of a user list is not a review. | J7: 1 | K7: =IF(J7="","",IF(J7="N/A","Not applicable",CHOOSE(J7+1,"Gap","Documented","Implemented","Evidenced","Automated"))) -> Documented | N7: POL-AC-001 §12, §15 | O7: Yes | P7: POL-AC-001 §12 requires quarterly reviews across cloud accounts, code repositories, identity provider administration, production data stores and finance systems; requires reviewer, entitlement, decision and date recorded and reconciled to reviews due; requires the reviewer not to be the person whose access is under review; requires removals evidenced as removed rather than merely decided; and brings privileged, non-human and external access into the same record. §15 lists the resulting evidence. | Q7: Nothing outstanding in policy. Note the tension with headcount: §12 forbids self-review, and at two people some entitlements have no independent reviewer. Record that limitation in the review itself rather than leaving it implicit.
A8: CC4.1-03 | B8: CC4.1 | C8: Vulnerability scanning runs at least monthly on production infrastructure and continuously on code dependencies, supported by an annual penetration test, with remediation verified before closure. | D8: Security Officer | E8: Monthly + annual | F8: AWS + CI/CD | G8: Scanning in the pipeline and on a schedule, findings routed to the same task project as failing Secureframe tests so the deficiency queue stays single. | H8: Scan records per period, finding population, rescan verification, annual penetration test report | I8: Applies with force for a testing firm. Being found to have an unscanned estate is a commercial problem here, not only an audit one. | J8: 1 | K8: =IF(J8="","",IF(J8="N/A","Not applicable",CHOOSE(J8+1,"Gap","Documented","Implemented","Evidenced","Automated"))) -> Documented | N8: POL-VPM-001 §5, §13 | O8: Yes | P8: POL-VPM-001 §5 requires monthly automated scanning of production infrastructure, continuous dependency scanning through the pipeline, cloud configuration monitored against secure baselines with misconfigurations treated as vulnerabilities, and monitoring of vendor advisories and threat intelligence including actively exploited vulnerabilities. §13 requires scan records for every period, the finding population with severity and closure date, evidence that remediation was verified by rescan, and the annual penetration test report with evidence findings were remediated or accepted. | Q8: Nothing outstanding in policy. §13 also requires scanning and patch coverage reconciled against the asset inventory — that reconciliation is what proves the scan covered everything, and it needs the CC2.1-02 inventory to exist first.
A9: CC4.1-04 | B9: CC4.1 | C9: Alert dispositions are reviewed at least monthly for production, recording the date, reviewer, period covered and conclusion; logging and alerting coverage is reviewed at least annually and after material change. | D9: Security Officer | E9: Monthly + annual | F9: AWS + Secureframe | G9: A recurring calendar item that produces a short dated note, not a report. The note is the evidence; the absence of one is the finding. | H9: Monthly alert disposition review notes and annual coverage review | I9: Applies. This is the cheapest CC4.1 control to operate and the one most likely to be skipped in a quiet month. Record the quiet months — a nil disposition review is still a performed control. | J9: 1 | K9: =IF(J9="","",IF(J9="N/A","Not applicable",CHOOSE(J9+1,"Gap","Documented","Implemented","Evidenced","Automated"))) -> Documented | N9: POL-LOG-001 §8, §12 | O9: Yes | P9: POL-LOG-001 §8 requires automated alerts for repeated authentication failures, privilege escalation, disabling of security controls or logging, anomalous administrative activity and tool detections, prompt triage with escalation to incident response, and annual review of logging and alerting coverage with pipeline failures detected and remediated. §12 requires monthly review of alert dispositions recording date, reviewer, period covered and conclusion. | Q9: Nothing outstanding in policy. Wire the alert on disabling of logging first — it is the one alert that protects every other control on this tab.
A10: CC4.1-05 | B10: CC4.1 | C10: The change population is reviewed at least quarterly for changes lacking an approver, self-approved changes, direct production modifications and emergency change frequency, and the review is recorded. | D10: Security Officer | E10: Quarterly | F10: GitHub | G10: Query the merge history rather than reading it. Four counts, one dated note, filed with the quarterly report. | H10: Quarterly change population review record | I10: Applies. At this size self-approved changes will not be zero, and the honest number is more defensible than a review that reports none. Record the count and the compensating control. | J10: 1 | K10: =IF(J10="","",IF(J10="N/A","Not applicable",CHOOSE(J10+1,"Gap","Documented","Implemented","Evidenced","Automated"))) -> Documented | N10: POL-CM-001 §8, §12 | O10: Yes | P10: POL-CM-001 §12 requires the Security Officer to review the change population at least quarterly for changes lacking an approver, self-approved changes, direct production modifications and emergency change frequency, and to record the review; deficiencies found go to the deficiency log and are reported to the Steering Committee. §8 requires security-relevant configuration changes logged and reviewed, with unauthorised changes treated as security events. | Q10: Nothing outstanding in policy. The review depends on branch protection being enforced (Setup step 7) — without it the population cannot distinguish approved from unapproved.
A11: CC4.1-06 | B11: CC4.1 | C11: At least one continuity exercise a year uses a realistic scenario, and every test records the objective, the result, the recovery objectives actually achieved and the deficiencies found. | D11: Security Officer | E11: Annual | F11: GitHub | G11: A tabletop is sufficient at this size. Write the record as you run it; reconstructing it afterwards is what makes it unconvincing. | H11: Test record with objective, result, RTO and RPO achieved, deficiencies | I11: Applies. POL-BCP-001 §13 names the right scenarios for this company, including unavailability of the Security Officer during an active incident — which at two people is the scenario that matters most. | J11: 1 | K11: =IF(J11="","",IF(J11="N/A","Not applicable",CHOOSE(J11+1,"Gap","Documented","Implemented","Evidenced","Automated"))) -> Documented | N11: POL-BCP-001 §13, §15 | O11: Yes | P11: POL-BCP-001 §13 requires at least one realistic exercise a year, names candidate scenarios including loss of an AWS Region, identity provider compromise, ransomware on an engagement repository and unavailability of the Security Officer, requires objective, result, RTO and RPO achieved and deficiencies recorded, and states that a test finding nothing shall be scrutinised before it is accepted. §15 requires reporting to the Committee at least annually and treats a missed test as a deficiency escalated to the CEO. | Q11: Nothing outstanding in policy. Note that §13 routes continuity deficiencies to the risk register while POL-ISP-001 §8 routes deficiencies to a plan of action — see CC4.2-03, which is where that divergence has to be resolved.
A12: CC4.1-07 | B12: CC4.1 | C12: Independent evaluations are obtained where contractually required, and subservice organisation assurance reports are reviewed annually with complementary user entity controls confirmed. | D12: CEO | E12: Annual | F12: This workbook | G12: Diarise the AWS report against the annual risk assessment. Reviewing it means recording which user entity controls fall to the Company and confirming each is operating — not filing the PDF. | H12: Reviewed assurance report with user entity controls confirmed and gaps in the register | I12: Applies. The complementary user entity controls half is routinely skipped, and it is asked about directly. This is the same omission flagged at CC2.3-06. | J12: 1 | K12: =IF(J12="","",IF(J12="N/A","Not applicable",CHOOSE(J12+1,"Gap","Documented","Implemented","Evidenced","Automated"))) -> Documented | N12: POL-ISP-001 §8 + POL-RSK-001 §13 | O12: Yes | P12: POL-ISP-001 §8 provides for independent examinations such as SOC 2 audits where contractually required. POL-RSK-001 §13 names AWS as the principal subservice organisation, requires its assurance reporting reviewed at least annually, complementary user entity controls confirmed, and gaps recorded in the risk register. | Q12: Nothing outstanding in policy. The AWS review has no calendar entry — it now sits on the annual risk assessment row.
A13: CC4.2 | C13: Evaluates and communicates deficiencies | J13: =IFERROR(ROUND(AVERAGE(J14:J19),1),"") -> 1 | K13: =IF(COUNT(J14:J19)=0,IF(COUNTIF(J14:J19,"N/A")>0,"all n/a","not scored"),COUNTIF(J14:J19,0)&" gaps, "&COUNTIFS(J14:J19,"<3")&" below 3") -> 0 gaps, 6 below 3 | O13: 2 of 6
A14: CC4.2-01 | B14: CC4.2 | C14: Deficiencies are recorded with an owner, a severity and a remediation date, and tracked to closure. | D14: Security Officer | E14: Continuous | F14: Secureframe | G14: Failing Secureframe tests create tasks automatically; route them to the same Jira or Linear project as everything else so one queue holds every deficiency. | H14: Plan of action with owner, severity, date and closure | I14: Applies. One queue, not one per source. The moment there are three deficiency lists nobody can answer how many are open. | J14: 1 | K14: =IF(J14="","",IF(J14="N/A","Not applicable",CHOOSE(J14+1,"Gap","Documented","Implemented","Evidenced","Automated"))) -> Documented | N14: POL-ISP-001 §8 | O14: Yes | P14: POL-ISP-001 §8 requires identified deficiencies recorded in a plan of action with assigned owners and remediation dates, tracked to closure by the Security Officer, and assigned a severity. | Q14: Nothing outstanding in policy. Stand the plan of action up before the first evaluation runs, or the first findings will land in email.
A15: CC4.2-02 | B15: CC4.2 | C15: Deficiencies are reported in writing to the Steering Committee at least quarterly, with those open beyond their agreed date escalated in that report. | D15: Security Officer | E15: Quarterly | F15: This workbook | G15: One section of the quarterly report that already satisfies CC2.2-05. Generate the overdue list from the task project rather than reading it. | H15: Quarterly report with deficiency status and escalations | I15: Applies. Expect zero overdue items in the first quarter and record the zero. An auditor cannot distinguish an empty escalation section from an unperformed report. | J15: 1 | K15: =IF(J15="","",IF(J15="N/A","Not applicable",CHOOSE(J15+1,"Gap","Documented","Implemented","Evidenced","Automated"))) -> Documented | N15: POL-ISP-001 §8 + POL-VPM-001 §13 + POL-CM-001 §12 | O15: Yes | P15: POL-ISP-001 §8 requires deficiencies assigned a severity and reported in writing to the Steering Committee at least quarterly, with items open beyond their remediation date escalated in that report. POL-VPM-001 §13 requires service level performance reported quarterly with repeated breaches escalated as a deficiency. POL-CM-001 §12 requires change review deficiencies reported to the Committee. | Q15: Nothing outstanding in policy. Three policies each require a quarterly report to the same body — merge them into the single CC2.2-05 report rather than producing three.
A16: CC4.2-03 | B16: CC4.2 | C16: Deficiencies from every evaluation source — self-assessment, access review, scanning, penetration test, change review, continuity test, incident and vendor assessment — are consolidated in a single log. | D16: Security Officer | E16: Continuous | F16: Secureframe | G16: One destination, chosen now. Every policy that generates a deficiency should reference that destination by name rather than describing its own. | H16: Single deficiency log covering all evaluation sources | I16: Applies, and this is the weakest row in CC4. The policy set currently names three different destinations for a deficiency, which means the population an auditor asks for cannot be produced from any one of them. | J16: 1 | K16: =IF(J16="","",IF(J16="N/A","Not applicable",CHOOSE(J16+1,"Gap","Documented","Implemented","Evidenced","Automated"))) -> Documented | N16: POL-ISP-001 §8 (plan of action) · POL-CM-001 §12 (deficiency log) · POL-BCP-001 §13 (risk register) | O16: Partial | P16: Three policies route deficiencies to three different places: POL-ISP-001 §8 to a plan of action, POL-CM-001 §12 to a deficiency log, and POL-BCP-001 §13 to the risk register with an owner and remediation date. POL-VPM-001 §13 keeps its own finding population. No policy states that these are the same artifact or reconciles them. | Q16: Pick one destination and amend the other three policies to name it. The plan of action at POL-ISP-001 §8 is the natural choice because it is already the CC1.5-04 artifact. Until this is resolved, the deficiency population cannot be produced on request.
A17: CC4.2-04 | B17: CC4.2 | C17: Corrective action is verified as effective before a deficiency is closed, not merely reported as done. | D17: Security Officer | E17: Continuous | F17: Secureframe | G17: Make verification a required field on closure. For vulnerabilities the rescan is automatic; for everything else it is a named test recorded by the person closing. | H17: Closure records showing the verification performed | I17: Applies. Closure without verification is the most common finding in a second-year Type II, because year one closes on assertion and year two samples it. | J17: 1 | K17: =IF(J17="","",IF(J17="N/A","Not applicable",CHOOSE(J17+1,"Gap","Documented","Implemented","Evidenced","Automated"))) -> Documented | N17: POL-VPM-001 §13 + POL-RSK-001 §9 | O17: Partial | P17: POL-VPM-001 §13 requires evidence that remediation was verified by rescan or equivalent validation, and POL-RSK-001 §9 requires every treatment to have a defined completion test. Neither extends to deficiencies from self-assessment, access review, change review or continuity testing, and POL-ISP-001 §8 requires only that deficiencies be tracked to closure. | Q17: Extend POL-ISP-001 §8: a deficiency is closed only when the corrective action has been verified, and the verification is recorded. The rule exists in two policies already — generalise it rather than writing a third.
A18: CC4.2-05 | B18: CC4.2 | C18: Deficiency trends and repeat findings are evaluated, and a recurring deficiency is escalated rather than closed again. | D18: Security Officer | E18: Quarterly | F18: This workbook | G18: Two counts in the quarterly report: deficiencies opened this quarter, and how many were previously closed. The second number is the one that matters. | H18: Trend and repeat-finding section of the quarterly report | I18: Applies. A control that fails twice is a design problem, not an operating slip, and treating it as the latter is how a Type II qualification happens. | J18: 1 | K18: =IF(J18="","",IF(J18="N/A","Not applicable",CHOOSE(J18+1,"Gap","Documented","Implemented","Evidenced","Automated"))) -> Documented | N18: POL-VPM-001 §13 + POL-CM-001 §12 | O18: Partial | P18: POL-VPM-001 §13 requires repeated service level breaches escalated as a deficiency, and POL-CM-001 §12 requires emergency change frequency reviewed quarterly. No policy requires deficiency trends or repeat findings to be evaluated across sources. | Q18: Add to POL-ISP-001 §8: the quarterly report identifies deficiencies previously closed and reopened, and a repeat deficiency is escalated as a design concern rather than reworked.
A19: CC4.2-06 | B19: CC4.2 | C19: Failure to perform a scheduled evaluation on time is itself recorded as a deficiency and escalated. | D19: Security Officer | E19: Quarterly | F19: Secureframe | G19: The compliance calendar produces the due dates; the plan of action receives anything not done by them. No human comparison step. | H19: Deficiency record for any missed evaluation | I19: Applies. This is what stops a monitoring programme from quietly stopping. At this size a missed month is likely, and recording it is a far better position than a gap nobody explains at audit. | J19: 1 | K19: =IF(J19="","",IF(J19="N/A","Not applicable",CHOOSE(J19+1,"Gap","Documented","Implemented","Evidenced","Automated"))) -> Documented | N19: POL-BCP-001 §15 + POL-ISP-001 §8 | O19: Partial | P19: POL-BCP-001 §15 requires failure to complete a scheduled test on time recorded as a deficiency and escalated to the CEO. No equivalent exists for the self-assessment, access reviews, scanning, alert disposition review or change review, and POL-ISP-001 §8 is silent on missed evaluations. | Q19: Generalise the POL-BCP-001 §15 rule into POL-ISP-001 §8: failure to perform any scheduled evaluation by its due date is a deficiency, recorded and escalated in the quarterly report.
A21: Scale | C21: 0 Gap · 1 Documented · 2 Implemented · 3 Evidenced · 4 Automated · N/A Not applicable. Full definitions on the Read Me tab. Scores on this tab were set from the approved policy library and are therefore capped at 1: a control written into an approved policy scores 1, and moving to 2 requires showing it operating. All thirteen rows score 1 — CC4 is the best-documented criterion in the workbook, and none of it has run yet.
A22: N/A rule | C22: An N/A with no rationale turns the rationale cell red. Nothing in CC4 is safely N/A. The independence requirements at POL-ISP-001 §8 and POL-AC-001 §12 cannot be met literally at two people, but both policies already supply the substitute — CEO review and signature — so the correct treatment is a documented limitation, not an exclusion.
A23: How to | C23: Use the outline buttons in the left margin (1 / 2, or the +/− next to each criterion) to collapse and expand. Level 1 shows the two criterion rows only; level 2 shows every control.
A25: Sources | C25: Column N names the document and section that owns each control, verified against the approved policy library in Polcies.zip. Columns O to Q assess this tab against that library rather than the implementation plans, on the same basis as CC3. The result is 9 Yes, 4 Partial, 0 No — CC4.1 is fully covered and unusually specific, with POL-AC-001 §12, POL-VPM-001 §5 and §13, POL-LOG-001 §12, POL-CM-001 §12 and POL-BCP-001 §13 each defining a distinct evaluation with its own evidence. Every Partial sits in CC4.2 and every one of them has the same root cause: the policies define excellent individual evaluations but do not converge on a single deficiency population, a single closure test, or a rule for a missed evaluation. CC4.2-03 is the row to fix first — until deficiencies land in one place, the population an auditor asks for cannot be produced.

Sheet CC5 Controls
A1: CC5 — Control Activities
A2: 12 control activities across CC5.1–CC5.3. Same scale and same columns as the CC1 and CC2 tabs, except that columns O to Q assess this tab against the approved policy library rather than the implementation plans, and are labelled accordingly. Scores were set from that policy review and are capped at 1 — a control written into an approved policy scores 1; moving to 2 means showing it operating.
A4: Ref | B4: Criterion | C4: Control activity | D4: Owner | E4: Frequency | F4: System of record | G4: How to automate it | H4: Evidence artifact | I4: Scoping note at this size | J4: Score | K4: Level | L4: Rationale if N/A | M4: Next due | N4: Owning policy or standard | O4: In the policies? | P4: What the policy set says | Q4: What to add to close it
A5: CC5.1 | C5: Selects and develops control activities | J5: =IFERROR(ROUND(AVERAGE(J6:J9),1),"") -> 1 | K5: =IF(COUNT(J6:J9)=0,IF(COUNTIF(J6:J9,"N/A")>0,"all n/a","not scored"),COUNTIF(J6:J9,0)&" gaps, "&COUNTIFS(J6:J9,"<3")&" below 3") -> 0 gaps, 4 below 3 | O5: 3 of 4
A6: CC5.1-01 | B6: CC5.1 | C6: Controls are selected to treat identified risks, and the mapping from risk to control is recorded so that every control can be traced to the risk it exists to address. | D6: Security Officer | E6: Annual + on trigger | F6: Secureframe | G6: The mapping is a field on the risk register entry, not a separate document. Populate it as risks are recorded rather than reconstructing it before an audit. | H6: Risk register showing the control recorded against each risk | I6: Applies. This is the criterion that stops the control set becoming a checklist. At this size the mapping is short, and its value is that it shows why each control is operated at all. | J6: 1 | K6: =IF(J6="","",IF(J6="N/A","Not applicable",CHOOSE(J6+1,"Gap","Documented","Implemented","Evidenced","Automated"))) -> Documented | N6: POL-RSK-001 §5, §9 + POL-ISP-001 §6 | O6: Yes | P6: POL-RSK-001 §5 states the Company shall not adopt a control solely because a framework lists it, requires controls selected to treat identified risks, and requires the risk-to-control mapping recorded. §9 repeats that where a control is selected to treat a risk it is recorded in the register against that risk. POL-ISP-001 §6 states control activities are selected and deployed in response to risks identified in the risk assessment. | Q6: Nothing outstanding in policy. The mapping cannot be populated until the first risk assessment runs, so this row moves with CC3.2-02.
A7: CC5.1-02 | B7: CC5.1 | C7: Control selection considers the level at which a risk arises and combines preventive and detective activity rather than relying on one type. | D7: Security Officer | E7: Annual | F7: Secureframe | G7: Record the control type on the matrix alongside the owner and frequency. One field, and it makes a detection-only area visible at a glance. | H7: Control matrix showing control type per control | I7: Applies. The failure mode at this size is a programme that is almost entirely detective, because detection is cheaper to buy. Naming the type is what makes that visible before an auditor names it. | J7: 1 | K7: =IF(J7="","",IF(J7="N/A","Not applicable",CHOOSE(J7+1,"Gap","Documented","Implemented","Evidenced","Automated"))) -> Documented | N7: POL-RSK-001 §9 (treatment options) + POL-ISP-001 §6 | O7: Partial | P7: POL-RSK-001 §9 defines the treatment options as mitigate, transfer, avoid or accept, and requires the selected control recorded. Neither §9 nor POL-ISP-001 §6 requires the mix of preventive and detective activity to be considered, or the control type to be recorded. | Q7: Add a control-type field to the control matrix and one line to POL-ISP-001 §6: control selection considers whether the activity prevents or detects, and an area covered only by detection is recorded as such.
A8: CC5.1-03 | B8: CC5.1 | C8: Controls are not adopted solely because a framework lists them, and a control that treats no identified risk is challenged rather than retained. | D8: Security Officer | E8: Annual | F8: Secureframe | G8: Review at the annual assessment: any control on the matrix with no risk mapped to it is either mapped or retired. | H8: Annual review note on unmapped controls | I8: Applies, and is unusually well stated in the policy. At this headcount an unnecessary control is not neutral — it consumes the capacity the necessary ones need. | J8: 1 | K8: =IF(J8="","",IF(J8="N/A","Not applicable",CHOOSE(J8+1,"Gap","Documented","Implemented","Evidenced","Automated"))) -> Documented | N8: POL-RSK-001 §5 | O8: Yes | P8: POL-RSK-001 §5 states directly that the Company shall not adopt a control solely because a framework lists it, that controls shall be selected to treat identified risks, and that the mapping from risk to control shall be recorded. | Q8: Nothing outstanding in policy. Make the unmapped-control check part of the annual assessment so the rule is tested rather than merely stated.
A9: CC5.1-04 | B9: CC5.1 | C9: Every Trust Services Criterion in the declared scope has at least one owning document and a named control owner. | D9: Security Officer | E9: Annual | F9: GitHub | G9: Annex A of POL-ISP-001 is the register. Regenerate it from the control matrix rather than maintaining both by hand. | H9: POL-ISP-001 Annex A criteria mapping | I9: Applies. This is the single artifact that answers “which document owns this criterion”, and it is the first thing an auditor asks for after the system description. | J9: 1 | K9: =IF(J9="","",IF(J9="N/A","Not applicable",CHOOSE(J9+1,"Gap","Documented","Implemented","Evidenced","Automated"))) -> Documented | N9: POL-ISP-001 §6, §13 (Annex A) | O9: Yes | P9: POL-ISP-001 §6 states that Annex A records each subordinate policy and standard with its identifier, version, approval date and owner, and that Annex A maps each Trust Services Criterion in the declared scope to the document that owns it and to the named control owner, with every criterion in scope having at least one owning document. | Q9: Nothing outstanding in policy, but Annex A must be reconciled against this workbook: the CC1 and CC2 tabs still reference POL-COI-001 and POL-PRIV-001, and neither is in the approved library.
A10: CC5.2 | C10: General controls over technology | J10: =IFERROR(ROUND(AVERAGE(J11:J14),1),"") -> 1 | K10: =IF(COUNT(J11:J14)=0,IF(COUNTIF(J11:J14,"N/A")>0,"all n/a","not scored"),COUNTIF(J11:J14,0)&" gaps, "&COUNTIFS(J11:J14,"<3")&" below 3") -> 0 gaps, 4 below 3 | O10: 4 of 4
A11: CC5.2-01 | B11: CC5.2 | C11: Production and non-production workloads are separated at the cloud account boundary, with permission sets granting only the entitlements a role requires in each. | D11: Security Officer | E11: Continuous | F11: AWS | G11: Account separation is structural — once established it holds without maintenance, which is why it is the highest-value general control at this size. | H11: Account structure and permission set exports | I11: Applies. Separating by account rather than by tag or subnet means audit scope can be established structurally, which is a large saving every year thereafter. | J11: 1 | K11: =IF(J11="","",IF(J11="N/A","Not applicable",CHOOSE(J11+1,"Gap","Documented","Implemented","Evidenced","Automated"))) -> Documented | N11: POL-AC-001 §10 + POL-NET-001 §5 + POL-AM-001 §8 | O11: Yes | P11: POL-AC-001 §10 requires production and non-production workloads in separate cloud accounts with permission sets granting only the entitlements a role requires. POL-NET-001 §5 requires the separation at the account boundary rather than merely by subnet or tag, so that scope can be established structurally. | Q11: Nothing outstanding in policy. Confirm the separation exists in the account structure as built — the policy is unambiguous and the finding, if any, will be an implementation one.
A12: CC5.2-02 | B12: CC5.2 | C12: Segregation of duties is applied where practicable and, where the Company's size prevents it, compensating controls are documented rather than the requirement being dropped. | D12: Security Officer | E12: Annual | F12: Word + GitHub | G12: One section of the Annual Assessment, shared with CC1.3-05. Name the conflicting duties held by one person and what compensates for each. | H12: Segregation of duties section of the Annual Assessment | I12: Applies. Three policies state the same rule, which is the right answer at this size: the honest conclusion is that segregation is limited, and the compensating controls are what make that defensible. | J12: 1 | K12: =IF(J12="","",IF(J12="N/A","Not applicable",CHOOSE(J12+1,"Gap","Documented","Implemented","Evidenced","Automated"))) -> Documented | N12: POL-AC-001 §5 + POL-CM-001 §6 + POL-ISP-001 §7 | O12: Yes | P12: POL-AC-001 §5 requires segregation applied where practicable, with compensating controls such as independent review and enhanced logging documented where size prevents it. POL-CM-001 §6 requires code and configuration changes reviewed by a person other than the author wherever staffing permits, with a stated alternative where independent review is not possible. POL-ISP-001 §7 states the rule at programme level. | Q12: Nothing outstanding in policy. The assessment at CC1.3-05 has not been performed — that is the gap, and it closes all three policy references at once.
A13: CC5.2-03 | B13: CC5.2 | C13: Infrastructure and network configuration are defined as code, held in version control and applied through the pipeline, with drift detected and remediated. | D13: Security Officer | E13: Continuous | F13: GitHub + AWS | G13: Console edits are the exception path, not the normal one. Reconcile emergency changes back into code within one business day as the policy requires. | H13: Repository history and drift detection findings | I13: Applies. Configuration as code is what makes the CC4.1-05 change review possible at all — a console-edited estate has no population to review. | J13: 1 | K13: =IF(J13="","",IF(J13="N/A","Not applicable",CHOOSE(J13+1,"Gap","Documented","Implemented","Evidenced","Automated"))) -> Documented | N13: POL-NET-001 §12 + POL-CM-001 §5, §8 | O13: Yes | P13: POL-NET-001 §12 requires network configuration defined as code, held in version control and applied through the pipeline rather than by console edit; proposed changes scanned for misconfiguration before application; emergency changes reconciled back into code within one business day; and drift between deployed network and definition detected and remediated. POL-CM-001 §8 requires security-relevant configuration changes logged and reviewed, with unauthorised changes treated as security events. | Q13: Nothing outstanding in policy. Enable drift detection at the same time as the pipeline, or the reconciliation requirement has nothing to compare against.
A14: CC5.2-04 | B14: CC5.2 | C14: Access to deploy changes to production is restricted, and security requirements are applied through the development lifecycle rather than added at release. | D14: Security Officer | E14: Continuous | F14: GitHub | G14: Branch protection and deployment permissions do this structurally. Setup step 7 is the prerequisite for both this row and CC4.1-05. | H14: Deployment permission export and branch protection settings | I14: Applies. At two people the deploy permission and the review requirement are the same control expressed twice — get branch protection right and both hold. | J14: 1 | K14: =IF(J14="","",IF(J14="N/A","Not applicable",CHOOSE(J14+1,"Gap","Documented","Implemented","Evidenced","Automated"))) -> Documented | N14: POL-CM-001 §6 + POL-SDLC-001 §4, §5, §6 | O14: Yes | P14: POL-CM-001 §6 requires access to deploy changes to production restricted in accordance with the Access Control Policy, and review by a person other than the author wherever staffing permits. POL-SDLC-001 covers secure design and coding, development environments and source control, and security testing and release. | Q14: Nothing outstanding in policy. Branch protection on private repositories requires GitHub Team — that dependency is already flagged at Setup step 7 and gates this row.
A15: CC5.3 | C15: Deploys through policies and procedures | J15: =IFERROR(ROUND(AVERAGE(J16:J19),1),"") -> 1 | K15: =IF(COUNT(J16:J19)=0,IF(COUNTIF(J16:J19,"N/A")>0,"all n/a","not scored"),COUNTIF(J16:J19,0)&" gaps, "&COUNTIFS(J16:J19,"<3")&" below 3") -> 0 gaps, 4 below 3 | O15: 3 of 4
A16: CC5.3-01 | B16: CC5.3 | C16: Policies are approved by the Steering Committee, reviewed at least annually, and communicated to personnel on hire and on material change. | D16: CEO | E16: Annual | F16: GitHub + Secureframe | G16: Approval is the merged pull request; communication is the Secureframe assignment. Neither needs a separate workflow. | H16: Approved policy set with approval dates and acknowledgment register | I16: Applies, and is already largely satisfied: the whole library carries an approval date of 23 July 2026 and signatures from the CEO and the Security Officer. | J16: 1 | K16: =IF(J16="","",IF(J16="N/A","Not applicable",CHOOSE(J16+1,"Gap","Documented","Implemented","Evidenced","Automated"))) -> Documented | N16: POL-ISP-001 §6 | O16: Yes | P16: POL-ISP-001 §6 requires all security policies and standards approved by the Information Security Steering Committee, reviewed at least annually, and communicated to personnel upon hire and upon material change, with Annex A recording identifier, title, current version, approval date and owner for each. | Q16: Nothing outstanding in policy. The next review date across the library is 23 July 2027 — put it on the compliance calendar now rather than discovering it has passed.
A17: CC5.3-02 | B17: CC5.3 | C17: Standards and procedures that implement the policies are maintained and kept current with the Company's technology and threat environment. | D17: Security Officer | E17: Annual | F17: GitHub | G17: Keep the changeable detail in standards so a configuration change does not require reissuing and re-approving a policy. | H17: Current standards set with version history | I17: Applies. The library already uses this pattern well — the cloud, cryptography, endpoint and logging standards carry the settings, and the policies carry the outcomes. | J17: 1 | K17: =IF(J17="","",IF(J17="N/A","Not applicable",CHOOSE(J17+1,"Gap","Documented","Implemented","Evidenced","Automated"))) -> Documented | N17: POL-ISP-001 §6 + STD-CLD-001, STD-CRY-001, STD-EPT-001, STD-LOG-001 | O17: Yes | P17: POL-ISP-001 §6 states that standards and procedures implementing these policies are maintained by the Security Officer and kept current with the Company's technology and threat environment. Four standards exist covering cloud platform, cryptography, endpoint and logging. | Q17: Nothing outstanding in policy. STD-SCR-001 for screening tiers is named in the CC1 rows and does not exist — it is the one standard the pattern is missing.
A18: CC5.3-03 | B18: CC5.3 | C18: Exceptions are requested in writing, approved before taking effect, documented, risk-assessed, time-bound and reviewed at least annually, and are recorded as accepted risks. | D18: CEO | E18: As they occur | F18: This workbook | G18: Governance Log type ‘Exception’, cross-referenced to the risk register entry. One decision, two records that point at each other. | H18: Exception records with compensating control and expiry | I18: Applies. The expiry date is the control. An exception without one becomes the standing configuration, which is how a temporary decision turns into an unexplained deviation two audits later. | J18: 1 | K18: =IF(J18="","",IF(J18="N/A","Not applicable",CHOOSE(J18+1,"Gap","Documented","Implemented","Evidenced","Automated"))) -> Documented | N18: POL-ISP-001 §11 + POL-RSK-001 §16 | O18: Yes | P18: POL-ISP-001 §11 requires exceptions requested in writing to the Security Officer and approved by the Steering Committee before taking effect, documented, risk-assessed, time-bound and reviewed at least annually. POL-RSK-001 §16 requires any exception granted under any Company policy recorded as an accepted risk in the register so that exceptions and risks are visible in one place. | Q18: Nothing outstanding in policy. Several policies name specific exceptions they expect — shared accounts, static credentials, removable media, unrestricted egress — so seed the register with those categories rather than waiting for the first request.
A19: CC5.3-04 | B19: CC5.3 | C19: Control activities are performed by competent personnel with defined responsibility, within the defined frequency, and deviations are corrected. | D19: Security Officer | E19: Quarterly | F19: Secureframe | G19: The control matrix carries the owner and frequency; the compliance calendar carries the due date; the plan of action receives anything not done by it. | H19: Control matrix with owner and frequency, and deficiency records for missed performances | I19: Applies. This is the row that connects CC5 to CC4: a control that exists and is owned but was not performed on schedule has failed, and the failure has to be visible. | J19: 1 | K19: =IF(J19="","",IF(J19="N/A","Not applicable",CHOOSE(J19+1,"Gap","Documented","Implemented","Evidenced","Automated"))) -> Documented | N19: POL-ISP-001 §7, §8 | O19: Partial | P19: POL-ISP-001 §7 requires security responsibilities defined for all roles, communicated in writing and acknowledged, with competencies defined per role and screening proportionate to them. §8 requires identified deficiencies recorded and tracked to closure. No policy states that failure to perform a control within its defined frequency is itself a deficiency. | Q19: Same amendment as CC4.2-06: generalise the POL-BCP-001 §15 rule into POL-ISP-001 §8 so that failure to perform any scheduled control activity by its due date is a deficiency, recorded and escalated in the quarterly report.
A21: Scale | C21: 0 Gap · 1 Documented · 2 Implemented · 3 Evidenced · 4 Automated · N/A Not applicable. Full definitions on the Read Me tab. Scores on this tab were set from the approved policy library and are therefore capped at 1: a control written into an approved policy scores 1, and moving to 2 requires showing it operating. All twelve rows score 1.
A22: N/A rule | C22: An N/A with no rationale turns the rationale cell red. Nothing in CC5 is safely N/A. CC5.2 segregation of duties is the row most often excluded on grounds of size, and all three owning policies already give the correct treatment — apply it where practicable, document the compensating control where it is not, and never drop the requirement.
A23: How to | C23: Use the outline buttons in the left margin (1 / 2, or the +/− next to each criterion) to collapse and expand. Level 1 shows the three criterion rows only; level 2 shows every control.
A25: Sources | C25: Column N names the document and section that owns each control, verified against the approved policy library in Polcies.zip. Columns O to Q assess this tab against that library rather than the implementation plans, on the same basis as CC3 and CC4. The result is 10 Yes and 2 Partial. CC5 is largely a restatement of decisions taken elsewhere — the risk-to-control mapping from POL-RSK-001 §5 and §9, the account separation from POL-AC-001 §10 and POL-NET-001 §5, the policy framework and exception process from POL-ISP-001 §6 and §11 — which is why it scores well without adding new work. The two Partials are the absence of a preventive-versus-detective consideration in control selection (CC5.1-02) and the absence of a rule that a control not performed on schedule is a deficiency (CC5.3-04, the same amendment CC4.2-06 needs). One reconciliation is outstanding: POL-ISP-001 Annex A must match this workbook, and it currently cannot, because the CC1 and CC2 tabs reference POL-COI-001 and POL-PRIV-001 and neither document exists in the library.

Sheet CC6 Controls
A1: CC6 — Logical and Physical Access Controls
A2: 32 control activities across CC6.1–CC6.8, the largest criterion in the Common Criteria. Same scale and same columns as the CC1 and CC2 tabs, except that columns O to Q assess this tab against the approved policy library rather than the implementation plans, and are labelled accordingly. Scores were set from that policy review and are capped at 1 — a control written into an approved policy scores 1; moving to 2 means showing it operating.
A4: Ref | B4: Criterion | C4: Control activity | D4: Owner | E4: Frequency | F4: System of record | G4: How to automate it | H4: Evidence artifact | I4: Scoping note at this size | J4: Score | K4: Level | L4: Rationale if N/A | M4: Next due | N4: Owning policy or standard | O4: In the policies? | P4: What the policy set says | Q4: What to add to close it
A5: CC6.1 | C5: Logical access security measures | J5: =IFERROR(ROUND(AVERAGE(J6:J10),1),"") -> 1 | K5: =IF(COUNT(J6:J10)=0,IF(COUNTIF(J6:J10,"N/A")>0,"all n/a","not scored"),COUNTIF(J6:J10,0)&" gaps, "&COUNTIFS(J6:J10,"<3")&" below 3") -> 0 gaps, 5 below 3 | O5: 5 of 5
